Workbook
Name AG: Premissas!$K$111
Name DOIS: Legenda!$F$53:$F$64
Name PG: Legenda!$C$41:$C$45
Name Salário_Base: 'Recursos Humanos'!#REF!
Name Salário_Base: 'Recursos Humanos'!#REF!
Name Salário_Base: 'Recursos Humanos'!#REF!
Name Salário_Base: 'Recursos Humanos'!#REF!
Name Salário_Base: '[1]Recursos Humanos'!#REF!
Name Salário_Base: 'Recursos Humanos'!#REF!
Name UM: Legenda!$F$53:$F$56

Sheet Legenda
C6: Legenda Básica:
B8: 0 | C8: Indica células para Input de Informações
B10: 0 | C10: Indica células de Output de Informações (não alterar conteúdo em nenhuma hipótese)
B12: 0 | C12: Indica células de Output de Informações. Permite inserir dados para usar como um "atalho" ou simulação, porém a fórmula contida será perdida.
C15: Principais Índices Financeiros:
E16: Franqueado | J16: Franqueadora
C17: Taxa de Retorno (IRR/TIR) | E17: =IRR('Fluxo de Caixa'!H95:BP95) -> 0.076826772 | F17: a.m. | G17: =((1+E17)^(12))-1 -> 1.4308051 | H17: a.a. | J17: =IRR('DRE Franqueadora'!D60:BL60) -> 0.045595776 | K17: a.m. | L17: =((1+J17)^(12))-1 -> 0.70752016 | M17: a.a.
C19: Necessidade de Capital Total | E19: =-'Investimento Inicial'!F38 -> -65321.93
C21: Capital de Giro | E21: =-'Investimento Inicial'!F33 -> -16843.93
C23: Investimento Inicial | E23: =E19-E21 -> -48478
C27: Gerenciamento de Caixa:
C29: Prazo Médio de Estoque | F29: =IF(M29=0,0,K29/M29*30) -> 0 | G29: dias | J29: estoque médio (R$) | K29: 0 | L29: CMV mensal (R$) | M29: 0
C31: Prazo Médio de Recebimento* | F31: =30*DRE!$D$20 -> 0 | G31: dias
C33: Prazo Médio de Pagto | F33: 0 | G33: dias | I33: maximo 90 dias | L33: Prazo Médio CMV | N33: ='Fluxo de Caixa'!F13 -> 0 | P33: Recursos Humanos | R33: ='Fluxo de Caixa'!F26 -> 0 | T33: Despesas Fixas | V33: ='Fluxo de Caixa'!F31 -> 0
C35: Ciclo de Caixa | F35: =F29+F31-F33 -> 0 | G35: dias
C37: *Recebíveis
E39: Check
C40: Percentual à Vista/a Prazo | D40: =SUM(D41:D45) -> 1 | E40: =IF(D40=1,"ok","ERRO") -> ok
C41: (-) Cartão de Crédito | D41: 0
C42: (-) Cartão de Débito | D42: 0
C43: À vista (dinheiro) | D43: 0
C44: PIX | D44: 0.98
C45: Boleto | D45: 0.02
C46: (-) Comissão
D47: À vista | E47: 2x | F47: 3x | G47: 4x | H47: 5x | I47: 6x | J47: 7x | K47: 8x | L47: 9x | M47: 10x | N47: 11x | O47: 12x
C48: Parcelamento Crédito/Alimentação | D48: 1 | E48: 0 | F48: 0 | G48: 0 | H48: 0 | I48: 0 | J48: 0 | K48: 0 | L48: 0 | M48: 0 | N48: 0 | O48: 0 | P48: =SUM(D48:O48) -> 1 | Q48: =IF(P48=1,"ok","ERRO") -> ok
C52: Impostos: | F52: Unidade de Medida
F53: m²
C54: Regime Tributário Franqueado: | F54: Unitário | R54: Simples Nacional - Anexo 1 | S54: Anexo I
F55: Diária | R55: Simples Nacional - Anexo 2 | S55: Anexo II
C56: Simples Nacional - Anexo 4 | F56: Empreitada | R56: Simples Nacional - Anexo 3 | S56: Anexo III
F57: Conjunto | R57: Simples Nacional - Anexo 4 | S57: Anexo IV
C58: Lucro Presumido - Serviços | F58: Kit | R58: Simples Nacional - Anexo 5 | S58: Anexo V
F59: Pacote | R59: Lucro Presumido - Comércio
F60: Saco | R60: Lucro Presumido - Industria
C61: Regime Tributário Franqueadora: | F61: Fardo | R61: Lucro Presumido - Serviços
F62: Milheiro
C63: Simples Nacional - Anexo 5 | F63: Quilo
F64: Caixa
C65: Lucro Presumido - Serviços

Sheet Dashboard Franqueado
J2: SIMULAÇÃO DOS RESULTADOS DO FRANQUEADO
J4: VPL | K4: Taxa VPL | L4: Payback | N4: Capital de giro | R4: Investimento | V4: Necessidade de Capital | X4: TIR (Taxa de Retorno)
J5: ='Fluxo de Caixa'!I112 -> 400845.73 | K5: ='Fluxo de Caixa'!G100 -> 0.12 | L5: ='Fluxo de Caixa'!I111 -> 17 | M5: meses | O5: =Legenda!E21 -> -16843.93 | R5: =Legenda!E23 -> -48478 | V5: =Legenda!E19 -> -65321.93 | X5: =Legenda!G17 -> 1.4308051 | Y5: a.a.
N43: O lucro líquido do franqueado (média mensal), de acordo com as projeções, será de:
N44: Ano 1 | O44: =BA81/12 -> 68.945445 | P44: - com uma lucratividade neste período de | T44: =BA82 -> 0.0016681467 | U44: - com uma rentabilidade neste período de | X44: =O44/'Investimento Inicial'!$F$37 -> 0.0014222007
N45: Ano 2 | O45: =BB81/12 -> 8918.9261 | P45: - com uma lucratividade neste período de | T45: =BB82 -> 0.11235737 | U45: - com uma rentabilidade neste período de | X45: =O45/'Investimento Inicial'!$F$37 -> 0.18397884
N46: Ano 3 | O46: =BC81/12 -> 12330.981 | P46: - com uma lucratividade neste período de | T46: =BC82 -> 0.12963106 | U46: - com uma rentabilidade neste período de | X46: =O46/'Investimento Inicial'!$F$37 -> 0.25436241
N47: Ano 4 | O47: =BD81/12 -> 14206.102 | P47: - com uma lucratividade neste período de | T47: =BD82 -> 0.13770591 | U47: - com uma rentabilidade neste período de | X47: =O47/'Investimento Inicial'!$F$37 -> 0.29304225
N48: Ano 5 | O48: =BE81/12 -> 16641.284 | P48: - com uma lucratividade neste período de | T48: =BE82 -> 0.1470313 | U48: - com uma rentabilidade neste período de | X48: =O48/'Investimento Inicial'!$F$37 -> 0.34327496
AZ59: TABELA DADOS BASE PARA GRÁFICOS
BB62: =(BB65/BA65)-1 -> 0.9206121 | BC62: =(BC65/BB65)-1 -> 0.19833303 | BD62: =(BD65/BC65)-1 -> 0.084510694 | BE62: =(BE65/BD65)-1 -> 0.097121284
AZ63: Média Fat.Bruto Mensal vs Média Receita Líq
BA64: Ano 1 | BB64: Ano 2 | BC64: Ano 3 | BD64: Ano 4 | BE64: Ano 5 | BF64: Ano 6 | BG64: Ano 7 | BH64: Ano 8 | BI64: Ano 9 | BJ64: Ano 10
AZ65: Faturamento Bruto | BA65: =DRE!BQ5/12 -> 41330.565 | BB65: =DRE!BR5/12 -> 79379.984 | BC65: =DRE!BS5/12 -> 95123.657 | BD65: =DRE!BT5/12 -> 103162.62 | BE65: =DRE!BU5/12 -> 113181.91 | BF65: =DRE!#REF!/12 -> #REF! | BG65: =DRE!#REF!/12 -> #REF! | BH65: =DRE!#REF!/12 -> #REF! | BI65: =DRE!#REF!/12 -> #REF! | BJ65: =DRE!#REF!/12 -> #REF!
AZ66: Receita Liquida | BA66: =DRE!BQ13/12 -> 38859.53 | BB66: =DRE!BR13/12 -> 72156.874 | BC66: =DRE!BS13/12 -> 85310.251 | BD66: =DRE!BT13/12 -> 92159.444 | BE66: =DRE!BU13/12 -> 100794.01 | BF66: =DRE!#REF!/12 -> #REF! | BG66: =DRE!#REF!/12 -> #REF! | BH66: =DRE!#REF!/12 -> #REF! | BI66: =DRE!#REF!/12 -> #REF! | BJ66: =DRE!#REF!/12 -> #REF!
BA69: Ano 1 | BB69: Ano 2 | BC69: Ano 3 | BD69: Ano 4 | BE69: Ano 5 | BF69: Ano 6 | BG69: Ano 7 | BH69: Ano 8 | BI69: Ano 9 | BJ69: Ano 10
AZ70: Lucro Bruto | BA70: =DRE!BQ28 -> 199114.62 | BB70: =DRE!BR28 -> 352695.44 | BC70: =DRE!BS28 -> 408754.02 | BD70: =DRE!BT28 -> 438972.89 | BE70: =DRE!BU28 -> 477813.58 | BF70: =DRE!#REF! -> #REF! | BG70: =DRE!#REF! -> #REF! | BH70: =DRE!#REF! -> #REF! | BI70: =DRE!#REF! -> #REF! | BJ70: =DRE!#REF! -> #REF!
AZ71: Média mensal de Lucro bruto | BA71: =BA70/12 -> 16592.885 | BB71: =BB70/12 -> 29391.286 | BC71: =BC70/12 -> 34062.835 | BD71: =BD70/12 -> 36581.074 | BE71: =BE70/12 -> 39817.798 | BF71: =BF70/12 -> #REF! | BG71: =BG70/12 -> #REF! | BH71: =BH70/12 -> #REF! | ... BJ71: =BJ70/12 -> #REF!
AZ72: % | BA72: =DRE!BQ30 -> 0.40146765 | BB72: =DRE!BR30 -> 0.37026068 | BC72: =DRE!BS30 -> 0.35809005 | BD72: =DRE!BT30 -> 0.3545962 | BE72: =DRE!BU30 -> 0.35180355 | BF72: =DRE!#REF! -> #REF! | BG72: =DRE!#REF! -> #REF! | BH72: =DRE!#REF! -> #REF! | BI72: =DRE!#REF! -> #REF! | BJ72: =DRE!#REF! -> #REF!
AZ74: Lucro liquido médio mensal vs lucratividade
BA75: Ano 1 | BB75: Ano 2 | BC75: Ano 3 | BD75: Ano 4 | BE75: Ano 5 | BF75: Ano 6 | BG75: Ano 7 | BH75: Ano 8 | BI75: Ano 9 | BJ75: Ano 10
AZ76: % | BA76: =DRE!BQ115 -> 0.0016681467 | BB76: =DRE!BR115 -> 0.11235737 | BC76: =DRE!BS115 -> 0.12963106 | BD76: =DRE!BT115 -> 0.13770591 | BE76: =DRE!BU115 -> 0.1470313 | BF76: =DRE!#REF! -> #REF! | BG76: =DRE!#REF! -> #REF! | BH76: =DRE!#REF! -> #REF! | BI76: =DRE!#REF! -> #REF! | BJ76: =DRE!#REF! -> #REF!
AZ77: Lucro liquido anual | BA77: =DRE!BQ87 -> 827.34533 | BB77: =DRE!BR84 -> 107027.11 | BC77: =DRE!BS87 -> 147971.77 | BD77: =DRE!BT87 -> 170473.23 | BE77: =DRE!BU87 -> 199695.4 | BF77: =DRE!#REF! -> #REF! | BG77: =DRE!#REF! -> #REF! | BH77: =DRE!#REF! -> #REF! | BI77: =DRE!#REF! -> #REF! | BJ77: =DRE!#REF! -> #REF!
BA80: Ano 1 | BB80: Ano 2 | BC80: Ano 3 | BD80: Ano 4 | BE80: Ano 5 | BF80: Ano 6 | BG80: Ano 7 | BH80: Ano 8 | BI80: Ano 9 | BJ80: Ano 10
AZ81: Lucro Liquido operacional anual | BA81: =DRE!BQ84 -> 827.34533 | BB81: =DRE!BR84 -> 107027.11 | BC81: =DRE!BS84 -> 147971.77 | BD81: =DRE!BT84 -> 170473.23 | BE81: =DRE!BU84 -> 199695.4 | BF81: =DRE!#REF! -> #REF! | BG81: =DRE!#REF! -> #REF! | BH81: =DRE!#REF! -> #REF! | BI81: =DRE!#REF! -> #REF! | BJ81: =DRE!#REF! -> #REF!
AZ82: % | BA82: =BA76 -> 0.0016681467 | BB82: =BB76 -> 0.11235737 | BC82: =BC76 -> 0.12963106 | BD82: =BD76 -> 0.13770591 | BE82: =BE76 -> 0.1470313 | BF82: =BF76 -> #REF! | BG82: =BG76 -> #REF! | BH82: =BH76 -> #REF! | ... BJ82: =BJ76 -> #REF!
BA85: Mês
BA86: 1 | BB86: 2 | BC86: 3 | BD86: 4 | BE86: 5 | BF86: 6 | BG86: 7 | BH86: 8 | BI86: 9 | BJ86: 10 | BK86: 11 | BL86: 12 | BM86: 13 | BN86: 14 | BO86: 15 | BP86: 16 | BQ86: 17 | BR86: 18 | BS86: 19 | BT86: 20 | BU86: 21 | BV86: 22 | BW86: 23 | BX86: 24 | BY86: 25 | BZ86: 26 | CA86: 27 | CB86: 28 | CC86: 29 | CD86: 30 | CE86: 31 | CF86: 32 | CG86: 33 | CH86: 34 | CI86: 35 | CJ86: 36 | CK86: 37 | CL86: 38 | CM86: 39 | CN86: 40 | CO86: 41 | CP86: 42 | CQ86: 43 | CR86: 44 | CS86: 45 | CT86: 46 | CU86: 47 | CV86: 48 | CW86: 49 | CX86: 50 | CY86: 51 | CZ86: 52 | DA86: 53 | DB86: 54 | DC86: 55 | DD86: 56 | DE86: 57 | DF86: 58 | DG86: 59 | DH86: 60 | DI86: 61 | DJ86: 62 | DK86: 63 | DL86: 64 | DM86: 65 | DN86: 66 | DO86: 67 | DP86: 68 | DQ86: 69 | DR86: 70 | DS86: 71 | DT86: 72 | DU86: 73 | DV86: 74 | DW86: 75 | DX86: 76 | DY86: 77 | DZ86: 78 | EA86: 79 | EB86: 80 | EC86: 81 | ED86: 82 | EE86: 83 | EF86: 84 | EG86: 85 | EH86: 86 | EI86: 87 | EJ86: 88 | EK86: 89 | EL86: 90 | EM86: 91 | EN86: 92 | EO86: 93 | EP86: 94 | EQ86: 95 | ER86: 96 | ES86: 97 | ET86: 98 | EU86: 99 | EV86: 100 | EW86: 101 | EX86: 102 | EY86: 103 | EZ86: 104 | FA86: 105 | FB86: 106 | FC86: 107 | FD86: 108 | FE86: 109 | FF86: 110 | FG86: 111 | FH86: 112 | FI86: 113 | FJ86: 114 | FK86: 115 | FL86: 116 | FM86: 117 | FN86: 118 | FO86: 119 | FP86: 120
AZ87: Fluxo caixa acumulado | BA87: ='Fluxo de Caixa'!I96 -> -48478 | BB87: ='Fluxo de Caixa'!J96 -> -59140.227 | BC87: ='Fluxo de Caixa'!K96 -> -69030.037 | BD87: ='Fluxo de Caixa'!L96 -> -75773.26 | BE87: ='Fluxo de Caixa'!M96 -> -79403.253 | BF87: ='Fluxo de Caixa'!N96 -> -80202.801 | BG87: ='Fluxo de Caixa'!O96 -> -78320.089 | BH87: ='Fluxo de Caixa'!P96 -> -74034.977 | ... DH87: ='Fluxo de Caixa'!BP96 -> 600441.94 | DI87: ='Fluxo de Caixa'!#REF! -> #REF! | DJ87: ='Fluxo de Caixa'!#REF! -> #REF! | DK87: ='Fluxo de Caixa'!#REF! -> #REF! | DL87: ='Fluxo de Caixa'!#REF! -> #REF! | DM87: ='Fluxo de Caixa'!#REF! -> #REF! | DN87: ='Fluxo de Caixa'!#REF! -> #REF! | DO87: ='Fluxo de Caixa'!#REF! -> #REF! | DP87: ='Fluxo de Caixa'!#REF! -> #REF! | ... FP87: ='Fluxo de Caixa'!#REF! -> #REF!
AZ92: Evolução Rentabilidade
BA93: Ano 1 | BB93: Ano 2 | BC93: Ano 3 | BD93: Ano 4 | BE93: Ano 5 | BF93: Ano 6 | BG93: Ano 7 | BH93: Ano 8 | BI93: Ano 9 | BJ93: Ano 10
AZ94: % | BA94: =-BA95/$R$5 -> 0.017066408 | BB94: =-BB95/$R$5 -> 2.2077461 | BC94: =-BC95/$R$5 -> 3.0523489 | BD94: =-BD95/$R$5 -> 3.5165071 | BE94: =-BE95/$R$5 -> 4.1192995 | BF94: =-BF95/$R$5 -> #REF! | BG94: =-BG95/$R$5 -> #REF! | BH94: =-BH95/$R$5 -> #REF! | ... BJ94: =-BJ95/$R$5 -> #REF!
AZ95: Lucro liquido anual | BA95: =BA77 -> 827.34533 | BB95: =BB77 -> 107027.11 | BC95: =BC77 -> 147971.77 | BD95: =BD77 -> 170473.23 | BE95: =BE77 -> 199695.4 | BF95: =BF77 -> #REF! | BG95: =BG77 -> #REF! | BH95: =BH77 -> #REF! | ... BJ95: =BJ77 -> #REF!

Sheet Investimento Inicial
B1: SIMULAÇÃO DE INVESTIMENTO INICIAL
B2: Projeção para Franquia Home Office | C2: ='Distribuição de Modelos'!E32 -> 171609 | D2: Habitantes
B3: Estimativa de Investimento Inicial (em R$) | C3: Quantidade | D3: Unidade de Medida | E3: Valor Unitário | F3: Total | G3: %
B4: 1. Reforma e Adaptação Visual | F4: =SUM(F5:F5) -> 0 | G4: =F4/$F$37 -> 0
F5: =IF(D5="Empreitada",E5,E5*C5) -> 0 | G5: =F5/$F$37 -> 0
B6: 2. Máquinas e Equipamentos | F6: =SUM(F7:F9) -> 3080 | G6: =F6/$F$37 -> 0.063533974
B7: Notebook I3 - 8100, SSD 256 GB, 8 GB RAM (Caso tenha não não é necessário) | C7: 1 | D7: Unitário | E7: 2000 | F7: =IF(D7="Empreitada",E7,E7*C7) -> 2000 | G7: =F7/$F$37 -> 0.041255827
B8: Celular (Pode utilizar o pessoal apenas precisa acesso ao WhatsApp Business) | C8: 1 | D8: Unitário | E8: 700 | F8: =IF(D8="Empreitada",E8,E8*C8) -> 700 | G8: =F8/$F$37 -> 0.01443954
B9: Impressora (Caso tenha não é necessário) | C9: 1 | D9: Unitário | E9: 380 | F9: =IF(D9="Empreitada",E9,E9*C9) -> 380 | G9: =F9/$F$37 -> 0.0078386072
B10: 3. Mobiliário | F10: =SUM(F11:F11) -> 0 | G10: =F10/$F$37 -> 0
F11: =IF(D11="Empreitada",E11,E11*C11) -> 0 | G11: =F11/$F$37 -> 0
B12: 4. Utensílios | F12: =SUM(F13:F13) -> 0 | G12: =F12/$F$37 -> 0
F13: =E13*C13 -> 0 | G13: =F13/$F$37 -> 0
B14: 5. Estoque Inicial/Embalagens | F14: =SUM(F15:F15) -> 100 | G14: =F14/$F$37 -> 0.0020627914
B15: Material para Escritório | C15: 1 | D15: Unitário | E15: 100 | F15: =IF(D15="Empreitada",E15,E15*C15) -> 100 | G15: =F15/$F$37 -> 0.0020627914
B16: 6. Treinamento | F16: =SUM(F17:F17) -> 0 | G16: =F16/$F$37 -> 0
F17: =IF(D17="Empreitada",E17,E17*C17) -> 0 | G17: =F17/$F$37 -> 0
B18: 7. Marketing de Inauguração | F18: =SUM(F19:F22) -> 7700 | G18: =F18/$F$37 -> 0.15883494
B19: Tráfego Pago | C19: 1 | D19: Unitário | E19: 5000 | F19: =IF(D19="Empreitada",E19,E19*C19) -> 5000 | G19: =F19/$F$37 -> 0.10313957
B20: Agência Marketing | C20: 1 | D20: Unitário | E20: 1200 | F20: =IF(D20="Empreitada",E20,E20*C20) -> 1200 | G20: =F20/$F$37 -> 0.024753496
B21: Equipe para distrubuir panfletos | C21: 1 | D21: Unitário | E21: 1000 | F21: =IF(D21="Empreitada",E21,E21*C21) -> 1000 | G21: =F21/$F$37 -> 0.020627914
B22: Panfletos | C22: 1 | D22: Unitário | E22: 500 | F22: =IF(D22="Empreitada",E22,E22*C22) -> 500 | G22: =F22/$F$37 -> 0.010313957
B23: 8. Abertura de Empresa | F23: =SUM(F24:F28) -> 1998 | G23: =F23/$F$37 -> 0.041214572
B24: Abertura CNPJ | C24: 1 | D24: Unitário | E24: 1200 | F24: =IF(D24="Empreitada",E24,E24*C24) -> 1200 | G24: =F24/$F$38 -> 0.018370553
B25: Alvará de funcionamento | C25: 1 | D25: Unitário | E25: 300 | F25: =IF(D25="Empreitada",E25,E25*C25) -> 300 | G25: =F25/$F$37 -> 0.0061883741
B26: Certificado digital | C26: 1 | D26: Unitário | E26: 180 | F26: =IF(D26="Empreitada",E26,E26*C26) -> 180 | G26: =F26/$F$37 -> 0.0037130245
B27: Junta comercial | C27: 1 | D27: Unitário | E27: 168 | F27: =IF(D27="Empreitada",E27,E27*C27) -> 168 | G27: =F27/$F$37 -> 0.0034654895
B28: Cartório | C28: 1 | D28: Unitário | E28: 150 | F28: =IF(D28="Empreitada",E28,E28*C28) -> 150 | G28: =F28/$F$37 -> 0.0030941871
B29: 9. Outros | F29: =SUM(F30:F31) -> 600 | G29: =F29/$F$37 -> 0.012376748
B30: Uniformes | C30: 15 | D30: Unitário | E30: 40 | F30: =IF(D30="Empreitada",E30,E30*C30) -> 600 | G30: =F30/$F$37 -> 0.012376748
B31: Implantação do Sistema de Gestão (Em Desenvolvimento) | C31: 1 | D31: Unitário | F31: =IF(D31="Empreitada",E31,E31*C31) -> 0 | G31: =F31/$F$37 -> 0
B32: 10. Taxa de Franquia | F32: =Premissas!G25 -> 35000 | G32: =F32/$F$37 -> 0.72197698
B33: 11. Capital de Giro | F33: =2*('Despesas Mensais'!D41+'Recursos Humanos'!N54) -> 16843.93 | G33: =F33/$F$37 -> 0.34745513
B35: TOTAL MONTAGEM LOJA | F35: =SUM(F4,F6,F10,F12,F14,F23,F29) -> 5778 | G35: =F35/$F$37 -> 0.11918809
B36: TOTAL MONTAGEM LOJA + TREINAMENTO + MKT INAUGURAÇÃO | F36: =F35+F16+F18 -> 13478 | G36: =F36/$F$37 -> 0.27802302
B37: TOTAL MONTAGEM LOJA + TREINAMENTO + MKT INAUGURAÇÃO + TAXA DE FRANQUIA | F37: =F36+F32 -> 48478 | G37: =F37/$F$37 -> 1
B38: TOTAL MONTAGEM LOJA + TREINAMENTO + MKT INAUGURAÇÃO + TAXA DE FRANQUIA + GIRO = NECESSIDADE DE CAPITAL | F38: =F37+F33 -> 65321.93 | G38: =F38/$F$38 -> 1
B41: OBSERVAÇÃO
B43: Devido as despesas mensais e folha de pagamento ter um custo relativamente baixo, por precaução, será considerado como necessidade de capital de giro o valor correspondente a 2 (duas) vezes o total gasto da folha de pagamento mais as despesas mensais.

Sheet Despesas Mensais
B1: SIMULAÇÃO DE CUSTOS E DESPESAS MENSAIS
B2: Valores mensais com reajustes anuais | C2: Variável (*)
B3: Descrição | D3: Ano 1 | E3: Ano 2 | F3: Ano 3 | G3: Ano 4 | H3: Ano 5
B4: % Performance Anual | D4: 0.6 | E4: =('Dashboard Franqueado'!BB65-'Dashboard Franqueado'!BA65)/'Dashboard Franqueado'!BA65 -> 0.9206121 | F4: =('Dashboard Franqueado'!BC65-'Dashboard Franqueado'!BB65)/'Dashboard Franqueado'!BB65 -> 0.19833303 | G4: =('Dashboard Franqueado'!BD65-'Dashboard Franqueado'!BC65)/'Dashboard Franqueado'!BC65 -> 0.084510694 | H4: =('Dashboard Franqueado'!BE65-'Dashboard Franqueado'!BD65)/'Dashboard Franqueado'!BD65 -> 0.097121284
B5: Ocupação
B6: Aluguel XX m² | D6: 0 | E6: =IFERROR(IF($C6="",$D6,(D6*E$4)+D6),"") -> 0 | F6: =IFERROR(IF($C6="",$D6,(E6*F$4)+E6),"") -> 0 | G6: =IFERROR(IF($C6="",$D6,(F6*G$4)+F6),"") -> 0 | H6: =IFERROR(IF($C6="",$D6,(G6*H$4)+G6),"") -> 0
B7: IPTU | D7: 0 | E7: =IFERROR(IF($C7="",$D7,(D7*E$4)+D7),"") -> 0 | F7: =IFERROR(IF($C7="",$D7,(E7*F$4)+E7),"") -> 0 | G7: =IFERROR(IF($C7="",$D7,(F7*G$4)+F7),"") -> 0 | H7: =IFERROR(IF($C7="",$D7,(G7*H$4)+G7),"") -> 0
B8: Condomínio | D8: 0 | E8: =IFERROR(IF($C8="",$D8,(D8*E$4)+D8),"") -> 0 | F8: =IFERROR(IF($C8="",$D8,(E8*F$4)+E8),"") -> 0 | G8: =IFERROR(IF($C8="",$D8,(F8*G$4)+F8),"") -> 0 | H8: =IFERROR(IF($C8="",$D8,(G8*H$4)+G8),"") -> 0
B9: Utilidades
B10: Água | D10: 0 | E10: =IFERROR(IF($C10="",$D10,(D10*E$4)+D10),"") -> 0 | F10: =IFERROR(IF($C10="",$D10,(E10*F$4)+E10),"") -> 0 | G10: =IFERROR(IF($C10="",$D10,(F10*G$4)+F10),"") -> 0 | H10: =IFERROR(IF($C10="",$D10,(G10*H$4)+G10),"") -> 0
B11: Energia Elétrica | D11: 0 | E11: =IFERROR(IF($C11="",$D11,(D11*E$4)+D11),"") -> 0 | F11: =IFERROR(IF($C11="",$D11,(E11*F$4)+E11),"") -> 0 | G11: =IFERROR(IF($C11="",$D11,(F11*G$4)+F11),"") -> 0 | H11: =IFERROR(IF($C11="",$D11,(G11*H$4)+G11),"") -> 0
B12: Gás | D12: 0 | E12: =IFERROR(IF($C12="",$D12,(D12*E$4)+D12),"") -> 0 | F12: =IFERROR(IF($C12="",$D12,(E12*F$4)+E12),"") -> 0 | G12: =IFERROR(IF($C12="",$D12,(F12*G$4)+F12),"") -> 0 | H12: =IFERROR(IF($C12="",$D12,(G12*H$4)+G12),"") -> 0
B13: Telefone - Celular | D13: 0 | E13: =IFERROR(IF($C13="",$D13,(D13*E$4)+D13),"") -> 0 | F13: =IFERROR(IF($C13="",$D13,(E13*F$4)+E13),"") -> 0 | G13: =IFERROR(IF($C13="",$D13,(F13*G$4)+F13),"") -> 0 | H13: =IFERROR(IF($C13="",$D13,(G13*H$4)+G13),"") -> 0
B14: Internet | D14: 130 | E14: =IFERROR(IF($C14="",$D14,(D14*E$4)+D14),"") -> 130 | F14: =IFERROR(IF($C14="",$D14,(E14*F$4)+E14),"") -> 130 | G14: =IFERROR(IF($C14="",$D14,(F14*G$4)+F14),"") -> 130 | H14: =IFERROR(IF($C14="",$D14,(G14*H$4)+G14),"") -> 130
B15: Serviços Terceirizados
B16: Manutenção Software | D16: 500 | E16: =IFERROR(IF($C16="",$D16,(D16*E$4)+D16),"") -> 500 | F16: =IFERROR(IF($C16="",$D16,(E16*F$4)+E16),"") -> 500 | G16: =IFERROR(IF($C16="",$D16,(F16*G$4)+F16),"") -> 500 | H16: =IFERROR(IF($C16="",$D16,(G16*H$4)+G16),"") -> 500
B17: Seguro Empresarial / Responsabilidade Civil | D17: 0 | E17: =IFERROR(IF($C17="",$D17,(D17*E$4)+D17),"") -> 0 | F17: =IFERROR(IF($C17="",$D17,(E17*F$4)+E17),"") -> 0 | G17: =IFERROR(IF($C17="",$D17,(F17*G$4)+F17),"") -> 0 | H17: =IFERROR(IF($C17="",$D17,(G17*H$4)+G17),"") -> 0
B18: Manutenção Instalação Física | D18: 0 | E18: =IFERROR(IF($C18="",$D18,(D18*E$4)+D18),"") -> 0 | F18: =IFERROR(IF($C18="",$D18,(E18*F$4)+E18),"") -> 0 | G18: =IFERROR(IF($C18="",$D18,(F18*G$4)+F18),"") -> 0 | H18: =IFERROR(IF($C18="",$D18,(G18*H$4)+G18),"") -> 0
B19: Manutenção Equipamentos Diversos | D19: 0 | E19: =IFERROR(IF($C19="",$D19,(D19*E$4)+D19),"") -> 0 | F19: =IFERROR(IF($C19="",$D19,(E19*F$4)+E19),"") -> 0 | G19: =IFERROR(IF($C19="",$D19,(F19*G$4)+F19),"") -> 0 | H19: =IFERROR(IF($C19="",$D19,(G19*H$4)+G19),"") -> 0
B20: Contador | D20: 700 | E20: =IFERROR(IF($C20="",$D20,(D20*E$4)+D20),"") -> 700 | F20: =IFERROR(IF($C20="",$D20,(E20*F$4)+E20),"") -> 700 | G20: =IFERROR(IF($C20="",$D20,(F20*G$4)+F20),"") -> 700 | H20: =IFERROR(IF($C20="",$D20,(G20*H$4)+G20),"") -> 700
B21: Auditoria de Vigilância Sanitária | D21: 0 | E21: =IFERROR(IF($C21="",$D21,(D21*E$4)+D21),"") -> 0 | F21: =IFERROR(IF($C21="",$D21,(E21*F$4)+E21),"") -> 0 | G21: =IFERROR(IF($C21="",$D21,(F21*G$4)+F21),"") -> 0 | H21: =IFERROR(IF($C21="",$D21,(G21*H$4)+G21),"") -> 0
B22: Serviços de Segurança/Monitoramento | D22: 0 | E22: =IFERROR(IF($C22="",$D22,(D22*E$4)+D22),"") -> 0 | F22: =IFERROR(IF($C22="",$D22,(E22*F$4)+E22),"") -> 0 | G22: =IFERROR(IF($C22="",$D22,(F22*G$4)+F22),"") -> 0 | H22: =IFERROR(IF($C22="",$D22,(G22*H$4)+G22),"") -> 0
B23: Despesas bancárias | D23: 90 | E23: =IFERROR(IF($C23="",$D23,(D23*E$4)+D23),"") -> 90 | F23: =IFERROR(IF($C23="",$D23,(E23*F$4)+E23),"") -> 90 | G23: =IFERROR(IF($C23="",$D23,(F23*G$4)+F23),"") -> 90 | H23: =IFERROR(IF($C23="",$D23,(G23*H$4)+G23),"") -> 90
B24: Serviços Gerais
B25: Correios | D25: 0 | E25: =IFERROR(IF($C25="",$D25,(D25*E$4)+D25),"") -> 0 | F25: =IFERROR(IF($C25="",$D25,(E25*F$4)+E25),"") -> 0 | G25: =IFERROR(IF($C25="",$D25,(F25*G$4)+F25),"") -> 0 | H25: =IFERROR(IF($C25="",$D25,(G25*H$4)+G25),"") -> 0
B26: Moto-Boy | D26: 0 | E26: =IFERROR(IF($C26="",$D26,(D26*E$4)+D26),"") -> 0 | F26: =IFERROR(IF($C26="",$D26,(E26*F$4)+E26),"") -> 0 | G26: =IFERROR(IF($C26="",$D26,(F26*G$4)+F26),"") -> 0 | H26: =IFERROR(IF($C26="",$D26,(G26*H$4)+G26),"") -> 0
B27: Faxina | D27: 0 | E27: =IFERROR(IF($C27="",$D27,(D27*E$4)+D27),"") -> 0 | F27: =IFERROR(IF($C27="",$D27,(E27*F$4)+E27),"") -> 0 | G27: =IFERROR(IF($C27="",$D27,(F27*G$4)+F27),"") -> 0 | H27: =IFERROR(IF($C27="",$D27,(G27*H$4)+G27),"") -> 0
B28: Materiais Diversos
B29: Material de Trabalho | D29: 0 | E29: =IFERROR(IF($C29="",$D29,(D29*E$4)+D29),"") -> 0 | F29: =IFERROR(IF($C29="",$D29,(E29*F$4)+E29),"") -> 0 | G29: =IFERROR(IF($C29="",$D29,(F29*G$4)+F29),"") -> 0 | H29: =IFERROR(IF($C29="",$D29,(G29*H$4)+G29),"") -> 0
B30: Materiais de Limpeza | D30: 0 | E30: =IFERROR(IF($C30="",$D30,(D30*E$4)+D30),"") -> 0 | F30: =IFERROR(IF($C30="",$D30,(E30*F$4)+E30),"") -> 0 | G30: =IFERROR(IF($C30="",$D30,(F30*G$4)+F30),"") -> 0 | H30: =IFERROR(IF($C30="",$D30,(G30*H$4)+G30),"") -> 0
B31: Materiais de Escritório | D31: 50 | E31: =IFERROR(IF($C31="",$D31,(D31*E$4)+D31),"") -> 50 | F31: =IFERROR(IF($C31="",$D31,(E31*F$4)+E31),"") -> 50 | G31: =IFERROR(IF($C31="",$D31,(F31*G$4)+F31),"") -> 50 | H31: =IFERROR(IF($C31="",$D31,(G31*H$4)+G31),"") -> 50
B32: Outros - diretamente na empresa
B33: Provisão Visita de Desenvolvimento do Franqueado | D33: 204.17 | E33: =((((12/Premissas!W70)*Premissas!H63)/12)) -> 204.16667 | F33: =((((12/Premissas!W70)*Premissas!I63)/12)) -> 204.16667 | G33: =((((12/Premissas!W70)*Premissas!J63)/12)) -> 204.16667 | H33: =((((12/Premissas!W70)*Premissas!K63)/12)) -> 204.16667
B34: Lanches e Refeições | D34: 0 | E34: =IFERROR(IF($C34="",$D34,(D34*E$4)+D34),"") -> 0 | F34: =IFERROR(IF($C34="",$D34,(E34*F$4)+E34),"") -> 0 | G34: =IFERROR(IF($C34="",$D34,(F34*G$4)+F34),"") -> 0 | H34: =IFERROR(IF($C34="",$D34,(G34*H$4)+G34),"") -> 0
B35: Combustível - considerar um custo por km rodado mínimo de R$1,10 | D35: 500 | E35: =IFERROR(IF($C35="",$D35,(D35*E$4)+D35),"") -> 500 | F35: =IFERROR(IF($C35="",$D35,(E35*F$4)+E35),"") -> 500 | G35: =IFERROR(IF($C35="",$D35,(F35*G$4)+F35),"") -> 500 | H35: =IFERROR(IF($C35="",$D35,(G35*H$4)+G35),"") -> 500
B36: Treinamento | D36: 0 | E36: =IFERROR(IF($C36="",$D36,(D36*E$4)+D36),"") -> 0 | F36: =IFERROR(IF($C36="",$D36,(E36*F$4)+E36),"") -> 0 | G36: =IFERROR(IF($C36="",$D36,(F36*G$4)+F36),"") -> 0 | H36: =IFERROR(IF($C36="",$D36,(G36*H$4)+G36),"") -> 0
B37: Sala de Coworking | D37: 500 | E37: =IFERROR(IF($C37="",$D37,(D37*E$4)+D37),"") -> 500 | F37: =IFERROR(IF($C37="",$D37,(E37*F$4)+E37),"") -> 500 | G37: =IFERROR(IF($C37="",$D37,(F37*G$4)+F37),"") -> 500 | H37: =IFERROR(IF($C37="",$D37,(G37*H$4)+G37),"") -> 500
B38: Freelancer | D38: 0 | E38: =IFERROR(IF($C38="",$D38,(D38*E$4)+D38),"") -> 0 | F38: =IFERROR(IF($C38="",$D38,(E38*F$4)+E38),"") -> 0 | G38: =IFERROR(IF($C38="",$D38,(F38*G$4)+F38),"") -> 0 | H38: 0
B39: E-cad | D39: 0 | E39: =IFERROR(IF($C39="",$D39,(D39*E$4)+D39),"") -> 0 | F39: =IFERROR(IF($C39="",$D39,(E39*F$4)+E39),"") -> 0 | G39: =IFERROR(IF($C39="",$D39,(F39*G$4)+F39),"") -> 0 | H39: =IFERROR(IF($C39="",$D39,(G39*H$4)+G39),"") -> 0
B40: Provisionamento para gastos não previstos | D40: 200 | E40: =IFERROR(IF($C40="",$D40,(D40*E$4)+D40),"") -> 200 | F40: =IFERROR(IF($C40="",$D40,(E40*F$4)+E40),"") -> 200 | G40: =IFERROR(IF($C40="",$D40,(F40*G$4)+F40),"") -> 200 | H40: =IFERROR(IF($C40="",$D40,(G40*H$4)+G40),"") -> 200
B41: TOTAL | D41: =SUM(D6:D40) -> 2874.17 | E41: =SUM(E6:E40) -> 2874.1667 | F41: =SUM(F6:F40) -> 2874.1667 | G41: =SUM(G6:G40) -> 2874.1667 | H41: =SUM(H6:H40) -> 2874.1667
B43: Obs.: Esta planilha não configura compromisso ou projeção de resultado, os quais dependerão do esforço e dedicação de cada Franqueado.
B45: Provisionamento para gastos não previstos fixado em R$200,00 (duzentos reais) pelo cliente.
B46: Ano 1 | D46: 3
B47: Ano 2 | D47: 4
B48: Ano 3 | D48: 5
B49: Ano 4 | D49: 6
B50: Ano 5 | D50: 7
B51: Ano 6 | D51: 8
B52: Ano 7 | D52: 9
B53: Ano 8 | D53: 10
B54: Ano 9 | D54: 11
B55: Ano 10 | D55: 12

Sheet Recursos Humanos
B2: SIMULAÇÃO DE SALÁRIOS E ENCARGOS SOCIAIS MENSAIS | N2: =IF(OR(DRE!$C$26="",DRE!$C$26=0%),"","*")
H3: Total de dias trabalhados por mês: | N3: 26
B4: Descrição | C4: Qtde | D4: Remuneração Unitária | E4: Salários | F4: Encargos Trabalhistas | G4: Encargos Comissão | H4: Vale Transporte - Base | I4: Vale Alimentação | J4: Kit Uniforme Básico | K4: Seguro de Vida | L4: Comissão (%) | M4: Tem Comissão (*) | N4: TOTAL
E5: 0 | F5: 0 | G5: 0 | J5: 13.33
F6: uni | G6: uni | H6: =H5*N3*2 -> 0 | I6: =$I$5*$N$3 -> 0 | J6: =J5/12 -> 1.1108333
B7: Franqueado (Pró-Labore) (*) | C7: 1 | D7: 0 | E7: =C7*D7 -> 0 | F7: =D7*0.11 -> 0 | K7: =$K$5*C7 -> 0 | N7: =IF(B7="","",SUM(E7:F7,H7:K7)) -> 0 | P7: Salário Base | R7: 1000 | S7: Quantidade | T7: 1
B8: Atendente | C8: =Receitas_1!Q204 -> 2 | D8: 2000 | E8: =C8*D8 -> 4000 | F8: =C8*(((D8/12)+(D8/12)+((D8/12)/3)+(D8*0.08)+(D8*0)+(((D8/12)+(D8/12))*0.0933))+((D8*0.08)*0.4))*1.2 -> 1545.5733 | G8: =IFERROR(IF(OR(D8=0,D8=""),"",IF(M8<>"*","",(F8/E8))),"") | H8: =$H$6*C8 -> 0 | I8: =$I$6*C8 -> 0 | J8: =$J$6*C8 -> 2.2216667 | K8: =$K$5*C8 -> 0 | L8: =IF(D8="","",IF(M8="","n/a",DRE!$C$26)) -> n/a | N8: =IF(B8="","",SUM(E8:F8,H8:K8)) -> 5547.795 | P8: DESCRIÇÃO | R8: VALORES
D9: 0 | E9: =C9*D9 -> 0 | F9: =C9*(((D9/12)+(D9/12)+((D9/12)/3)+(D9*0.08)+(D9*0)+(((D9/12)+(D9/12))*0.0933))+((D9*0.08)*0.4))*1.2 -> 0 | G9: =IFERROR(IF(OR(D9=0,D9=""),"",IF(M9<>"*","",(F9/E9))),"") | H9: =$H$6*C9 -> 0 | I9: =$I$6*C9 -> 0 | J9: =$J$6*C9 -> 0 | K9: 0 | L9: =IF(D9="","",IF(M9="","n/a",DRE!$C$26)) -> n/a | N9: =IF(B9="","",SUM(E9:F9,H9:K9)) | P9: Salário Base | R9: =R7 -> 1000 | S9: =R9*$T$7 -> 1000 | U9: =S9 -> 1000
D10: 0 | E10: =C10*D10 -> 0 | F10: =C10*(((D10/12)+(D10/12)+((D10/12)/3)+(D10*0.08)+(D10*0)+(((D10/12)+(D10/12))*0.0933))+((D10*0.08)*0.4))*1.2 -> 0 | G10: =IFERROR(IF(OR(D10=0,D10=""),"",IF(M10<>"*","",(F10/E10))),"") | H10: =$H$6*C10 -> 0 | I10: =$I$6*C10 -> 0 | J10: 0 | K10: 0 | L10: =IF(D10="","",IF(M10="","n/a",DRE!$C$26)) -> n/a | N10: =IF(B10="","",SUM(E10:F10,H10:K10))
D11: 0 | E11: =C11*D11 -> 0 | F11: =C11*(((D11/12)+(D11/12)+((D11/12)/3)+(D11*0.08)+(D11*0)+(((D11/12)+(D11/12))*0.0933))+((D11*0.08)*0.4))*1.2 -> 0 | G11: =IFERROR(IF(OR(D11=0,D11=""),"",IF(M11<>"*","",(F11/E11))),"") | H11: =$H$6*C11 -> 0 | I11: =$I$6*C11 -> 0 | J11: 0 | K11: 0 | L11: =IF(D11="","",IF(M11="","n/a",DRE!$C$26)) -> n/a | N11: =IF(B11="","",SUM(E11:F11,H11:K11))
D12: 0 | E12: =C12*D12 -> 0 | F12: =C12*(((D12/12)+(D12/12)+((D12/12)/3)+(D12*0.08)+(D12*0)+(((D12/12)+(D12/12))*0.0933))+((D12*0.08)*0.4))*1.2 -> 0 | G12: =IFERROR(IF(OR(D12=0,D12=""),"",IF(M12<>"*","",(F12/E12))),"") | H12: =$H$6*C12 -> 0 | I12: =$I$6*C12 -> 0 | J12: =$J$6*C12 -> 0 | K12: =$K$5*C12 -> 0 | L12: =IF(D12="","",IF(M12="","n/a",DRE!$C$26)) -> n/a | N12: =IF(B12="","",SUM(E12:F12,H12:K12)) | P12: Férias 1/12 avos | R12: =R9/12 -> 83.333333 | S12: =R12*$T$7 -> 83.333333
D13: 0 | E13: =C13*D13 -> 0 | F13: =C13*(((D13/12)+(D13/12)+((D13/12)/3)+(D13*0.08)+(D13*0)+(((D13/12)+(D13/12))*0.0933))+((D13*0.08)*0.4))*1.2 -> 0 | G13: =IFERROR(IF(OR(D13=0,D13=""),"",IF(M13<>"*","",(F13/E13))),"") | H13: =$H$6*C13 -> 0 | I13: =$I$6*C13 -> 0 | J13: =$J$6*C13 -> 0 | K13: =$K$5*C13 -> 0 | L13: =IF(D13="","",IF(M13="","n/a",DRE!$C$26)) -> n/a | N13: =IF(B13="","",SUM(E13:F13,H13:K13)) | P13: 13º Salário 1/12 avos | R13: =R9/12 -> 83.333333 | S13: =R13*$T$7 -> 83.333333
B14: TOTAL MENSAL (Ano 1) | C14: =SUM(C7:C13) -> 3 | E14: =SUM(E7:E13) -> 4000 | F14: =SUM(F7:F13) -> 1545.5733 | G14: =IFERROR(IF(OR(DRE!$C$26=0%,DRE!$C$26=""),"",F14/E14),"") | H14: =SUM(H7:H13) -> 0 | I14: =SUM(I7:I13) -> 0 | J14: =SUM(J7:J13) -> 2.2216667 | K14: =SUM(K7:K13) -> 0 | N14: =SUM(N7:N13) -> 5547.795 | P14: 1/3 sobre Férias | R14: =R12/3 -> 27.777778 | S14: =R14*$T$7 -> 27.777778
P15: FGTS | Q15: 0.08 | R15: =R7*Q15 -> 80 | S15: =R15*$T$7 -> 80
P16: INSS(Contribuição Mínima) | Q16: 0 | R16: =R7*Q16 -> 0 | S16: =R16*$T$7 -> 0
B17: =B7 -> Franqueado (Pró-Labore) (*) | C17: 1 | E17: =C17*D17 -> 0 | F17: =D17*0.11 -> 0 | K17: =$K$5*C17 -> 0 | N17: =IF(B17="","",SUM(E17:F17,H17:K17)) -> 0 | P17: Provisão FGTS (13º e Férias) | Q17: 0.093337493 | R17: =(R13+R12)*Q17 -> 15.556249 | S17: =R17*$T$7 -> 15.556249
B18: =B8 -> Atendente | C18: =Receitas_1!AC204 -> 2 | D18: 2000 | E18: =C18*D18 -> 4000 | F18: =C18*(((D18/12)+(D18/12)+((D18/12)/3)+(D18*0.08)+(D18*0)+(((D18/12)+(D18/12))*0.0933))+((D18*0.08)*0.4))*1.2 -> 1545.5733 | G18: =IFERROR(IF(OR(D18=0,D18=""),"",IF(M18<>"*","",(F18/E18))),"") | H18: =$H$6*C18 -> 0 | I18: =$I$6*C18 -> 0 | J18: =$J$6*C18 -> 2.2216667 | K18: =$K$5*C18 -> 0 | L18: =IF(D18="","",IF(M18="","n/a",DRE!$C$26)) -> n/a | N18: =IF(B18="","",SUM(E18:F18,H18:K18)) -> 5547.795 | P18: Provisão INSS (13º e Férias) | Q18: 0 | R18: =(R16+R12)*Q18 -> 0 | S18: =R18*$T$7 -> 0 | U18: =SUM(S12:T18) -> 290.00069
E19: =C19*D19 -> 0 | F19: =C19*(((D19/12)+(D19/12)+((D19/12)/3)+(D19*0.08)+(D19*0)+(((D19/12)+(D19/12))*0.0933))+((D19*0.08)*0.4))*1.2 -> 0 | G19: =IFERROR(IF(OR(D19=0,D19=""),"",IF(M19<>"*","",(F19/E19))),"") | H19: =$H$6*C19 -> 0 | I19: =$I$6*C19 -> 0 | J19: =$J$6*C19 -> 0 | K19: =$K$5*C19 -> 0 | L19: =IF(D19="","",IF(M19="","n/a",DRE!$C$26)) | N19: =IF(B19="","",SUM(E19:F19,H19:K19))
E20: =C20*D20 -> 0 | F20: =C20*(((D20/12)+(D20/12)+((D20/12)/3)+(D20*0.08)+(D20*0)+(((D20/12)+(D20/12))*0.0933))+((D20*0.08)*0.4))*1.2 -> 0 | G20: =IFERROR(IF(OR(D20=0,D20=""),"",IF(M20<>"*","",(F20/E20))),"") | H20: =$H$6*C20 -> 0 | I20: =$I$6*C20 -> 0 | J20: =$J$6*C20 -> 0 | K20: =$K$5*C20 -> 0 | L20: =IF(D20="","",IF(M20="","n/a",DRE!$C$26)) | N20: =IF(B20="","",SUM(E20:F20,H20:K20))
E21: =C21*D21 -> 0 | F21: =C21*(((D21/12)+(D21/12)+((D21/12)/3)+(D21*0.08)+(D21*0)+(((D21/12)+(D21/12))*0.0933))+((D21*0.08)*0.4))*1.2 -> 0 | G21: =IFERROR(IF(OR(D21=0,D21=""),"",IF(M21<>"*","",(F21/E21))),"") | H21: =$H$6*C21 -> 0 | I21: =$I$6*C21 -> 0 | J21: =$J$6*C21 -> 0 | K21: =$K$5*C21 -> 0 | L21: =IF(D21="","",IF(M21="","n/a",DRE!$C$26)) | N21: =IF(B21="","",SUM(E21:F21,H21:K21))
E22: =C22*D22 -> 0 | F22: =C22*(((D22/12)+(D22/12)+((D22/12)/3)+(D22*0.08)+(D22*0)+(((D22/12)+(D22/12))*0.0933))+((D22*0.08)*0.4))*1.2 -> 0 | G22: =IFERROR(IF(OR(D22=0,D22=""),"",IF(M22<>"*","",(F22/E22))),"") | H22: =$H$6*C22 -> 0 | I22: =$I$6*C22 -> 0 | J22: =$J$6*C22 -> 0 | K22: =$K$5*C22 -> 0 | L22: =IF(D22="","",IF(M22="","n/a",DRE!$C$26)) | N22: =IF(B22="","",SUM(E22:F22,H22:K22))
E23: =C23*D23 -> 0 | F23: =C23*(((D23/12)+(D23/12)+((D23/12)/3)+(D23*0.08)+(D23*0)+(((D23/12)+(D23/12))*0.0933))+((D23*0.08)*0.4))*1.2 -> 0 | G23: =IFERROR(IF(OR(D23=0,D23=""),"",IF(M23<>"*","",(F23/E23))),"") | H23: =$H$6*C23 -> 0 | I23: =$I$6*C23 -> 0 | J23: =$J$6*C23 -> 0 | K23: =$K$5*C23 -> 0 | L23: =IF(D23="","",IF(M23="","n/a",DRE!$C$26)) | N23: =IF(B23="","",SUM(E23:F23,H23:K23)) | P23: Desconto Vale Transporte | R23: =-(#REF!-#REF!) -> #REF! | S23: =R23*$T$7 -> #REF! | U23: =S23 -> #REF!
B24: TOTAL MENSAL (Ano 2) | C24: =SUM(C17:C23) -> 3 | E24: =SUM(E17:E23) -> 4000 | F24: =SUM(F17:F23) -> 1545.5733 | G24: =IFERROR(IF(OR(DRE!$C$26=0%,DRE!$C$26=""),"",F24/E24),"") | H24: =SUM(H17:H23) -> 0 | I24: =SUM(I17:I23) -> 0 | J24: =SUM(J17:J23) -> 2.2216667 | K24: =SUM(K17:K23) -> 0 | N24: =SUM(N17:N23) -> 5547.795 | P24: Vale Alimentação | R24: =I6 -> 0 | S24: =R24*$T$7 -> 0 | U24: =S24 -> 0
P25: Kit Uniforme Básico | R25: =J6 -> 1.1108333 | S25: =R25*$T$7 -> 1.1108333 | U25: =S25 -> 1.1108333
P26: Plano de Saúde | R26: =K5 -> 0 | S26: =R26*$T$7 -> 0 | U26: =S26 -> 0
B27: =B7 -> Franqueado (Pró-Labore) (*) | C27: 1 | E27: =C27*D27 -> 0 | F27: =D27*0.11 -> 0 | K27: =$K$5*C27 -> 0 | N27: =IF(B27="","",SUM(E27:F27,H27:K27)) -> 0 | P27: Gratificações e Comissões | S27: =R27*$T$7 -> 0 | U27: =S27 -> 0
B28: =B8 -> Atendente | C28: =Receitas_1!AO204 -> 2 | D28: 2000 | E28: =C28*D28 -> 4000 | F28: =C28*(((D28/12)+(D28/12)+((D28/12)/3)+(D28*0.08)+(D28*0)+(((D28/12)+(D28/12))*0.0933))+((D28*0.08)*0.4))*1.2 -> 1545.5733 | G28: =IFERROR(IF(OR(D28=0,D28=""),"",IF(M28<>"*","",(F28/E28))),"") | H28: =$H$6*C28 -> 0 | I28: =$I$6*C28 -> 0 | J28: =$J$6*C28 -> 2.2216667 | K28: =$K$5*C28 -> 0 | L28: =IF(D28="","",IF(M28="","n/a",DRE!$C$26)) -> n/a | N28: =IF(B28="","",SUM(E28:F28,H28:K28)) -> 5547.795 | P28: TOTAL | R28: =SUM(R9:R22)+R23+R24+R25+R26+R27 -> #REF! | S28: =SUM(S9:T22)+S23+S24+S25+S26+S27 -> #REF! | U28: =SUM(U9+U18+#REF!+U24+U25+U26+U27) -> #REF!
E29: =C29*D29 -> 0 | F29: =C29*(((D29/12)+(D29/12)+((D29/12)/3)+(D29*0.08)+(D29*0)+(((D29/12)+(D29/12))*0.0933))+((D29*0.08)*0.4))*1.2 -> 0 | G29: =IFERROR(IF(OR(D29=0,D29=""),"",IF(M29<>"*","",(F29/E29))),"") | H29: =$H$6*C29 -> 0 | I29: =$I$6*C29 -> 0 | J29: =$J$6*C29 -> 0 | K29: =$K$5*C29 -> 0 | L29: =IF(D29="","",IF(M29="","n/a",DRE!$C$26)) | N29: =IF(B29="","",SUM(E29:F29,H29:K29))
E30: =C30*D30 -> 0 | F30: =C30*(((D30/12)+(D30/12)+((D30/12)/3)+(D30*0.08)+(D30*0)+(((D30/12)+(D30/12))*0.0933))+((D30*0.08)*0.4))*1.2 -> 0 | G30: =IFERROR(IF(OR(D30=0,D30=""),"",IF(M30<>"*","",(F30/E30))),"") | H30: =$H$6*C30 -> 0 | I30: =$I$6*C30 -> 0 | J30: =$J$6*C30 -> 0 | K30: =$K$5*C30 -> 0 | L30: =IF(D30="","",IF(M30="","n/a",DRE!$C$26)) | N30: =IF(B30="","",SUM(E30:F30,H30:K30))
E31: =C31*D31 -> 0 | F31: =C31*(((D31/12)+(D31/12)+((D31/12)/3)+(D31*0.08)+(D31*0)+(((D31/12)+(D31/12))*0.0933))+((D31*0.08)*0.4))*1.2 -> 0 | G31: =IFERROR(IF(OR(D31=0,D31=""),"",IF(M31<>"*","",(F31/E31))),"") | H31: =$H$6*C31 -> 0 | I31: =$I$6*C31 -> 0 | J31: =$J$6*C31 -> 0 | K31: =$K$5*C31 -> 0 | L31: =IF(D31="","",IF(M31="","n/a",DRE!$C$26)) | N31: =IF(B31="","",SUM(E31:F31,H31:K31))
E32: =C32*D32 -> 0 | F32: =C32*(((D32/12)+(D32/12)+((D32/12)/3)+(D32*0.08)+(D32*0)+(((D32/12)+(D32/12))*0.0933))+((D32*0.08)*0.4))*1.2 -> 0 | G32: =IFERROR(IF(OR(D32=0,D32=""),"",IF(M32<>"*","",(F32/E32))),"") | H32: =$H$6*C32 -> 0 | I32: =$I$6*C32 -> 0 | J32: =$J$6*C32 -> 0 | K32: =$K$5*C32 -> 0 | L32: =IF(D32="","",IF(M32="","n/a",DRE!$C$26)) | N32: =IF(B32="","",SUM(E32:F32,H32:K32))
E33: =C33*D33 -> 0 | F33: =C33*(((D33/12)+(D33/12)+((D33/12)/3)+(D33*0.08)+(D33*0)+(((D33/12)+(D33/12))*0.0933))+((D33*0.08)*0.4))*1.2 -> 0 | G33: =IFERROR(IF(OR(D33=0,D33=""),"",IF(M33<>"*","",(F33/E33))),"") | H33: =$H$6*C33 -> 0 | I33: =$I$6*C33 -> 0 | J33: =$J$6*C33 -> 0 | K33: =$K$5*C33 -> 0 | L33: =IF(D33="","",IF(M33="","n/a",DRE!$C$26)) | N33: =IF(B33="","",SUM(E33:F33,H33:K33))
B34: TOTAL MENSAL (Ano 3) | C34: =SUM(C27:C33) -> 3 | E34: =SUM(E27:E33) -> 4000 | F34: =SUM(F27:F33) -> 1545.5733 | G34: =IFERROR(IF(OR(DRE!$C$26=0%,DRE!$C$26=""),"",F34/E34),"") | H34: =SUM(H27:H33) -> 0 | I34: =SUM(I27:I33) -> 0 | J34: =SUM(J27:J33) -> 2.2216667 | K34: =SUM(K27:K33) -> 0 | N34: =SUM(N27:N33) -> 5547.795
B37: =B7 -> Franqueado (Pró-Labore) (*) | C37: 1 | E37: =C37*D37 -> 0 | F37: =D37*0.11 -> 0 | K37: =$K$5*C37 -> 0 | N37: =IF(B37="","",SUM(E37:F37,H37:K37)) -> 0
B38: =B8 -> Atendente | C38: =Receitas_1!BA204 -> 2 | D38: 2000 | E38: =C38*D38 -> 4000 | F38: =C38*(((D38/12)+(D38/12)+((D38/12)/3)+(D38*0.08)+(D38*0)+(((D38/12)+(D38/12))*0.0933))+((D38*0.08)*0.4))*1.2 -> 1545.5733 | G38: =IFERROR(IF(OR(D38=0,D38=""),"",IF(M38<>"*","",(F38/E38))),"") | H38: =$H$6*C38 -> 0 | I38: =$I$6*C38 -> 0 | J38: =$J$6*C38 -> 2.2216667 | K38: =$K$5*C38 -> 0 | L38: =IF(D38="","",IF(M38="","n/a",DRE!$C$26)) -> n/a | N38: =IF(B38="","",SUM(E38:F38,H38:K38)) -> 5547.795
E39: =C39*D39 -> 0 | F39: =C39*(((D39/12)+(D39/12)+((D39/12)/3)+(D39*0.08)+(D39*0)+(((D39/12)+(D39/12))*0.0933))+((D39*0.08)*0.4))*1.2 -> 0 | G39: =IFERROR(IF(OR(D39=0,D39=""),"",IF(M39<>"*","",(F39/E39))),"") | H39: =$H$6*C39 -> 0 | I39: =$I$6*C39 -> 0 | J39: =$J$6*C39 -> 0 | K39: =$K$5*C39 -> 0 | L39: =IF(D39="","",IF(M39="","n/a",DRE!$C$26)) | N39: =IF(B39="","",SUM(E39:F39,H39:K39))
E40: =C40*D40 -> 0 | F40: =C40*(((D40/12)+(D40/12)+((D40/12)/3)+(D40*0.08)+(D40*0)+(((D40/12)+(D40/12))*0.0933))+((D40*0.08)*0.4))*1.2 -> 0 | G40: =IFERROR(IF(OR(D40=0,D40=""),"",IF(M40<>"*","",(F40/E40))),"") | H40: =$H$6*C40 -> 0 | I40: =$I$6*C40 -> 0 | J40: =$J$6*C40 -> 0 | K40: =$K$5*C40 -> 0 | L40: =IF(D40="","",IF(M40="","n/a",DRE!$C$26)) | N40: =IF(B40="","",SUM(E40:F40,H40:K40))
E41: =C41*D41 -> 0 | F41: =C41*(((D41/12)+(D41/12)+((D41/12)/3)+(D41*0.08)+(D41*0)+(((D41/12)+(D41/12))*0.0933))+((D41*0.08)*0.4))*1.2 -> 0 | G41: =IFERROR(IF(OR(D41=0,D41=""),"",IF(M41<>"*","",(F41/E41))),"") | H41: =$H$6*C41 -> 0 | I41: =$I$6*C41 -> 0 | J41: =$J$6*C41 -> 0 | K41: =$K$5*C41 -> 0 | L41: =IF(D41="","",IF(M41="","n/a",DRE!$C$26)) | N41: =IF(B41="","",SUM(E41:F41,H41:K41))
E42: =C42*D42 -> 0 | F42: =C42*(((D42/12)+(D42/12)+((D42/12)/3)+(D42*0.08)+(D42*0)+(((D42/12)+(D42/12))*0.0933))+((D42*0.08)*0.4))*1.2 -> 0 | G42: =IFERROR(IF(OR(D42=0,D42=""),"",IF(M42<>"*","",(F42/E42))),"") | H42: =$H$6*C42 -> 0 | I42: =$I$6*C42 -> 0 | J42: =$J$6*C42 -> 0 | K42: =$K$5*C42 -> 0 | L42: =IF(D42="","",IF(M42="","n/a",DRE!$C$26)) | N42: =IF(B42="","",SUM(E42:F42,H42:K42))
E43: =C43*D43 -> 0 | F43: =C43*(((D43/12)+(D43/12)+((D43/12)/3)+(D43*0.08)+(D43*0)+(((D43/12)+(D43/12))*0.0933))+((D43*0.08)*0.4))*1.2 -> 0 | G43: =IFERROR(IF(OR(D43=0,D43=""),"",IF(M43<>"*","",(F43/E43))),"") | H43: =$H$6*C43 -> 0 | I43: =$I$6*C43 -> 0 | J43: =$J$6*C43 -> 0 | K43: =$K$5*C43 -> 0 | L43: =IF(D43="","",IF(M43="","n/a",DRE!$C$26)) | N43: =IF(B43="","",SUM(E43:F43,H43:K43))
B44: TOTAL MENSAL (Ano 4) | C44: =SUM(C37:C43) -> 3 | E44: =SUM(E37:E43) -> 4000 | F44: =SUM(F37:F43) -> 1545.5733 | G44: =IFERROR(IF(OR(DRE!$C$26=0%,DRE!$C$26=""),"",F44/E44),"") | H44: =SUM(H37:H43) -> 0 | I44: =SUM(I37:I43) -> 0 | J44: =SUM(J37:J43) -> 2.2216667 | K44: =SUM(K37:K43) -> 0 | N44: =SUM(N37:N43) -> 5547.795
B47: =B7 -> Franqueado (Pró-Labore) (*) | C47: 1 | E47: =C47*D47 -> 0 | F47: =D47*0.11 -> 0 | K47: =$K$5*C47 -> 0 | N47: =IF(B47="","",SUM(E47:F47,H47:K47)) -> 0
B48: =B8 -> Atendente | C48: =Receitas_1!BM204 -> 2 | D48: 2000 | E48: =C48*D48 -> 4000 | F48: =C48*(((D48/12)+(D48/12)+((D48/12)/3)+(D48*0.08)+(D48*0)+(((D48/12)+(D48/12))*0.0933))+((D48*0.08)*0.4))*1.2 -> 1545.5733 | G48: =IFERROR(IF(OR(D48=0,D48=""),"",IF(M48<>"*","",(F48/E48))),"") | H48: =$H$6*C48 -> 0 | I48: =$I$6*C48 -> 0 | J48: =$J$6*C48 -> 2.2216667 | K48: =$K$5*C48 -> 0 | L48: =IF(D48="","",IF(M48="","n/a",DRE!$C$26)) -> n/a | N48: =IF(B48="","",SUM(E48:F48,H48:K48)) -> 5547.795
E49: =C49*D49 -> 0 | F49: =C49*(((D49/12)+(D49/12)+((D49/12)/3)+(D49*0.08)+(D49*0)+(((D49/12)+(D49/12))*0.0933))+((D49*0.08)*0.4))*1.2 -> 0 | G49: =IFERROR(IF(OR(D49=0,D49=""),"",IF(M49<>"*","",(F49/E49))),"") | H49: =$H$6*C49 -> 0 | I49: =$I$6*C49 -> 0 | J49: =$J$6*C49 -> 0 | K49: =$K$5*C49 -> 0 | L49: =IF(D49="","",IF(M49="","n/a",DRE!$C$26)) | N49: =IF(B49="","",SUM(E49:F49,H49:K49))
E50: =C50*D50 -> 0 | F50: =C50*(((D50/12)+(D50/12)+((D50/12)/3)+(D50*0.08)+(D50*0)+(((D50/12)+(D50/12))*0.0933))+((D50*0.08)*0.4))*1.2 -> 0 | G50: =IFERROR(IF(OR(D50=0,D50=""),"",IF(M50<>"*","",(F50/E50))),"") | H50: =$H$6*C50 -> 0 | I50: =$I$6*C50 -> 0 | J50: =$J$6*C50 -> 0 | K50: =$K$5*C50 -> 0 | L50: =IF(D50="","",IF(M50="","n/a",DRE!$C$26)) | N50: =IF(B50="","",SUM(E50:F50,H50:K50))
E51: =C51*D51 -> 0 | F51: =C51*(((D51/12)+(D51/12)+((D51/12)/3)+(D51*0.08)+(D51*0)+(((D51/12)+(D51/12))*0.0933))+((D51*0.08)*0.4))*1.2 -> 0 | G51: =IFERROR(IF(OR(D51=0,D51=""),"",IF(M51<>"*","",(F51/E51))),"") | H51: =$H$6*C51 -> 0 | I51: =$I$6*C51 -> 0 | J51: =$J$6*C51 -> 0 | K51: =$K$5*C51 -> 0 | L51: =IF(D51="","",IF(M51="","n/a",DRE!$C$26)) | N51: =IF(B51="","",SUM(E51:F51,H51:K51))
E52: =C52*D52 -> 0 | F52: =C52*(((D52/12)+(D52/12)+((D52/12)/3)+(D52*0.08)+(D52*0)+(((D52/12)+(D52/12))*0.0933))+((D52*0.08)*0.4))*1.2 -> 0 | G52: =IFERROR(IF(OR(D52=0,D52=""),"",IF(M52<>"*","",(F52/E52))),"") | H52: =$H$6*C52 -> 0 | I52: =$I$6*C52 -> 0 | J52: =$J$6*C52 -> 0 | K52: =$K$5*C52 -> 0 | L52: =IF(D52="","",IF(M52="","n/a",DRE!$C$26)) | N52: =IF(B52="","",SUM(E52:F52,H52:K52))
E53: =D53 -> 0 | F53: =C53*(((D53/12)+(D53/12)+((D53/12)/3)+(D53*0.08)+(D53*0)+(((D53/12)+(D53/12))*0.0933))+((D53*0.08)*0.4))*1.2 -> 0 | G53: =IFERROR(IF(OR(D53=0,D53=""),"",IF(M53<>"*","",(F53/E53))),"") | H53: =$H$6*C53 -> 0 | I53: =$I$6*C53 -> 0 | J53: =$J$6*C53 -> 0 | K53: =$K$5*C53 -> 0 | L53: =IF(D53="","",IF(M53="","n/a",DRE!$C$26)) | N53: =IF(B53="","",SUM(E53:F53,H53:K53))
B54: TOTAL MENSAL (Ano 5) | C54: =SUM(C47:C53) -> 3 | E54: =SUM(E47:E53) -> 4000 | F54: =SUM(F47:F53) -> 1545.5733 | G54: =IFERROR(IF(OR(DRE!$C$26=0%,DRE!$C$26=""),"",F54/E54),"") | H54: =SUM(H47:H53) -> 0 | I54: =SUM(I47:I53) -> 0 | J54: =SUM(J47:J53) -> 2.2216667 | K54: =SUM(K47:K53) -> 0 | N54: =SUM(N47:N53) -> 5547.795
B62: OBSERVAÇÕES: - Operação para produção mínima de 15 rodadas semanais. * Encargos trabalhistas estão inclusos além dos custos mensais as provisões de 13º, férias, 1/3 férias, FGTS férias e 13º, INSS férias e 13º para recolhimento mensal.
B64: Devido ao baixo valor de investimento inicial, a remuneração do Franqueado deverá ser composta através do resultado da divisão dos lucros da operação
B67: INFORMATIVOS
B71: Correção Anual | D71: =1*(1+'Despesas Mensais'!$E$4) -> 1.9206121
B72: Correção Anual | D72: =1*(1+'Despesas Mensais'!$F$4) -> 1.198333
B73: Correção Anual | D73: =1*(1+'Despesas Mensais'!$G$4) -> 1.0845107
B74: Correção Anual | D74: 1
B76: Ano 1 | E76: Cálculo 13º e férias
B77: Ano 2 | E77: % | F77: =1/3+1 -> 1.3333333
B78: Ano 3 | E78: Parcelas | F78: 12
B79: Ano 4
B80: Ano 5
B81: Ano 6
B82: Ano 7
B83: Ano 8
B84: Ano 9
B85: Ano 10
C87: Ano 1 | D87: Ano 2 | E87: Ano 3 | F87: Ano 4 | G87: Ano 5
B88: Salários | C88: =E14 -> 4000 | D88: =E24 -> 4000 | E88: =E34 -> 4000 | F88: =E44 -> 4000 | G88: =E54 -> 4000
B89: Encargos | C89: =F14 -> 1545.5733 | D89: =F24 -> 1545.5733 | E89: =F34 -> 1545.5733 | F89: =F44 -> 1545.5733 | G89: =F54 -> 1545.5733
B90: Benefícios | C90: =SUM(C91:C94) -> 2.2216667 | D90: =SUM(D91:D94) -> 2.2216667 | E90: =SUM(E91:E94) -> 2.2216667 | F90: =SUM(F91:F94) -> 2.2216667 | G90: =SUM(G91:G94) -> 2.2216667
B91: =H4 -> Vale Transporte - Base | C91: =H14 -> 0 | D91: =H24 -> 0 | E91: =H34 -> 0 | F91: =H44 -> 0 | G91: =H54 -> 0
B92: =I4 -> Vale Alimentação | C92: =I14 -> 0 | D92: =I24 -> 0 | E92: =I34 -> 0 | F92: =I44 -> 0 | G92: =I54 -> 0
B93: Plano de Saúde | C93: =K14 -> 0 | D93: =K24 -> 0 | E93: =K34 -> 0 | F93: =K44 -> 0 | G93: =K54 -> 0
B94: =J4 -> Kit Uniforme Básico | C94: =J14 -> 2.2216667 | D94: =J24 -> 2.2216667 | E94: =J34 -> 2.2216667 | F94: =J44 -> 2.2216667 | G94: =J54 -> 2.2216667

Sheet Receitas_1
C1: SIMULAÇÃO DE FORMAÇÃO DA RECEITA
F2: Ano 1 | G2: Ano 1 | H2: Ano 1 | I2: Ano 1 | J2: Ano 1 | K2: Ano 1 | L2: Ano 1 | M2: Ano 1 | N2: Ano 1 | O2: Ano 1 | P2: Ano 1 | Q2: Ano 1 | R2: Ano 2 | S2: Ano 2 | T2: Ano 2 | U2: Ano 2 | V2: Ano 2 | W2: Ano 2 | X2: Ano 2 | Y2: Ano 2 | Z2: Ano 2 | AA2: Ano 2 | AB2: Ano 2 | AC2: Ano 2 | AD2: Ano 3 | AE2: Ano 3 | AF2: Ano 3 | AG2: Ano 3 | AH2: Ano 3 | AI2: Ano 3 | AJ2: Ano 3 | AK2: Ano 3 | AL2: Ano 3 | AM2: Ano 3 | AN2: Ano 3 | AO2: Ano 3 | AP2: Ano 4 | AQ2: Ano 4 | AR2: Ano 4 | AS2: Ano 4 | AT2: Ano 4 | AU2: Ano 4 | AV2: Ano 4 | AW2: Ano 4 | AX2: Ano 4 | AY2: Ano 4 | AZ2: Ano 4 | BA2: Ano 4 | BB2: Ano 5 | BC2: Ano 5 | BD2: Ano 5 | BE2: Ano 5 | BF2: Ano 5 | BG2: Ano 5 | BH2: Ano 5 | BI2: Ano 5 | BJ2: Ano 5 | BK2: Ano 5 | BL2: Ano 5 | BM2: Ano 5 | BO2: Ano 1 | BP2: Ano 2 | BQ2: Ano 3 | BR2: Ano 4 | BS2: Ano 5
D3: Cenário | E3: Conservador | F3: Jan | G3: Fev | H3: Mar | I3: Abr | J3: Mai | K3: Jun | L3: Jul | M3: Ago | N3: Set | O3: Out | P3: Nov | Q3: Dez | R3: Jan | S3: Fev | T3: Mar | U3: Abr | V3: Mai | W3: Jun | X3: Jul | Y3: Ago | Z3: Set | AA3: Out | AB3: Nov | AC3: Dez | AD3: Jan | AE3: Fev | AF3: Mar | AG3: Abr | AH3: Mai | AI3: Jun | AJ3: Jul | AK3: Ago | AL3: Set | AM3: Out | AN3: Nov | AO3: Dez | AP3: Jan | AQ3: Fev | AR3: Mar | AS3: Abr | AT3: Mai | AU3: Jun | AV3: Jul | AW3: Ago | AX3: Set | AY3: Out | AZ3: Nov | BA3: Dez | BB3: Jan | BC3: Fev | BD3: Mar | BE3: Abr | BF3: Mai | BG3: Jun | BH3: Jul | BI3: Ago | BJ3: Set | BK3: Out | BL3: Nov | BM3: Dez
B4: Quantidades vendidas | C4: Representatividade nas Vendas em % nos 5 anos | D4: Potencial TOTAL | E4: Quantidade Média Vendida | F4: IMPLANTAÇÃO | G4: Crescimento vs. Mês Anterior => | H4: 1 | I4: 0.5 | J4: 0.33 | K4: 0.25 | L4: 0.2 | M4: 0.16 | N4: 0.14 | O4: 0.13 | P4: 0.11 | Q4: 0.1 | R4: -0.25 | S4: -0.05 | T4: 0.1 | U4: 0.1 | V4: 0.1 | W4: 0.1 | X4: -0.05 | Y4: -0.05 | Z4: 0.07 | AA4: 0.07 | AB4: 0.07 | AC4: 0.1 | AD4: -0.15 | AE4: -0.05 | AF4: 0.05 | AG4: 0.05 | AH4: 0.05 | AI4: 0.07 | AJ4: -0.1 | AK4: -0.1 | AL4: 0.07 | AM4: 0.07 | AN4: 0.07 | AO4: 0.08 | AP4: -0.14 | AQ4: -0.05 | AR4: 0.05 | AS4: 0.05 | AT4: 0.05 | AU4: 0.07 | AV4: -0.1 | AW4: -0.1 | AX4: 0.07 | AY4: 0.07 | AZ4: 0.07 | BA4: 0.08 | BB4: -0.13 | BC4: -0.05 | BD4: 0.05 | BE4: 0.05 | BF4: 0.05 | BG4: 0.07 | BH4: -0.1 | BI4: -0.1 | BJ4: 0.07 | BK4: 0.07 | BL4: 0.07 | BM4: 0.08 | BN4: 0.05 | BO4: 0.05 | BP4: unidades | BQ4: unidades | BR4: unidades | BS4: unidades | BV4: Representatividade nas Vendas em % (Qtde) | BX4: Média Crescimento Ano 1 | BY4: Média Crescimento Ano 2 | BZ4: Média Crescimento Ano 3 | CA4: Média Crescimento Ano 4 | CB4: Média Geral
F5: % de Atingimento => | G5: =IF(E3="Conservador",C162,IF(E3="Moderado",C163,IF(E3="Otimista",C164,C163))) -> 0.054 | H5: =SUM(H6:H50)/SUM($D$6:$D$50) -> 0.108 | I5: =SUM(I6:I50)/SUM($D$6:$D$50) -> 0.162 | J5: =SUM(J6:J50)/SUM($D$6:$D$50) -> 0.21546 | K5: =SUM(K6:K50)/SUM($D$6:$D$50) -> 0.269325 | L5: =SUM(L6:L50)/SUM($D$6:$D$50) -> 0.32319 | M5: =SUM(M6:M50)/SUM($D$6:$D$50) -> 0.3749004 | N5: =SUM(N6:N50)/SUM($D$6:$D$50) -> 0.42738646 | O5: =SUM(O6:O50)/SUM($D$6:$D$50) -> 0.4829467 | ... BM5: =SUM(BM6:BM50)/SUM($D$6:$D$50) -> 0.95412328
B6: Limpeza Residencial - 4 horas | C6: =SUM(F52:BL52)/SUM($F$97:$BM$97) -> 0.46612813 | D6: =F6*'Distribuição de Modelos'!$E$50 -> 418.60405 | E6: 200 | F6: 673 | G6: =IFERROR(IF($D6="","",$G$5*$D6),"") -> 22.604619 | H6: =IFERROR(IF($D6="","",IF(G6+(G6*H$4)>$D6,$D6,G6+(G6*H$4))),"") -> 45.209237 | I6: =IFERROR(IF($D6="","",IF(H6+(H6*I$4)>$D6,$D6,H6+(H6*I$4))),"") -> 67.813856 | J6: =IFERROR(IF($D6="","",IF(I6+(I6*J$4)>$D6,$D6,I6+(I6*J$4))),"") -> 90.192428 | K6: =IFERROR(IF($D6="","",IF(J6+(J6*K$4)>$D6,$D6,J6+(J6*K$4))),"") -> 112.74054 | L6: =IFERROR(IF($D6="","",IF(K6+(K6*L$4)>$D6,$D6,K6+(K6*L$4))),"") -> 135.28864 | M6: =IFERROR(IF($D6="","",IF(L6+(L6*M$4)>$D6,$D6,L6+(L6*M$4))),"") -> 156.93483 | N6: =IFERROR(IF($D6="","",IF(M6+(M6*N$4)>$D6,$D6,M6+(M6*N$4))),"") -> 178.9057 | O6: =IFERROR(IF($D6="","",IF(N6+(N6*O$4)>$D6,$D6,N6+(N6*O$4))),"") -> 202.16344 | ... BM6: =IFERROR(IF($D6="","",IF(BL6+(BL6*BM$4)>$D6,$D6,BL6+(BL6*BM$4))),"") -> 399.39987
B7: Limpeza Empresarial 4 horas | C7: =SUM(F53:BL53)/SUM($F$97:$BM$97) -> 0.13090374 | D7: =F7*'Distribuição de Modelos'!$E$50 -> 117.55745 | E7: 56 | F7: 189 | G7: =IFERROR(IF($D7="","",$G$5*$D7),"") -> 6.3481024 | H7: =IFERROR(IF($D7="","",IF(G7+(G7*H$4)>$D7,$D7,G7+(G7*H$4))),"") -> 12.696205 | I7: =IFERROR(IF($D7="","",IF(H7+(H7*I$4)>$D7,$D7,H7+(H7*I$4))),"") -> 19.044307 | J7: =IFERROR(IF($D7="","",IF(I7+(I7*J$4)>$D7,$D7,I7+(I7*J$4))),"") -> 25.328929 | K7: =IFERROR(IF($D7="","",IF(J7+(J7*K$4)>$D7,$D7,J7+(J7*K$4))),"") -> 31.661161 | L7: =IFERROR(IF($D7="","",IF(K7+(K7*L$4)>$D7,$D7,K7+(K7*L$4))),"") -> 37.993393 | M7: =IFERROR(IF($D7="","",IF(L7+(L7*M$4)>$D7,$D7,L7+(L7*M$4))),"") -> 44.072336 | N7: =IFERROR(IF($D7="","",IF(M7+(M7*N$4)>$D7,$D7,M7+(M7*N$4))),"") -> 50.242463 | O7: =IFERROR(IF($D7="","",IF(N7+(N7*O$4)>$D7,$D7,N7+(N7*O$4))),"") -> 56.773983 | ... BM7: =IFERROR(IF($D7="","",IF(BL7+(BL7*BM$4)>$D7,$D7,BL7+(BL7*BM$4))),"") -> 112.1643
B8: Limpeza condominial 4 horas | C8: =SUM(F54:BL54)/SUM($F$97:$BM$97) -> 0.056101603 | D8: =F8*'Distribuição de Modelos'!$E$50 -> 50.381765 | E8: 24 | F8: 81 | G8: =IFERROR(IF($D8="","",$G$5*$D8),"") -> 2.7206153 | H8: =IFERROR(IF($D8="","",IF(G8+(G8*H$4)>$D8,$D8,G8+(G8*H$4))),"") -> 5.4412306 | I8: =IFERROR(IF($D8="","",IF(H8+(H8*I$4)>$D8,$D8,H8+(H8*I$4))),"") -> 8.161846 | J8: =IFERROR(IF($D8="","",IF(I8+(I8*J$4)>$D8,$D8,I8+(I8*J$4))),"") -> 10.855255 | K8: =IFERROR(IF($D8="","",IF(J8+(J8*K$4)>$D8,$D8,J8+(J8*K$4))),"") -> 13.569069 | L8: =IFERROR(IF($D8="","",IF(K8+(K8*L$4)>$D8,$D8,K8+(K8*L$4))),"") -> 16.282883 | M8: =IFERROR(IF($D8="","",IF(L8+(L8*M$4)>$D8,$D8,L8+(L8*M$4))),"") -> 18.888144 | N8: =IFERROR(IF($D8="","",IF(M8+(M8*N$4)>$D8,$D8,M8+(M8*N$4))),"") -> 21.532484 | O8: =IFERROR(IF($D8="","",IF(N8+(N8*O$4)>$D8,$D8,N8+(N8*O$4))),"") -> 24.331707 | ... BM8: =IFERROR(IF($D8="","",IF(BL8+(BL8*BM$4)>$D8,$D8,BL8+(BL8*BM$4))),"") -> 48.070415
B9: Passadoria - 4 horas | C9: =SUM(F55:BL55)/SUM($F$97:$BM$97) -> 0.055105973 | D9: =F9*'Distribuição de Modelos'!$E$50 -> 41.673806 | E9: 20 | F9: 67 | G9: =IFERROR(IF($D9="","",$G$5*$D9),"") -> 2.2503855 | H9: =IFERROR(IF($D9="","",IF(G9+(G9*H$4)>$D9,$D9,G9+(G9*H$4))),"") -> 4.500771 | I9: =IFERROR(IF($D9="","",IF(H9+(H9*I$4)>$D9,$D9,H9+(H9*I$4))),"") -> 6.7511565 | J9: =IFERROR(IF($D9="","",IF(I9+(I9*J$4)>$D9,$D9,I9+(I9*J$4))),"") -> 8.9790382 | K9: =IFERROR(IF($D9="","",IF(J9+(J9*K$4)>$D9,$D9,J9+(J9*K$4))),"") -> 11.223798 | L9: =IFERROR(IF($D9="","",IF(K9+(K9*L$4)>$D9,$D9,K9+(K9*L$4))),"") -> 13.468557 | M9: =IFERROR(IF($D9="","",IF(L9+(L9*M$4)>$D9,$D9,L9+(L9*M$4))),"") -> 15.623526 | N9: =IFERROR(IF($D9="","",IF(M9+(M9*N$4)>$D9,$D9,M9+(M9*N$4))),"") -> 17.81082 | O9: =IFERROR(IF($D9="","",IF(N9+(N9*O$4)>$D9,$D9,N9+(N9*O$4))),"") -> 20.126227 | ... BM9: =IFERROR(IF($D9="","",IF(BL9+(BL9*BM$4)>$D9,$D9,BL9+(BL9*BM$4))),"") -> 39.761948
B10: Limpeza Residencial - 6 horas | C10: =SUM(F56:BL56)/SUM($F$97:$BM$97) -> 0.049088903 | D10: =F10*'Distribuição de Modelos'!$E$50 -> 33.587843 | E10: 16 | F10: 54 | G10: =IFERROR(IF($D10="","",$G$5*$D10),"") -> 1.8137435 | H10: =IFERROR(IF($D10="","",IF(G10+(G10*H$4)>$D10,$D10,G10+(G10*H$4))),"") -> 3.6274871 | I10: =IFERROR(IF($D10="","",IF(H10+(H10*I$4)>$D10,$D10,H10+(H10*I$4))),"") -> 5.4412306 | J10: =IFERROR(IF($D10="","",IF(I10+(I10*J$4)>$D10,$D10,I10+(I10*J$4))),"") -> 7.2368367 | K10: =IFERROR(IF($D10="","",IF(J10+(J10*K$4)>$D10,$D10,J10+(J10*K$4))),"") -> 9.0460459 | L10: =IFERROR(IF($D10="","",IF(K10+(K10*L$4)>$D10,$D10,K10+(K10*L$4))),"") -> 10.855255 | M10: =IFERROR(IF($D10="","",IF(L10+(L10*M$4)>$D10,$D10,L10+(L10*M$4))),"") -> 12.592096 | N10: =IFERROR(IF($D10="","",IF(M10+(M10*N$4)>$D10,$D10,M10+(M10*N$4))),"") -> 14.354989 | O10: =IFERROR(IF($D10="","",IF(N10+(N10*O$4)>$D10,$D10,N10+(N10*O$4))),"") -> 16.221138 | ... BM10: =IFERROR(IF($D10="","",IF(BL10+(BL10*BM$4)>$D10,$D10,BL10+(BL10*BM$4))),"") -> 32.046943
B11: Limpeza Residencial - 8 horas | C11: =SUM(F57:BL57)/SUM($F$97:$BM$97) -> 0.041210437 | D11: =F11*'Distribuição de Modelos'!$E$50 -> 21.147901 | E11: 10 | F11: 34 | G11: =IFERROR(IF($D11="","",$G$5*$D11),"") -> 1.1419867 | H11: =IFERROR(IF($D11="","",IF(G11+(G11*H$4)>$D11,$D11,G11+(G11*H$4))),"") -> 2.2839734 | I11: =IFERROR(IF($D11="","",IF(H11+(H11*I$4)>$D11,$D11,H11+(H11*I$4))),"") -> 3.42596 | J11: =IFERROR(IF($D11="","",IF(I11+(I11*J$4)>$D11,$D11,I11+(I11*J$4))),"") -> 4.5565268 | K11: =IFERROR(IF($D11="","",IF(J11+(J11*K$4)>$D11,$D11,J11+(J11*K$4))),"") -> 5.6956585 | L11: =IFERROR(IF($D11="","",IF(K11+(K11*L$4)>$D11,$D11,K11+(K11*L$4))),"") -> 6.8347903 | M11: =IFERROR(IF($D11="","",IF(L11+(L11*M$4)>$D11,$D11,L11+(L11*M$4))),"") -> 7.9283567 | N11: =IFERROR(IF($D11="","",IF(M11+(M11*N$4)>$D11,$D11,M11+(M11*N$4))),"") -> 9.0383266 | O11: =IFERROR(IF($D11="","",IF(N11+(N11*O$4)>$D11,$D11,N11+(N11*O$4))),"") -> 10.213309 | ... BM11: =IFERROR(IF($D11="","",IF(BL11+(BL11*BM$4)>$D11,$D11,BL11+(BL11*BM$4))),"") -> 20.177705
B12: Limpeza Residencial - 2 horas | C12: =SUM(F58:BL58)/SUM($F$97:$BM$97) -> 0.015194184 | D12: =F12*'Distribuição de Modelos'!$E$50 -> 16.793922 | E12: 8 | F12: 27 | G12: =IFERROR(IF($D12="","",$G$5*$D12),"") -> 0.90687177 | H12: =IFERROR(IF($D12="","",IF(G12+(G12*H$4)>$D12,$D12,G12+(G12*H$4))),"") -> 1.8137435 | I12: =IFERROR(IF($D12="","",IF(H12+(H12*I$4)>$D12,$D12,H12+(H12*I$4))),"") -> 2.7206153 | J12: =IFERROR(IF($D12="","",IF(I12+(I12*J$4)>$D12,$D12,I12+(I12*J$4))),"") -> 3.6184184 | K12: =IFERROR(IF($D12="","",IF(J12+(J12*K$4)>$D12,$D12,J12+(J12*K$4))),"") -> 4.523023 | L12: =IFERROR(IF($D12="","",IF(K12+(K12*L$4)>$D12,$D12,K12+(K12*L$4))),"") -> 5.4276276 | M12: =IFERROR(IF($D12="","",IF(L12+(L12*M$4)>$D12,$D12,L12+(L12*M$4))),"") -> 6.296048 | N12: =IFERROR(IF($D12="","",IF(M12+(M12*N$4)>$D12,$D12,M12+(M12*N$4))),"") -> 7.1774947 | O12: =IFERROR(IF($D12="","",IF(N12+(N12*O$4)>$D12,$D12,N12+(N12*O$4))),"") -> 8.110569 | ... BM12: =IFERROR(IF($D12="","",IF(BL12+(BL12*BM$4)>$D12,$D12,BL12+(BL12*BM$4))),"") -> 16.023472
B13: Babá 4 horas | C13: =SUM(F59:BL59)/SUM($F$97:$BM$97) -> 0.018700534 | D13: =F13*'Distribuição de Modelos'!$E$50 -> 16.793922 | E13: 8 | F13: 27 | G13: =IFERROR(IF($D13="","",$G$5*$D13),"") -> 0.90687177 | H13: =IFERROR(IF($D13="","",IF(G13+(G13*H$4)>$D13,$D13,G13+(G13*H$4))),"") -> 1.8137435 | I13: =IFERROR(IF($D13="","",IF(H13+(H13*I$4)>$D13,$D13,H13+(H13*I$4))),"") -> 2.7206153 | J13: =IFERROR(IF($D13="","",IF(I13+(I13*J$4)>$D13,$D13,I13+(I13*J$4))),"") -> 3.6184184 | K13: =IFERROR(IF($D13="","",IF(J13+(J13*K$4)>$D13,$D13,J13+(J13*K$4))),"") -> 4.523023 | L13: =IFERROR(IF($D13="","",IF(K13+(K13*L$4)>$D13,$D13,K13+(K13*L$4))),"") -> 5.4276276 | M13: =IFERROR(IF($D13="","",IF(L13+(L13*M$4)>$D13,$D13,L13+(L13*M$4))),"") -> 6.296048 | N13: =IFERROR(IF($D13="","",IF(M13+(M13*N$4)>$D13,$D13,M13+(M13*N$4))),"") -> 7.1774947 | O13: =IFERROR(IF($D13="","",IF(N13+(N13*O$4)>$D13,$D13,N13+(N13*O$4))),"") -> 8.110569 | ... BM13: =IFERROR(IF($D13="","",IF(BL13+(BL13*BM$4)>$D13,$D13,BL13+(BL13*BM$4))),"") -> 16.023472
B14: Limpeza Empresarial 8 horas | C14: =SUM(F60:BL60)/SUM($F$97:$BM$97) -> 0.024241433 | D14: =F14*'Distribuição de Modelos'!$E$50 -> 12.439942 | E14: 6 | F14: 20 | G14: =IFERROR(IF($D14="","",$G$5*$D14),"") -> 0.67175687 | H14: =IFERROR(IF($D14="","",IF(G14+(G14*H$4)>$D14,$D14,G14+(G14*H$4))),"") -> 1.3435137 | I14: =IFERROR(IF($D14="","",IF(H14+(H14*I$4)>$D14,$D14,H14+(H14*I$4))),"") -> 2.0152706 | J14: =IFERROR(IF($D14="","",IF(I14+(I14*J$4)>$D14,$D14,I14+(I14*J$4))),"") -> 2.6803099 | K14: =IFERROR(IF($D14="","",IF(J14+(J14*K$4)>$D14,$D14,J14+(J14*K$4))),"") -> 3.3503874 | L14: =IFERROR(IF($D14="","",IF(K14+(K14*L$4)>$D14,$D14,K14+(K14*L$4))),"") -> 4.0204649 | M14: =IFERROR(IF($D14="","",IF(L14+(L14*M$4)>$D14,$D14,L14+(L14*M$4))),"") -> 4.6637392 | N14: =IFERROR(IF($D14="","",IF(M14+(M14*N$4)>$D14,$D14,M14+(M14*N$4))),"") -> 5.3166627 | O14: =IFERROR(IF($D14="","",IF(N14+(N14*O$4)>$D14,$D14,N14+(N14*O$4))),"") -> 6.0078289 | ... BM14: =IFERROR(IF($D14="","",IF(BL14+(BL14*BM$4)>$D14,$D14,BL14+(BL14*BM$4))),"") -> 11.869238
B15: Passadoria - 6 horas | C15: =SUM(F61:BL61)/SUM($F$97:$BM$97) -> 0.017661616 | D15: =F15*'Distribuição de Modelos'!$E$50 -> 10.573951 | E15: 5 | F15: 17 | G15: =IFERROR(IF($D15="","",$G$5*$D15),"") -> 0.57099334 | H15: =IFERROR(IF($D15="","",IF(G15+(G15*H$4)>$D15,$D15,G15+(G15*H$4))),"") -> 1.1419867 | I15: =IFERROR(IF($D15="","",IF(H15+(H15*I$4)>$D15,$D15,H15+(H15*I$4))),"") -> 1.71298 | J15: =IFERROR(IF($D15="","",IF(I15+(I15*J$4)>$D15,$D15,I15+(I15*J$4))),"") -> 2.2782634 | K15: =IFERROR(IF($D15="","",IF(J15+(J15*K$4)>$D15,$D15,J15+(J15*K$4))),"") -> 2.8478293 | L15: =IFERROR(IF($D15="","",IF(K15+(K15*L$4)>$D15,$D15,K15+(K15*L$4))),"") -> 3.4173951 | M15: =IFERROR(IF($D15="","",IF(L15+(L15*M$4)>$D15,$D15,L15+(L15*M$4))),"") -> 3.9641783 | N15: =IFERROR(IF($D15="","",IF(M15+(M15*N$4)>$D15,$D15,M15+(M15*N$4))),"") -> 4.5191633 | O15: =IFERROR(IF($D15="","",IF(N15+(N15*O$4)>$D15,$D15,N15+(N15*O$4))),"") -> 5.1066545 | ... BM15: =IFERROR(IF($D15="","",IF(BL15+(BL15*BM$4)>$D15,$D15,BL15+(BL15*BM$4))),"") -> 10.088853
B16: Limpeza Empresarial 6 horas | C16: =SUM(F62:BL62)/SUM($F$97:$BM$97) -> 0.015453914 | D16: =F16*'Distribuição de Modelos'!$E$50 -> 10.573951 | E16: 5 | F16: 17 | G16: =IFERROR(IF($D16="","",$G$5*$D16),"") -> 0.57099334 | H16: =IFERROR(IF($D16="","",IF(G16+(G16*H$4)>$D16,$D16,G16+(G16*H$4))),"") -> 1.1419867 | I16: =IFERROR(IF($D16="","",IF(H16+(H16*I$4)>$D16,$D16,H16+(H16*I$4))),"") -> 1.71298 | J16: =IFERROR(IF($D16="","",IF(I16+(I16*J$4)>$D16,$D16,I16+(I16*J$4))),"") -> 2.2782634 | K16: =IFERROR(IF($D16="","",IF(J16+(J16*K$4)>$D16,$D16,J16+(J16*K$4))),"") -> 2.8478293 | L16: =IFERROR(IF($D16="","",IF(K16+(K16*L$4)>$D16,$D16,K16+(K16*L$4))),"") -> 3.4173951 | M16: =IFERROR(IF($D16="","",IF(L16+(L16*M$4)>$D16,$D16,L16+(L16*M$4))),"") -> 3.9641783 | N16: =IFERROR(IF($D16="","",IF(M16+(M16*N$4)>$D16,$D16,M16+(M16*N$4))),"") -> 4.5191633 | O16: =IFERROR(IF($D16="","",IF(N16+(N16*O$4)>$D16,$D16,N16+(N16*O$4))),"") -> 5.1066545 | ... BM16: =IFERROR(IF($D16="","",IF(BL16+(BL16*BM$4)>$D16,$D16,BL16+(BL16*BM$4))),"") -> 10.088853
B17: Limpeza condominial 2 horas | C17: =SUM(F63:BL63)/SUM($F$97:$BM$97) -> 0.0095667085 | D17: =F17*'Distribuição de Modelos'!$E$50 -> 10.573951 | E17: 5 | F17: 17 | G17: =IFERROR(IF($D17="","",$G$5*$D17),"") -> 0.57099334 | H17: =IFERROR(IF($D17="","",IF(G17+(G17*H$4)>$D17,$D17,G17+(G17*H$4))),"") -> 1.1419867 | I17: =IFERROR(IF($D17="","",IF(H17+(H17*I$4)>$D17,$D17,H17+(H17*I$4))),"") -> 1.71298 | J17: =IFERROR(IF($D17="","",IF(I17+(I17*J$4)>$D17,$D17,I17+(I17*J$4))),"") -> 2.2782634 | K17: =IFERROR(IF($D17="","",IF(J17+(J17*K$4)>$D17,$D17,J17+(J17*K$4))),"") -> 2.8478293 | L17: =IFERROR(IF($D17="","",IF(K17+(K17*L$4)>$D17,$D17,K17+(K17*L$4))),"") -> 3.4173951 | M17: =IFERROR(IF($D17="","",IF(L17+(L17*M$4)>$D17,$D17,L17+(L17*M$4))),"") -> 3.9641783 | N17: =IFERROR(IF($D17="","",IF(M17+(M17*N$4)>$D17,$D17,M17+(M17*N$4))),"") -> 4.5191633 | O17: =IFERROR(IF($D17="","",IF(N17+(N17*O$4)>$D17,$D17,N17+(N17*O$4))),"") -> 5.1066545 | ... BM17: =IFERROR(IF($D17="","",IF(BL17+(BL17*BM$4)>$D17,$D17,BL17+(BL17*BM$4))),"") -> 10.088853
... B50: Garçom 8 horas | C50: =SUM(F96:BL96)/SUM($F$97:$BM$97) -> 0 | D50: =F50*'Distribuição de Modelos'!$E$50 -> 0 | E50: 0 | F50: 0 | G50: =IFERROR(IF($D50="","",$G$5*$D50),"") -> 0 | H50: =IFERROR(IF($D50="","",IF(G50+(G50*H$4)>$D50,$D50,G50+(G50*H$4))),"") -> 0 | I50: =IFERROR(IF($D50="","",IF(H50+(H50*I$4)>$D50,$D50,H50+(H50*I$4))),"") -> 0 | J50: =IFERROR(IF($D50="","",IF(I50+(I50*J$4)>$D50,$D50,I50+(I50*J$4))),"") -> 0 | K50: =IFERROR(IF($D50="","",IF(J50+(J50*K$4)>$D50,$D50,J50+(J50*K$4))),"") -> 0 | L50: =IFERROR(IF($D50="","",IF(K50+(K50*L$4)>$D50,$D50,K50+(K50*L$4))),"") -> 0 | M50: =IFERROR(IF($D50="","",IF(L50+(L50*M$4)>$D50,$D50,L50+(L50*M$4))),"") -> 0 | N50: =IFERROR(IF($D50="","",IF(M50+(M50*N$4)>$D50,$D50,M50+(M50*N$4))),"") -> 0 | O50: =IFERROR(IF($D50="","",IF(N50+(N50*O$4)>$D50,$D50,N50+(N50*O$4))),"") -> 0 | ... BM50: =IFERROR(IF($D50="","",IF(BL50+(BL50*BM$4)>$D50,$D50,BL50+(BL50*BM$4))),"") -> 0
B51: Faturamento Bruto | C51: Preço Médio de Venda em R$ | D51: Receita Potencial | E51: Receita Média | BO51: R$ | BP51: R$ | BQ51: R$ | BR51: R$
B52: =B6 -> Limpeza Residencial - 4 horas | C52: 160 | D52: =IFERROR(C52*D6,"") -> 66976.648 | E52: =IFERROR(AVERAGE(G52:BL52),"") -> 41679.449 | G52: =$C52*G6 -> 3616.739 | H52: =$C52*H6 -> 7233.478 | I52: =$C52*I6 -> 10850.217 | J52: =$C52*J6 -> 14430.789 | K52: =$C52*K6 -> 18038.486 | L52: =$C52*L6 -> 21646.183 | M52: =$C52*M6 -> 25109.572 | N52: =$C52*N6 -> 28624.912 | ... BM52: =$C52*BM6 -> 63903.979
B53: =B7 -> Limpeza Empresarial 4 horas | C53: 160 | D53: =IFERROR(C53*D7,"") -> 18809.192 | E53: =IFERROR(AVERAGE(G53:BL53),"") -> 11704.927 | G53: =$C53*G7 -> 1015.6964 | H53: =$C53*H7 -> 2031.3928 | I53: =$C53*I7 -> 3047.0892 | J53: =$C53*J7 -> 4052.6286 | K53: =$C53*K7 -> 5065.7857 | L53: =$C53*L7 -> 6078.9429 | M53: =$C53*M7 -> 7051.5737 | N53: =$C53*N7 -> 8038.794 | ... BM53: =$C53*BM7 -> 17946.288
B54: =B8 -> Limpeza condominial 4 horas | C54: 160 | D54: =IFERROR(C54*D8,"") -> 8061.0824 | E54: =IFERROR(AVERAGE(G54:BL54),"") -> 5016.3972 | G54: =$C54*G8 -> 435.29845 | H54: =$C54*H8 -> 870.5969 | I54: =$C54*I8 -> 1305.8954 | J54: =$C54*J8 -> 1736.8408 | K54: =$C54*K8 -> 2171.051 | L54: =$C54*L8 -> 2605.2612 | M54: =$C54*M8 -> 3022.103 | N54: =$C54*N8 -> 3445.1974 | ... BM54: =$C54*BM8 -> 7691.2664
B55: =B9 -> Passadoria - 4 horas | C55: 190 | D55: =IFERROR(C55*D9,"") -> 7918.0231 | E55: =IFERROR(AVERAGE(G55:BL55),"") -> 4927.3717 | G55: =$C55*G9 -> 427.57325 | H55: =$C55*H9 -> 855.14649 | I55: =$C55*I9 -> 1282.7197 | J55: =$C55*J9 -> 1706.0173 | K55: =$C55*K9 -> 2132.5216 | L55: =$C55*L9 -> 2559.0259 | M55: =$C55*M9 -> 2968.47 | N55: =$C55*N9 -> 3384.0558 | ... BM55: =$C55*BM9 -> 7554.7702
B56: =B10 -> Limpeza Residencial - 6 horas | C56: 210 | D56: =IFERROR(C56*D10,"") -> 7053.4471 | E56: =IFERROR(AVERAGE(G56:BL56),"") -> 4389.3476 | G56: =$C56*G10 -> 380.88614 | H56: =$C56*H10 -> 761.77229 | I56: =$C56*I10 -> 1142.6584 | J56: =$C56*J10 -> 1519.7357 | K56: =$C56*K10 -> 1899.6696 | L56: =$C56*L10 -> 2279.6036 | M56: =$C56*M10 -> 2644.3401 | N56: =$C56*N10 -> 3014.5478 | ... BM56: =$C56*BM10 -> 6729.8581
B57: =B11 -> Limpeza Residencial - 8 horas | C57: 280 | D57: =IFERROR(C57*D11,"") -> 5921.4124 | E57: =IFERROR(AVERAGE(G57:BL57),"") -> 3684.8844 | G57: =$C57*G11 -> 319.75627 | H57: =$C57*H11 -> 639.51254 | I57: =$C57*I11 -> 959.26881 | J57: =$C57*J11 -> 1275.8275 | K57: =$C57*K11 -> 1594.7844 | L57: =$C57*L11 -> 1913.7413 | M57: =$C57*M11 -> 2219.9399 | N57: =$C57*N11 -> 2530.7315 | ... BM57: =$C57*BM11 -> 5649.7574
B58: =B12 -> Limpeza Residencial - 2 horas | C58: 130 | D58: =IFERROR(C58*D12,"") -> 2183.2098 | E58: =IFERROR(AVERAGE(G58:BL58),"") -> 1358.6076 | G58: =$C58*G12 -> 117.89333 | H58: =$C58*H12 -> 235.78666 | I58: =$C58*I12 -> 353.67999 | J58: =$C58*J12 -> 470.39439 | K58: =$C58*K12 -> 587.99299 | L58: =$C58*L12 -> 705.59158 | M58: =$C58*M12 -> 818.48624 | N58: =$C58*N12 -> 933.07431 | ... BM58: =$C58*BM12 -> 2083.0513
B59: =B13 -> Babá 4 horas | C59: 160 | D59: =IFERROR(C59*D13,"") -> 2687.0275 | E59: =IFERROR(AVERAGE(G59:BL59),"") -> 1672.1324 | G59: =$C59*G13 -> 145.09948 | H59: =$C59*H13 -> 290.19897 | I59: =$C59*I13 -> 435.29845 | J59: =$C59*J13 -> 578.94694 | K59: =$C59*K13 -> 723.68367 | L59: =$C59*L13 -> 868.42041 | M59: =$C59*M13 -> 1007.3677 | N59: =$C59*N13 -> 1148.3991 | ... BM59: =$C59*BM13 -> 2563.7555
B60: =B14 -> Limpeza Empresarial 8 horas | C60: 280 | D60: =IFERROR(C60*D14,"") -> 3483.1838 | E60: =IFERROR(AVERAGE(G60:BL60),"") -> 2167.5791 | G60: =$C60*G14 -> 188.09192 | H60: =$C60*H14 -> 376.18385 | I60: =$C60*I14 -> 564.27577 | J60: =$C60*J14 -> 750.48677 | K60: =$C60*K14 -> 938.10847 | L60: =$C60*L14 -> 1125.7302 | M60: =$C60*M14 -> 1305.847 | N60: =$C60*N14 -> 1488.6656 | ... BM60: =$C60*BM14 -> 3323.3867
B61: =B15 -> Passadoria - 6 horas | C61: 240 | D61: =IFERROR(C61*D15,"") -> 2537.7482 | E61: =IFERROR(AVERAGE(G61:BL61),"") -> 1579.2362 | G61: =$C61*G15 -> 137.0384 | H61: =$C61*H15 -> 274.0768 | I61: =$C61*I15 -> 411.1152 | J61: =$C61*J15 -> 546.78322 | K61: =$C61*K15 -> 683.47903 | L61: =$C61*L15 -> 820.17483 | M61: =$C61*M15 -> 951.4028 | N61: =$C61*N15 -> 1084.5992 | ... BM61: =$C61*BM15 -> 2421.3246
B62: =B16 -> Limpeza Empresarial 6 horas | C62: 210 | D62: =IFERROR(C62*D16,"") -> 2220.5296 | E62: =IFERROR(AVERAGE(G62:BL62),"") -> 1381.8316 | G62: =$C62*G16 -> 119.9086 | H62: =$C62*H16 -> 239.8172 | I62: =$C62*I16 -> 359.7258 | J62: =$C62*J16 -> 478.43532 | K62: =$C62*K16 -> 598.04415 | L62: =$C62*L16 -> 717.65298 | M62: =$C62*M16 -> 832.47745 | N62: =$C62*N16 -> 949.0243 | ... BM62: =$C62*BM16 -> 2118.659
B63: =B17 -> Limpeza condominial 2 horas | C63: 130 | D63: =IFERROR(C63*D17,"") -> 1374.6136 | E63: =IFERROR(AVERAGE(G63:BL63),"") -> 855.41959 | G63: =$C63*G17 -> 74.229134 | H63: =$C63*H17 -> 148.45827 | I63: =$C63*I17 -> 222.6874 | J63: =$C63*J17 -> 296.17424 | K63: =$C63*K17 -> 370.21781 | L63: =$C63*L17 -> 444.26137 | M63: =$C63*M17 -> 515.34319 | N63: =$C63*N17 -> 587.49123 | ... BM63: =$C63*BM17 -> 1311.5508
... B96: =B50 -> Garçom 8 horas | C96: 280 | D96: =IFERROR(C96*D50,"") -> 0 | E96: =IFERROR(AVERAGE(G96:BL96),"") -> 0 | G96: =$C96*G50 -> 0 | H96: =$C96*H50 -> 0 | I96: =$C96*I50 -> 0 | J96: =$C96*J50 -> 0 | K96: =$C96*K50 -> 0 | L96: =$C96*L50 -> 0 | M96: =$C96*M50 -> 0 | N96: =$C96*N50 -> 0 | ... BM96: =$C96*BM50 -> 0
B97: Receita Total Mês (Potencial / Média) | D97: =SUM(D52:D96) -> 139986.67 | E97: =SUM(E52:E96) -> 87113.454 | G97: =SUM(G52:G96) -> 7559.28 | H97: =SUM(H52:H96) -> 15118.56 | I97: =SUM(I52:I96) -> 22677.84 | J97: =SUM(J52:J96) -> 30161.527 | K97: =SUM(K52:K96) -> 37701.909 | L97: =SUM(L52:L96) -> 45242.291 | M97: =SUM(M52:M96) -> 52481.058 | N97: =SUM(N52:N96) -> 59828.406 | ... BM97: =SUM(BM52:BM96) -> 133564.54 | BO97: =SUMIF($F$2:$BA$2,BO$2,$F97:$BA97) -> 495966.78 | BP97: =SUMIF($F$2:$BA$2,BP$2,$F97:$BA97) -> 952559.81 | BQ97: =SUMIF($F$2:$BA$2,BQ$2,$F97:$BA97) -> 1141483.9 | BR97: =SUMIF($F$2:$BA$2,BR$2,$F97:$BA97) -> 1237951.5 | BS97: =SUM(BS52:BS96) -> 0
B98: Ticket Médio | C98: 150
B99: Quantidade de Clientes | G99: =G97/$C$98 -> 50.3952 | H99: =H97/$C$98 -> 100.7904 | I99: =I97/$C$98 -> 151.1856 | J99: =J97/$C$98 -> 201.07685 | K99: =K97/$C$98 -> 251.34606 | L99: =L97/$C$98 -> 301.61527 | M99: =M97/$C$98 -> 349.87372 | N99: =N97/$C$98 -> 398.85604 | ... BM99: =BM97/$C$98 -> 890.43026
E100: 1300 atendimentos máximo em Erechim 100k habitantes | G100: 85 | H100: 170 | I100: 220 | J100: 270 | K100: 320 | L100: 370 | M100: 420 | N100: 470 | O100: 520 | P100: 570 | Q100: 620
B101: Detalhamento CSP | C101: CSP $ | D101: CSP % | F101: 1 | G101: 2 | H101: 3 | I101: 4 | J101: 5 | K101: 6 | L101: 7 | M101: 8 | N101: 9 | O101: 10 | P101: 11 | Q101: 12 | R101: 13 | S101: 14 | T101: 15 | U101: 16 | V101: 17 | W101: 18 | X101: 19 | Y101: 20 | Z101: 21 | AA101: 22 | AB101: 23 | AC101: 24 | AD101: 25 | AE101: 26 | AF101: 27 | AG101: 28 | AH101: 29 | AI101: 30 | AJ101: 31 | AK101: 32 | AL101: 33 | AM101: 34 | AN101: 35 | AO101: 36 | AP101: 37 | AQ101: 38 | AR101: 39 | AS101: 40 | AT101: 41 | AU101: 42 | AV101: 43 | AW101: 44 | AX101: 45 | AY101: 46 | AZ101: 47 | BA101: 48 | BB101: 49 | BC101: 50 | BD101: 51 | BE101: 52 | BF101: 53 | BG101: 54 | BH101: 55 | BI101: 56 | BJ101: 57 | BK101: 58 | BL101: 59 | BM101: 60
B102: =B6 -> Limpeza Residencial - 4 horas | C102: 85 | D102: =C102/C52 -> 0.53125 | G102: =G52*$D102 -> 1921.3926 | H102: =H52*$D102 -> 3842.7852 | I102: =I52*$D102 -> 5764.1777 | J102: =J52*$D102 -> 7666.3564 | K102: =K52*$D102 -> 9582.9455 | L102: =L52*$D102 -> 11499.535 | M102: =M52*$D102 -> 13339.46 | N102: =N52*$D102 -> 15206.985 | ... BM102: =BM52*$D102 -> 33948.989
B103: =B7 -> Limpeza Empresarial 4 horas | C103: 85 | D103: =C103/C53 -> 0.53125 | G103: =G53*$D103 -> 539.5887 | H103: =H53*$D103 -> 1079.1774 | I103: =I53*$D103 -> 1618.7661 | J103: =J53*$D103 -> 2152.9589 | K103: =K53*$D103 -> 2691.1987 | L103: =L53*$D103 -> 3229.4384 | M103: =M53*$D103 -> 3746.1485 | N103: =N53*$D103 -> 4270.6093 | ... BM103: =BM53*$D103 -> 9533.9657
B104: =B8 -> Limpeza condominial 4 horas | C104: 85 | D104: =C104/C54 -> 0.53125 | G104: =G54*$D104 -> 231.2523 | H104: =H54*$D104 -> 462.5046 | I104: =I54*$D104 -> 693.75691 | J104: =J54*$D104 -> 922.69668 | K104: =K54*$D104 -> 1153.3709 | L104: =L54*$D104 -> 1384.045 | M104: =M54*$D104 -> 1605.4922 | N104: =N54*$D104 -> 1830.2611 | ... BM104: =BM54*$D104 -> 4085.9853
B105: =B9 -> Passadoria - 4 horas | C105: 100 | D105: =C105/C55 -> 0.52631579 | G105: =G55*$D105 -> 225.03855 | H105: =H55*$D105 -> 450.0771 | I105: =I55*$D105 -> 675.11565 | J105: =J55*$D105 -> 897.90382 | K105: =K55*$D105 -> 1122.3798 | L105: =L55*$D105 -> 1346.8557 | M105: =M55*$D105 -> 1562.3526 | N105: =N55*$D105 -> 1781.082 | ... BM105: =BM55*$D105 -> 3976.1948
B106: =B10 -> Limpeza Residencial - 6 horas | C106: 125 | D106: =C106/C56 -> 0.5952381 | G106: =G56*$D106 -> 226.71794 | H106: =H56*$D106 -> 453.43589 | I106: =I56*$D106 -> 680.15383 | J106: =J56*$D106 -> 904.60459 | K106: =K56*$D106 -> 1130.7557 | L106: =L56*$D106 -> 1356.9069 | M106: =M56*$D106 -> 1574.012 | N106: =N56*$D106 -> 1794.3737 | ... BM106: =BM56*$D106 -> 4005.8679
B107: =B11 -> Limpeza Residencial - 8 horas | C107: 160 | D107: =C107/C57 -> 0.57142857 | G107: =G57*$D107 -> 182.71787 | H107: =H57*$D107 -> 365.43574 | I107: =I57*$D107 -> 548.1536 | J107: =J57*$D107 -> 729.04429 | K107: =K57*$D107 -> 911.30537 | L107: =L57*$D107 -> 1093.5664 | M107: =M57*$D107 -> 1268.5371 | N107: =N57*$D107 -> 1446.1323 | ... BM107: =BM57*$D107 -> 3228.4328
B108: =B12 -> Limpeza Residencial - 2 horas | C108: 65 | D108: =C108/C58 -> 0.5 | G108: =G58*$D108 -> 58.946665 | H108: =H58*$D108 -> 117.89333 | I108: =I58*$D108 -> 176.84 | J108: =J58*$D108 -> 235.19719 | K108: =K58*$D108 -> 293.99649 | L108: =L58*$D108 -> 352.79579 | M108: =M58*$D108 -> 409.24312 | N108: =N58*$D108 -> 466.53715 | ... BM108: =BM58*$D108 -> 1041.5257
B109: =B13 -> Babá 4 horas | C109: 85 | D109: =C109/C59 -> 0.53125 | G109: =G59*$D109 -> 77.084101 | H109: =H59*$D109 -> 154.1682 | I109: =I59*$D109 -> 231.2523 | J109: =J59*$D109 -> 307.56556 | K109: =K59*$D109 -> 384.45695 | L109: =L59*$D109 -> 461.34834 | M109: =M59*$D109 -> 535.16408 | N109: =N59*$D109 -> 610.08705 | ... BM109: =BM59*$D109 -> 1361.9951
B110: =B14 -> Limpeza Empresarial 8 horas | C110: 160 | D110: =C110/C60 -> 0.57142857 | G110: =G60*$D110 -> 107.4811 | H110: =H60*$D110 -> 214.9622 | I110: =I60*$D110 -> 322.4433 | J110: =J60*$D110 -> 428.84958 | K110: =K60*$D110 -> 536.06198 | L110: =L60*$D110 -> 643.27438 | M110: =M60*$D110 -> 746.19828 | N110: =N60*$D110 -> 850.66604 | ... BM110: =BM60*$D110 -> 1899.0781
B111: =B15 -> Passadoria - 6 horas | C111: 140 | D111: =C111/C61 -> 0.58333333 | G111: =G61*$D111 -> 79.939067 | H111: =H61*$D111 -> 159.87813 | I111: =I61*$D111 -> 239.8172 | J111: =J61*$D111 -> 318.95688 | K111: =K61*$D111 -> 398.6961 | L111: =L61*$D111 -> 478.43532 | M111: =M61*$D111 -> 554.98497 | N111: =N61*$D111 -> 632.68286 | ... BM111: =BM61*$D111 -> 1412.4394
B112: =B16 -> Limpeza Empresarial 6 horas | C112: 125 | D112: =C112/C62 -> 0.5952381 | G112: =G62*$D112 -> 71.374167 | H112: =H62*$D112 -> 142.74833 | I112: =I62*$D112 -> 214.1225 | J112: =J62*$D112 -> 284.78293 | K112: =K62*$D112 -> 355.97866 | L112: =L62*$D112 -> 427.17439 | M112: =M62*$D112 -> 495.52229 | N112: =N62*$D112 -> 564.89541 | ... BM112: =BM62*$D112 -> 1261.1066
B113: =B17 -> Limpeza condominial 2 horas | C113: 65 | D113: =C113/C63 -> 0.5 | G113: =G63*$D113 -> 37.114567 | H113: =H63*$D113 -> 74.229134 | I113: =I63*$D113 -> 111.3437 | J113: =J63*$D113 -> 148.08712 | K113: =K63*$D113 -> 185.1089 | L113: =L63*$D113 -> 222.13068 | M113: =M63*$D113 -> 257.67159 | N113: =N63*$D113 -> 293.74562 | ... BM113: =BM63*$D113 -> 655.77542
... B146: =B50 -> Garçom 8 horas | C146: 160 | D146: =C146/C96 -> 0.57142857 | G146: =G96*$D146 -> 0 | H146: =H96*$D146 -> 0 | I146: =I96*$D146 -> 0 | J146: =J96*$D146 -> 0 | K146: =K96*$D146 -> 0 | L146: =L96*$D146 -> 0 | M146: =M96*$D146 -> 0 | N146: =N96*$D146 -> 0 | ... BM146: =BM96*$D146 -> 0
B147: CSP Sub-TOTAL | G147: =SUM(G102:G146) -> 4072.526 | H147: =SUM(H102:H146) -> 8145.052 | I147: =SUM(I102:I146) -> 12217.578 | J147: =SUM(J102:J146) -> 16249.379 | K147: =SUM(K102:K146) -> 20311.723 | L147: =SUM(L102:L146) -> 24374.068 | M147: =SUM(M102:M146) -> 28273.919 | N147: =SUM(N102:N146) -> 32232.268 | ... BM147: =SUM(BM102:BM146) -> 71957.257 | BO147: =SUM(BO102:BO146) -> 0 | BP147: =SUM(BP102:BP146) -> 0 | BQ147: =SUM(BQ102:BQ146) -> 0 | BR147: =SUM(BR102:BR146) -> 0 | BS147: =SUM(BS102:BS146) -> 0
B149: Desperdício Pratos | G149: =$C$149*SUM(G102:G127) -> 0 | H149: =$C$149*SUM(H102:H127) -> 0 | I149: =$C$149*SUM(I102:I127) -> 0 | J149: =$C$149*SUM(J102:J127) -> 0 | K149: =$C$149*SUM(K102:K127) -> 0 | L149: =$C$149*SUM(L102:L127) -> 0 | M149: =$C$149*SUM(M102:M127) -> 0 | N149: =$C$149*SUM(N102:N127) -> 0 | ... CC149: =$C$149*SUM(CC102:CC127) -> 0
B150: Desperdício Cerveja | G150: =$C$150*SUM(G128:G146) -> 0 | H150: =$C$150*SUM(H128:H146) -> 0 | I150: =$C$150*SUM(I128:I146) -> 0 | J150: =$C$150*SUM(J128:J146) -> 0 | K150: =$C$150*SUM(K128:K146) -> 0 | L150: =$C$150*SUM(L128:L146) -> 0 | M150: =$C$150*SUM(M128:M146) -> 0 | N150: =$C$150*SUM(N128:N146) -> 0 | ... CC150: =$C$150*SUM(CC128:CC146) -> 0
B152: CSP TOTAL | G152: =G147+G149+G150 -> 4072.526 | H152: =H147+H149+H150 -> 8145.052 | I152: =I147+I149+I150 -> 12217.578 | J152: =J147+J149+J150 -> 16249.379 | K152: =K147+K149+K150 -> 20311.723 | L152: =L147+L149+L150 -> 24374.068 | M152: =M147+M149+M150 -> 28273.919 | N152: =N147+N149+N150 -> 32232.268 | ... CC152: =CC147+CC149+CC150 -> 0
B154: CSP TOTAL % | G154: =G152/G97 -> 0.53874522 | H154: =H152/H97 -> 0.53874522 | I154: =I152/I97 -> 0.53874522 | J154: =J152/J97 -> 0.53874522 | K154: =K152/K97 -> 0.53874522 | L154: =L152/L97 -> 0.53874522 | M154: =M152/M97 -> 0.53874522 | N154: =N152/N97 -> 0.53874522 | ... BM154: =BM152/BM97 -> 0.53874522
B161: CENÁRIO
B162: Conservador | C162: 0.054
B163: Moderado | C163: 0.065
B164: Otimista | C164: 0.085
B169: OBSERVAÇÃO
B170: Obs.: Esta planilha não configura compromisso ou projeção de resultado, os quais dependerão do esforço e dedicação de cada Franqueado.
G198: Ano 1 | H198: Ano 1 | I198: Ano 1 | J198: Ano 1 | K198: Ano 1 | L198: Ano 1 | M198: Ano 1 | N198: Ano 1 | O198: Ano 1 | P198: Ano 1 | Q198: Ano 1 | R198: Ano 2 | S198: Ano 2 | T198: Ano 2 | U198: Ano 2 | V198: Ano 2 | W198: Ano 2 | X198: Ano 2 | Y198: Ano 2 | Z198: Ano 2 | AA198: Ano 2 | AB198: Ano 2 | AC198: Ano 2 | AD198: Ano 3 | AE198: Ano 3 | AF198: Ano 3 | AG198: Ano 3 | AH198: Ano 3 | AI198: Ano 3 | AJ198: Ano 3 | AK198: Ano 3 | AL198: Ano 3 | AM198: Ano 3 | AN198: Ano 3 | AO198: Ano 3 | AP198: Ano 4 | AQ198: Ano 4 | AR198: Ano 4 | AS198: Ano 4 | AT198: Ano 4 | AU198: Ano 4 | AV198: Ano 4 | AW198: Ano 4 | AX198: Ano 4 | AY198: Ano 4 | AZ198: Ano 4 | BA198: Ano 4 | BB198: Ano 5 | BC198: Ano 5 | BD198: Ano 5 | BE198: Ano 5 | BF198: Ano 5 | BG198: Ano 5 | BH198: Ano 5 | BI198: Ano 5 | BJ198: Ano 5 | BK198: Ano 5 | BL198: Ano 5 | BM198: Ano 5
G199: Fev | H199: Mar | I199: Abr | J199: Mai | K199: Jun | L199: Jul | M199: Ago | N199: Set | O199: Out | P199: Nov | Q199: Dez | R199: Jan | S199: Fev | T199: Mar | U199: Abr | V199: Mai | W199: Jun | X199: Jul | Y199: Ago | Z199: Set | AA199: Out | AB199: Nov | AC199: Dez | AD199: Jan | AE199: Fev | AF199: Mar | AG199: Abr | AH199: Mai | AI199: Jun | AJ199: Jul | AK199: Ago | AL199: Set | AM199: Out | AN199: Nov | AO199: Dez | AP199: Jan | AQ199: Fev | AR199: Mar | AS199: Abr | AT199: Mai | AU199: Jun | AV199: Jul | AW199: Ago | AX199: Set | AY199: Out | AZ199: Nov | BA199: Dez | BB199: Jan | BC199: Fev | BD199: Mar | BE199: Abr | BF199: Mai | BG199: Jun | BH199: Jul | BI199: Ago | BJ199: Set | BK199: Out | BL199: Nov | BM199: Dez
C200: Funcionário | D200: Parâmetro | F200: Quantidade
C201: Atendente | D201: A cada | E201: 400 | F201: 1 | G201: =IF(G99<=$E$201,$F$201,$F$201+1) -> 1 | H201: =IF(H99<=$E$201,$F$201,$F$201+1) -> 1 | I201: =IF(I99<=$E$201,$F$201,$F$201+1) -> 1 | J201: =IF(J99<=$E$201,$F$201,$F$201+1) -> 1 | K201: =IF(K99<=$E$201,$F$201,$F$201+1) -> 1 | L201: =IF(L99<=$E$201,$F$201,$F$201+1) -> 1 | M201: =IF(M99<=$E$201,$F$201,$F$201+1) -> 1 | N201: =IF(N99<=$E$201,$F$201,$F$201+1) -> 1 | ... BM201: =IF(BM99<=$E$201,$F$201,$F$201+1) -> 2
C203: Total Funcionários
C204: Atendente | Q204: =Q201 -> 2 | AC204: =AC201 -> 2 | AO204: =AO201 -> 2 | BA204: =BA201 -> 2 | BM204: =BM201 -> 2

Sheet Receitas_2
C1: SIMULAÇÃO DE FORMAÇÃO DA RECEITA
F2: Ano 1 | G2: Ano 1 | H2: Ano 1 | I2: Ano 1 | J2: Ano 1 | K2: Ano 1 | L2: Ano 1 | M2: Ano 1 | N2: Ano 1 | O2: Ano 1 | P2: Ano 1 | Q2: Ano 1 | R2: Ano 2 | S2: Ano 2 | T2: Ano 2 | U2: Ano 2 | V2: Ano 2 | W2: Ano 2 | X2: Ano 2 | Y2: Ano 2 | Z2: Ano 2 | AA2: Ano 2 | AB2: Ano 2 | AC2: Ano 2 | AD2: Ano 3 | AE2: Ano 3 | AF2: Ano 3 | AG2: Ano 3 | AH2: Ano 3 | AI2: Ano 3 | AJ2: Ano 3 | AK2: Ano 3 | AL2: Ano 3 | AM2: Ano 3 | AN2: Ano 3 | AO2: Ano 3 | AP2: Ano 4 | AQ2: Ano 4 | AR2: Ano 4 | AS2: Ano 4 | AT2: Ano 4 | AU2: Ano 4 | AV2: Ano 4 | AW2: Ano 4 | AX2: Ano 4 | AY2: Ano 4 | AZ2: Ano 4 | BA2: Ano 4 | BB2: Ano 5 | BC2: Ano 5 | BD2: Ano 5 | BE2: Ano 5 | BF2: Ano 5 | BG2: Ano 5 | BH2: Ano 5 | BI2: Ano 5 | BJ2: Ano 5 | BK2: Ano 5 | BL2: Ano 5 | BM2: Ano 5 | BO2: Ano 1 | BP2: Ano 2 | BQ2: Ano 3 | BR2: Ano 4 | BS2: Ano 5
D3: Cenário | E3: Moderado | F3: Jan | G3: Fev | H3: Mar | I3: Abr | J3: Mai | K3: Jun | L3: Jul | M3: Ago | N3: Set | O3: Out | P3: Nov | Q3: Dez | R3: Jan | S3: Fev | T3: Mar | U3: Abr | V3: Mai | W3: Jun | X3: Jul | Y3: Ago | Z3: Set | AA3: Out | AB3: Nov | AC3: Dez | AD3: Jan | AE3: Fev | AF3: Mar | AG3: Abr | AH3: Mai | AI3: Jun | AJ3: Jul | AK3: Ago | AL3: Set | AM3: Out | AN3: Nov | AO3: Dez | AP3: Jan | AQ3: Fev | AR3: Mar | AS3: Abr | AT3: Mai | AU3: Jun | AV3: Jul | AW3: Ago | AX3: Set | AY3: Out | AZ3: Nov | BA3: Dez | BB3: Jan | BC3: Fev | BD3: Mar | BE3: Abr | BF3: Mai | BG3: Jun | BH3: Jul | BI3: Ago | BJ3: Set | BK3: Out | BL3: Nov | BM3: Dez
B4: Quantidades vendidas | C4: Representatividade nas Vendas em % nos 5 anos | D4: Potencial TOTAL | E4: Quantidade Média Vendida | F4: IMPLANTAÇÃO | H4: Crescimento vs. Mês Anterior => | BO4: unidades | BP4: unidades | BQ4: unidades | BR4: unidades | BS4: unidades | BV4: Representatividade nas Vendas em % (Qtde) | BX4: Média Crescimento Ano 1 | BY4: Média Crescimento Ano 2 | BZ4: Média Crescimento Ano 3 | CA4: Média Crescimento Ano 4 | CB4: Média Geral
G5: % de Atingimento => | H5: =IF(E3="Conservador",C163,IF(E3="Moderado",C164,IF(E3="Otimista",C165,C164))) -> 0 | I5: =SUM(I6:I50)/SUM($D$6:$D$50) -> #DIV/0! | J5: =SUM(J6:J50)/SUM($D$6:$D$50) -> #DIV/0! | K5: =SUM(K6:K50)/SUM($D$6:$D$50) -> #DIV/0! | L5: =SUM(L6:L50)/SUM($D$6:$D$50) -> #DIV/0! | M5: =SUM(M6:M50)/SUM($D$6:$D$50) -> #DIV/0! | N5: =SUM(N6:N50)/SUM($D$6:$D$50) -> #DIV/0! | O5: =SUM(O6:O50)/SUM($D$6:$D$50) -> #DIV/0! | P5: =SUM(P6:P50)/SUM($D$6:$D$50) -> #DIV/0! | ... BM5: =SUM(BM6:BM50)/SUM($D$6:$D$50) -> #DIV/0!
B6: =Receitas_1!B6 -> Limpeza Residencial - 4 horas | C6: =SUM(F52:BM52)/SUM($F$98:$BM$98) -> #VALUE! | H6: =IFERROR(IF($D6="","",$H$5*$D6),"") | I6: =IFERROR(IF($D6="","",IF(H6+(H6*I$4)>$D6,$D6,H6+(H6*I$4))),"") | J6: =IFERROR(IF($D6="","",IF(I6+(I6*J$4)>$D6,$D6,I6+(I6*J$4))),"") | K6: =IFERROR(IF($D6="","",IF(J6+(J6*K$4)>$D6,$D6,J6+(J6*K$4))),"") | L6: =IFERROR(IF($D6="","",IF(K6+(K6*L$4)>$D6,$D6,K6+(K6*L$4))),"") | M6: =IFERROR(IF($D6="","",IF(L6+(L6*M$4)>$D6,$D6,L6+(L6*M$4))),"") | N6: =IFERROR(IF($D6="","",IF(M6+(M6*N$4)>$D6,$D6,M6+(M6*N$4))),"") | O6: =IFERROR(IF($D6="","",IF(N6+(N6*O$4)>$D6,$D6,N6+(N6*O$4))),"") | P6: =IFERROR(IF($D6="","",IF(O6+(O6*P$4)>$D6,$D6,O6+(O6*P$4))),"") | ... BM6: =IFERROR(IF($D6="","",IF(BL6+(BL6*BM$4)>$D6,$D6,BL6+(BL6*BM$4))),"")
B7: =Receitas_1!B7 -> Limpeza Empresarial 4 horas | C7: =SUM(F53:BM53)/SUM($F$98:$BM$98) -> #VALUE! | H7: =IFERROR(IF($D7="","",$H$5*$D7),"") | I7: =IFERROR(IF($D7="","",IF(H7+(H7*I$4)>$D7,$D7,H7+(H7*I$4))),"") | J7: =IFERROR(IF($D7="","",IF(I7+(I7*J$4)>$D7,$D7,I7+(I7*J$4))),"") | K7: =IFERROR(IF($D7="","",IF(J7+(J7*K$4)>$D7,$D7,J7+(J7*K$4))),"") | L7: =IFERROR(IF($D7="","",IF(K7+(K7*L$4)>$D7,$D7,K7+(K7*L$4))),"") | M7: =IFERROR(IF($D7="","",IF(L7+(L7*M$4)>$D7,$D7,L7+(L7*M$4))),"") | N7: =IFERROR(IF($D7="","",IF(M7+(M7*N$4)>$D7,$D7,M7+(M7*N$4))),"") | O7: =IFERROR(IF($D7="","",IF(N7+(N7*O$4)>$D7,$D7,N7+(N7*O$4))),"") | P7: =IFERROR(IF($D7="","",IF(O7+(O7*P$4)>$D7,$D7,O7+(O7*P$4))),"") | ... BM7: =IFERROR(IF($D7="","",IF(BL7+(BL7*BM$4)>$D7,$D7,BL7+(BL7*BM$4))),"")
B8: =Receitas_1!B8 -> Limpeza condominial 4 horas | C8: =SUM(F54:BM54)/SUM($F$98:$BM$98) -> #VALUE! | H8: =IFERROR(IF($D8="","",$H$5*$D8),"") | I8: =IFERROR(IF($D8="","",IF(H8+(H8*I$4)>$D8,$D8,H8+(H8*I$4))),"") | J8: =IFERROR(IF($D8="","",IF(I8+(I8*J$4)>$D8,$D8,I8+(I8*J$4))),"") | K8: =IFERROR(IF($D8="","",IF(J8+(J8*K$4)>$D8,$D8,J8+(J8*K$4))),"") | L8: =IFERROR(IF($D8="","",IF(K8+(K8*L$4)>$D8,$D8,K8+(K8*L$4))),"") | M8: =IFERROR(IF($D8="","",IF(L8+(L8*M$4)>$D8,$D8,L8+(L8*M$4))),"") | N8: =IFERROR(IF($D8="","",IF(M8+(M8*N$4)>$D8,$D8,M8+(M8*N$4))),"") | O8: =IFERROR(IF($D8="","",IF(N8+(N8*O$4)>$D8,$D8,N8+(N8*O$4))),"") | P8: =IFERROR(IF($D8="","",IF(O8+(O8*P$4)>$D8,$D8,O8+(O8*P$4))),"") | ... BM8: =IFERROR(IF($D8="","",IF(BL8+(BL8*BM$4)>$D8,$D8,BL8+(BL8*BM$4))),"")
B9: =Receitas_1!B9 -> Passadoria - 4 horas | C9: =SUM(F55:BM55)/SUM($F$98:$BM$98) -> #VALUE! | H9: =IFERROR(IF($D9="","",$H$5*$D9),"") | I9: =IFERROR(IF($D9="","",IF(H9+(H9*I$4)>$D9,$D9,H9+(H9*I$4))),"") | J9: =IFERROR(IF($D9="","",IF(I9+(I9*J$4)>$D9,$D9,I9+(I9*J$4))),"") | K9: =IFERROR(IF($D9="","",IF(J9+(J9*K$4)>$D9,$D9,J9+(J9*K$4))),"") | L9: =IFERROR(IF($D9="","",IF(K9+(K9*L$4)>$D9,$D9,K9+(K9*L$4))),"") | M9: =IFERROR(IF($D9="","",IF(L9+(L9*M$4)>$D9,$D9,L9+(L9*M$4))),"") | N9: =IFERROR(IF($D9="","",IF(M9+(M9*N$4)>$D9,$D9,M9+(M9*N$4))),"") | O9: =IFERROR(IF($D9="","",IF(N9+(N9*O$4)>$D9,$D9,N9+(N9*O$4))),"") | P9: =IFERROR(IF($D9="","",IF(O9+(O9*P$4)>$D9,$D9,O9+(O9*P$4))),"") | ... BM9: =IFERROR(IF($D9="","",IF(BL9+(BL9*BM$4)>$D9,$D9,BL9+(BL9*BM$4))),"")
B10: =Receitas_1!B10 -> Limpeza Residencial - 6 horas | C10: =SUM(F56:BM56)/SUM($F$98:$BM$98) -> #VALUE! | H10: =IFERROR(IF($D10="","",$H$5*$D10),"") | I10: =IFERROR(IF($D10="","",IF(H10+(H10*I$4)>$D10,$D10,H10+(H10*I$4))),"") | J10: =IFERROR(IF($D10="","",IF(I10+(I10*J$4)>$D10,$D10,I10+(I10*J$4))),"") | K10: =IFERROR(IF($D10="","",IF(J10+(J10*K$4)>$D10,$D10,J10+(J10*K$4))),"") | L10: =IFERROR(IF($D10="","",IF(K10+(K10*L$4)>$D10,$D10,K10+(K10*L$4))),"") | M10: =IFERROR(IF($D10="","",IF(L10+(L10*M$4)>$D10,$D10,L10+(L10*M$4))),"") | N10: =IFERROR(IF($D10="","",IF(M10+(M10*N$4)>$D10,$D10,M10+(M10*N$4))),"") | O10: =IFERROR(IF($D10="","",IF(N10+(N10*O$4)>$D10,$D10,N10+(N10*O$4))),"") | P10: =IFERROR(IF($D10="","",IF(O10+(O10*P$4)>$D10,$D10,O10+(O10*P$4))),"") | ... BM10: =IFERROR(IF($D10="","",IF(BL10+(BL10*BM$4)>$D10,$D10,BL10+(BL10*BM$4))),"")
B11: =Receitas_1!B11 -> Limpeza Residencial - 8 horas | C11: =SUM(F57:BM57)/SUM($F$98:$BM$98) -> #VALUE! | H11: =IFERROR(IF($D11="","",$H$5*$D11),"") | I11: =IFERROR(IF($D11="","",IF(H11+(H11*I$4)>$D11,$D11,H11+(H11*I$4))),"") | J11: =IFERROR(IF($D11="","",IF(I11+(I11*J$4)>$D11,$D11,I11+(I11*J$4))),"") | K11: =IFERROR(IF($D11="","",IF(J11+(J11*K$4)>$D11,$D11,J11+(J11*K$4))),"") | L11: =IFERROR(IF($D11="","",IF(K11+(K11*L$4)>$D11,$D11,K11+(K11*L$4))),"") | M11: =IFERROR(IF($D11="","",IF(L11+(L11*M$4)>$D11,$D11,L11+(L11*M$4))),"") | N11: =IFERROR(IF($D11="","",IF(M11+(M11*N$4)>$D11,$D11,M11+(M11*N$4))),"") | O11: =IFERROR(IF($D11="","",IF(N11+(N11*O$4)>$D11,$D11,N11+(N11*O$4))),"") | P11: =IFERROR(IF($D11="","",IF(O11+(O11*P$4)>$D11,$D11,O11+(O11*P$4))),"") | ... BM11: =IFERROR(IF($D11="","",IF(BL11+(BL11*BM$4)>$D11,$D11,BL11+(BL11*BM$4))),"")
B12: =Receitas_1!B12 -> Limpeza Residencial - 2 horas | C12: =SUM(F58:BM58)/SUM($F$98:$BM$98) -> #VALUE! | H12: =IFERROR(IF($D12="","",$H$5*$D12),"") | I12: =IFERROR(IF($D12="","",IF(H12+(H12*I$4)>$D12,$D12,H12+(H12*I$4))),"") | J12: =IFERROR(IF($D12="","",IF(I12+(I12*J$4)>$D12,$D12,I12+(I12*J$4))),"") | K12: =IFERROR(IF($D12="","",IF(J12+(J12*K$4)>$D12,$D12,J12+(J12*K$4))),"") | L12: =IFERROR(IF($D12="","",IF(K12+(K12*L$4)>$D12,$D12,K12+(K12*L$4))),"") | M12: =IFERROR(IF($D12="","",IF(L12+(L12*M$4)>$D12,$D12,L12+(L12*M$4))),"") | N12: =IFERROR(IF($D12="","",IF(M12+(M12*N$4)>$D12,$D12,M12+(M12*N$4))),"") | O12: =IFERROR(IF($D12="","",IF(N12+(N12*O$4)>$D12,$D12,N12+(N12*O$4))),"") | P12: =IFERROR(IF($D12="","",IF(O12+(O12*P$4)>$D12,$D12,O12+(O12*P$4))),"") | ... BM12: =IFERROR(IF($D12="","",IF(BL12+(BL12*BM$4)>$D12,$D12,BL12+(BL12*BM$4))),"")
B13: =Receitas_1!B13 -> Babá 4 horas | C13: =SUM(F59:BM59)/SUM($F$98:$BM$98) -> #VALUE! | H13: =IFERROR(IF($D13="","",$H$5*$D13),"") | I13: =IFERROR(IF($D13="","",IF(H13+(H13*I$4)>$D13,$D13,H13+(H13*I$4))),"") | J13: =IFERROR(IF($D13="","",IF(I13+(I13*J$4)>$D13,$D13,I13+(I13*J$4))),"") | K13: =IFERROR(IF($D13="","",IF(J13+(J13*K$4)>$D13,$D13,J13+(J13*K$4))),"") | L13: =IFERROR(IF($D13="","",IF(K13+(K13*L$4)>$D13,$D13,K13+(K13*L$4))),"") | M13: =IFERROR(IF($D13="","",IF(L13+(L13*M$4)>$D13,$D13,L13+(L13*M$4))),"") | N13: =IFERROR(IF($D13="","",IF(M13+(M13*N$4)>$D13,$D13,M13+(M13*N$4))),"") | O13: =IFERROR(IF($D13="","",IF(N13+(N13*O$4)>$D13,$D13,N13+(N13*O$4))),"") | P13: =IFERROR(IF($D13="","",IF(O13+(O13*P$4)>$D13,$D13,O13+(O13*P$4))),"") | ... BM13: =IFERROR(IF($D13="","",IF(BL13+(BL13*BM$4)>$D13,$D13,BL13+(BL13*BM$4))),"")
B14: =Receitas_1!B14 -> Limpeza Empresarial 8 horas | C14: =SUM(F60:BM60)/SUM($F$98:$BM$98) -> #VALUE! | H14: =IFERROR(IF($D14="","",$H$5*$D14),"") | I14: =IFERROR(IF($D14="","",IF(H14+(H14*I$4)>$D14,$D14,H14+(H14*I$4))),"") | J14: =IFERROR(IF($D14="","",IF(I14+(I14*J$4)>$D14,$D14,I14+(I14*J$4))),"") | K14: =IFERROR(IF($D14="","",IF(J14+(J14*K$4)>$D14,$D14,J14+(J14*K$4))),"") | L14: =IFERROR(IF($D14="","",IF(K14+(K14*L$4)>$D14,$D14,K14+(K14*L$4))),"") | M14: =IFERROR(IF($D14="","",IF(L14+(L14*M$4)>$D14,$D14,L14+(L14*M$4))),"") | N14: =IFERROR(IF($D14="","",IF(M14+(M14*N$4)>$D14,$D14,M14+(M14*N$4))),"") | O14: =IFERROR(IF($D14="","",IF(N14+(N14*O$4)>$D14,$D14,N14+(N14*O$4))),"") | P14: =IFERROR(IF($D14="","",IF(O14+(O14*P$4)>$D14,$D14,O14+(O14*P$4))),"") | ... BM14: =IFERROR(IF($D14="","",IF(BL14+(BL14*BM$4)>$D14,$D14,BL14+(BL14*BM$4))),"")
B15: =Receitas_1!B15 -> Passadoria - 6 horas | C15: =SUM(F61:BM61)/SUM($F$98:$BM$98) -> #VALUE! | H15: =IFERROR(IF($D15="","",$H$5*$D15),"") | I15: =IFERROR(IF($D15="","",IF(H15+(H15*I$4)>$D15,$D15,H15+(H15*I$4))),"") | J15: =IFERROR(IF($D15="","",IF(I15+(I15*J$4)>$D15,$D15,I15+(I15*J$4))),"") | K15: =IFERROR(IF($D15="","",IF(J15+(J15*K$4)>$D15,$D15,J15+(J15*K$4))),"") | L15: =IFERROR(IF($D15="","",IF(K15+(K15*L$4)>$D15,$D15,K15+(K15*L$4))),"") | M15: =IFERROR(IF($D15="","",IF(L15+(L15*M$4)>$D15,$D15,L15+(L15*M$4))),"") | N15: =IFERROR(IF($D15="","",IF(M15+(M15*N$4)>$D15,$D15,M15+(M15*N$4))),"") | O15: =IFERROR(IF($D15="","",IF(N15+(N15*O$4)>$D15,$D15,N15+(N15*O$4))),"") | P15: =IFERROR(IF($D15="","",IF(O15+(O15*P$4)>$D15,$D15,O15+(O15*P$4))),"") | ... BM15: =IFERROR(IF($D15="","",IF(BL15+(BL15*BM$4)>$D15,$D15,BL15+(BL15*BM$4))),"")
B16: =Receitas_1!B16 -> Limpeza Empresarial 6 horas | C16: =SUM(F62:BM62)/SUM($F$98:$BM$98) -> #VALUE! | H16: =IFERROR(IF($D16="","",$H$5*$D16),"") | I16: =IFERROR(IF($D16="","",IF(H16+(H16*I$4)>$D16,$D16,H16+(H16*I$4))),"") | J16: =IFERROR(IF($D16="","",IF(I16+(I16*J$4)>$D16,$D16,I16+(I16*J$4))),"") | K16: =IFERROR(IF($D16="","",IF(J16+(J16*K$4)>$D16,$D16,J16+(J16*K$4))),"") | L16: =IFERROR(IF($D16="","",IF(K16+(K16*L$4)>$D16,$D16,K16+(K16*L$4))),"") | M16: =IFERROR(IF($D16="","",IF(L16+(L16*M$4)>$D16,$D16,L16+(L16*M$4))),"") | N16: =IFERROR(IF($D16="","",IF(M16+(M16*N$4)>$D16,$D16,M16+(M16*N$4))),"") | O16: =IFERROR(IF($D16="","",IF(N16+(N16*O$4)>$D16,$D16,N16+(N16*O$4))),"") | P16: =IFERROR(IF($D16="","",IF(O16+(O16*P$4)>$D16,$D16,O16+(O16*P$4))),"") | ... BM16: =IFERROR(IF($D16="","",IF(BL16+(BL16*BM$4)>$D16,$D16,BL16+(BL16*BM$4))),"")
B17: =Receitas_1!B17 -> Limpeza condominial 2 horas | C17: =SUM(F63:BM63)/SUM($F$98:$BM$98) -> #VALUE! | H17: =IFERROR(IF($D17="","",$H$5*$D17),"") | I17: =IFERROR(IF($D17="","",IF(H17+(H17*I$4)>$D17,$D17,H17+(H17*I$4))),"") | J17: =IFERROR(IF($D17="","",IF(I17+(I17*J$4)>$D17,$D17,I17+(I17*J$4))),"") | K17: =IFERROR(IF($D17="","",IF(J17+(J17*K$4)>$D17,$D17,J17+(J17*K$4))),"") | L17: =IFERROR(IF($D17="","",IF(K17+(K17*L$4)>$D17,$D17,K17+(K17*L$4))),"") | M17: =IFERROR(IF($D17="","",IF(L17+(L17*M$4)>$D17,$D17,L17+(L17*M$4))),"") | N17: =IFERROR(IF($D17="","",IF(M17+(M17*N$4)>$D17,$D17,M17+(M17*N$4))),"") | O17: =IFERROR(IF($D17="","",IF(N17+(N17*O$4)>$D17,$D17,N17+(N17*O$4))),"") | P17: =IFERROR(IF($D17="","",IF(O17+(O17*P$4)>$D17,$D17,O17+(O17*P$4))),"") | ... BM17: =IFERROR(IF($D17="","",IF(BL17+(BL17*BM$4)>$D17,$D17,BL17+(BL17*BM$4))),"")
... B50: =Receitas_1!B50 -> Garçom 8 horas | C50: =SUM(F96:BM96)/SUM($F$98:$BM$98) -> #VALUE! | H50: =IFERROR(IF($D50="","",$H$5*$D50),"") | I50: =IFERROR(IF($D50="","",IF(H50+(H50*I$4)>$D50,$D50,H50+(H50*I$4))),"") | J50: =IFERROR(IF($D50="","",IF(I50+(I50*J$4)>$D50,$D50,I50+(I50*J$4))),"") | K50: =IFERROR(IF($D50="","",IF(J50+(J50*K$4)>$D50,$D50,J50+(J50*K$4))),"") | L50: =IFERROR(IF($D50="","",IF(K50+(K50*L$4)>$D50,$D50,K50+(K50*L$4))),"") | M50: =IFERROR(IF($D50="","",IF(L50+(L50*M$4)>$D50,$D50,L50+(L50*M$4))),"") | N50: =IFERROR(IF($D50="","",IF(M50+(M50*N$4)>$D50,$D50,M50+(M50*N$4))),"") | O50: =IFERROR(IF($D50="","",IF(N50+(N50*O$4)>$D50,$D50,N50+(N50*O$4))),"") | P50: =IFERROR(IF($D50="","",IF(O50+(O50*P$4)>$D50,$D50,O50+(O50*P$4))),"") | ... BM50: =IFERROR(IF($D50="","",IF(BL50+(BL50*BM$4)>$D50,$D50,BL50+(BL50*BM$4))),"")
B51: Faturamento Bruto | C51: Preço Médio de Venda em R$ | D51: Receita Potencial | E51: Receita Média | BO51: R$ | BP51: R$ | BQ51: R$ | BR51: R$
B52: =B6 -> Limpeza Residencial - 4 horas | D52: =IFERROR(C52*D6,"") -> 0 | E52: =IFERROR(AVERAGE(H52:BM52),"") | H52: =$C52*H6 -> #VALUE! | I52: =$C52*I6 -> #VALUE! | J52: =$C52*J6 -> #VALUE! | K52: =$C52*K6 -> #VALUE! | L52: =$C52*L6 -> #VALUE! | M52: =$C52*M6 -> #VALUE! | N52: =$C52*N6 -> #VALUE! | O52: =$C52*O6 -> #VALUE! | ... BM52: =$C52*BM6 -> #VALUE!
B53: =B7 -> Limpeza Empresarial 4 horas | D53: =IFERROR(C53*D7,"") -> 0 | E53: =IFERROR(AVERAGE(H53:BM53),"") | H53: =$C53*H7 -> #VALUE! | I53: =$C53*I7 -> #VALUE! | J53: =$C53*J7 -> #VALUE! | K53: =$C53*K7 -> #VALUE! | L53: =$C53*L7 -> #VALUE! | M53: =$C53*M7 -> #VALUE! | N53: =$C53*N7 -> #VALUE! | O53: =$C53*O7 -> #VALUE! | ... BM53: =$C53*BM7 -> #VALUE!
B54: =B8 -> Limpeza condominial 4 horas | D54: =IFERROR(C54*D8,"") -> 0 | E54: =IFERROR(AVERAGE(H54:BM54),"") | H54: =$C54*H8 -> #VALUE! | I54: =$C54*I8 -> #VALUE! | J54: =$C54*J8 -> #VALUE! | K54: =$C54*K8 -> #VALUE! | L54: =$C54*L8 -> #VALUE! | M54: =$C54*M8 -> #VALUE! | N54: =$C54*N8 -> #VALUE! | O54: =$C54*O8 -> #VALUE! | ... BM54: =$C54*BM8 -> #VALUE!
B55: =B9 -> Passadoria - 4 horas | D55: =IFERROR(C55*D9,"") -> 0 | E55: =IFERROR(AVERAGE(H55:BM55),"") | H55: =$C55*H9 -> #VALUE! | I55: =$C55*I9 -> #VALUE! | J55: =$C55*J9 -> #VALUE! | K55: =$C55*K9 -> #VALUE! | L55: =$C55*L9 -> #VALUE! | M55: =$C55*M9 -> #VALUE! | N55: =$C55*N9 -> #VALUE! | O55: =$C55*O9 -> #VALUE! | ... BM55: =$C55*BM9 -> #VALUE!
B56: =B10 -> Limpeza Residencial - 6 horas | D56: =IFERROR(C56*D10,"") -> 0 | E56: =IFERROR(AVERAGE(H56:BM56),"") | H56: =$C56*H10 -> #VALUE! | I56: =$C56*I10 -> #VALUE! | J56: =$C56*J10 -> #VALUE! | K56: =$C56*K10 -> #VALUE! | L56: =$C56*L10 -> #VALUE! | M56: =$C56*M10 -> #VALUE! | N56: =$C56*N10 -> #VALUE! | O56: =$C56*O10 -> #VALUE! | ... BM56: =$C56*BM10 -> #VALUE!
B57: =B11 -> Limpeza Residencial - 8 horas | D57: =IFERROR(C57*D11,"") -> 0 | E57: =IFERROR(AVERAGE(H57:BM57),"") | H57: =$C57*H11 -> #VALUE! | I57: =$C57*I11 -> #VALUE! | J57: =$C57*J11 -> #VALUE! | K57: =$C57*K11 -> #VALUE! | L57: =$C57*L11 -> #VALUE! | M57: =$C57*M11 -> #VALUE! | N57: =$C57*N11 -> #VALUE! | O57: =$C57*O11 -> #VALUE! | ... BM57: =$C57*BM11 -> #VALUE!
B58: =B12 -> Limpeza Residencial - 2 horas | D58: =IFERROR(C58*D12,"") -> 0 | E58: =IFERROR(AVERAGE(H58:BM58),"") | H58: =$C58*H12 -> #VALUE! | I58: =$C58*I12 -> #VALUE! | J58: =$C58*J12 -> #VALUE! | K58: =$C58*K12 -> #VALUE! | L58: =$C58*L12 -> #VALUE! | M58: =$C58*M12 -> #VALUE! | N58: =$C58*N12 -> #VALUE! | O58: =$C58*O12 -> #VALUE! | ... BM58: =$C58*BM12 -> #VALUE!
B59: =B13 -> Babá 4 horas | D59: =IFERROR(C59*D13,"") -> 0 | E59: =IFERROR(AVERAGE(H59:BM59),"") | H59: =$C59*H13 -> #VALUE! | I59: =$C59*I13 -> #VALUE! | J59: =$C59*J13 -> #VALUE! | K59: =$C59*K13 -> #VALUE! | L59: =$C59*L13 -> #VALUE! | M59: =$C59*M13 -> #VALUE! | N59: =$C59*N13 -> #VALUE! | O59: =$C59*O13 -> #VALUE! | ... BM59: =$C59*BM13 -> #VALUE!
B60: =B14 -> Limpeza Empresarial 8 horas | D60: =IFERROR(C60*D14,"") -> 0 | E60: =IFERROR(AVERAGE(H60:BM60),"") | H60: =$C60*H14 -> #VALUE! | I60: =$C60*I14 -> #VALUE! | J60: =$C60*J14 -> #VALUE! | K60: =$C60*K14 -> #VALUE! | L60: =$C60*L14 -> #VALUE! | M60: =$C60*M14 -> #VALUE! | N60: =$C60*N14 -> #VALUE! | O60: =$C60*O14 -> #VALUE! | ... BM60: =$C60*BM14 -> #VALUE!
B61: =B15 -> Passadoria - 6 horas | D61: =IFERROR(C61*D15,"") -> 0 | E61: =IFERROR(AVERAGE(H61:BM61),"") | H61: =$C61*H15 -> #VALUE! | I61: =$C61*I15 -> #VALUE! | J61: =$C61*J15 -> #VALUE! | K61: =$C61*K15 -> #VALUE! | L61: =$C61*L15 -> #VALUE! | M61: =$C61*M15 -> #VALUE! | N61: =$C61*N15 -> #VALUE! | O61: =$C61*O15 -> #VALUE! | ... BM61: =$C61*BM15 -> #VALUE!
B62: =B16 -> Limpeza Empresarial 6 horas | D62: =IFERROR(C62*D16,"") -> 0 | E62: =IFERROR(AVERAGE(H62:BM62),"") | H62: =$C62*H16 -> #VALUE! | I62: =$C62*I16 -> #VALUE! | J62: =$C62*J16 -> #VALUE! | K62: =$C62*K16 -> #VALUE! | L62: =$C62*L16 -> #VALUE! | M62: =$C62*M16 -> #VALUE! | N62: =$C62*N16 -> #VALUE! | O62: =$C62*O16 -> #VALUE! | ... BM62: =$C62*BM16 -> #VALUE!
B63: =B17 -> Limpeza condominial 2 horas | D63: =IFERROR(C63*D17,"") -> 0 | E63: =IFERROR(AVERAGE(H63:BM63),"") | H63: =$C63*H17 -> #VALUE! | I63: =$C63*I17 -> #VALUE! | J63: =$C63*J17 -> #VALUE! | K63: =$C63*K17 -> #VALUE! | L63: =$C63*L17 -> #VALUE! | M63: =$C63*M17 -> #VALUE! | N63: =$C63*N17 -> #VALUE! | O63: =$C63*O17 -> #VALUE! | ... BM63: =$C63*BM17 -> #VALUE!
... B96: =B50 -> Garçom 8 horas | D96: =IFERROR(C96*D50,"") -> 0 | E96: =IFERROR(AVERAGE(H96:BM96),"") | H96: =$C96*H50 -> #VALUE! | I96: =$C96*I50 -> #VALUE! | J96: =$C96*J50 -> #VALUE! | K96: =$C96*K50 -> #VALUE! | L96: =$C96*L50 -> #VALUE! | M96: =$C96*M50 -> #VALUE! | N96: =$C96*N50 -> #VALUE! | O96: =$C96*O50 -> #VALUE! | ... BM96: =$C96*BM50 -> #VALUE!
B98: Receita Total Mês (Potencial / Média) | D98: =SUM(D52:D96) -> 0 | E98: =SUM(E52:E96) -> 0 | H98: =SUM(H52:H96) -> #VALUE! | I98: =SUM(I52:I96) -> #VALUE! | J98: =SUM(J52:J96) -> #VALUE! | K98: =SUM(K52:K96) -> #VALUE! | L98: =SUM(L52:L96) -> #VALUE! | M98: =SUM(M52:M96) -> #VALUE! | N98: =SUM(N52:N96) -> #VALUE! | O98: =SUM(O52:O96) -> #VALUE! | ... BM98: =SUM(BM52:BM96) -> #VALUE! | BO98: =SUMIF($F$2:$BA$2,BO$2,$F98:$BA98) -> #VALUE! | BP98: =SUMIF($F$2:$BA$2,BP$2,$F98:$BA98) -> #VALUE! | BQ98: =SUMIF($F$2:$BA$2,BQ$2,$F98:$BA98) -> #VALUE! | BR98: =SUMIF($F$2:$BA$2,BR$2,$F98:$BA98) -> #VALUE! | BS98: =SUM(BS52:BS96) -> 0
B99: Ticket Médio
B100: Quantidade de Tickets | H100: =H98/$C$99 -> #VALUE! | I100: =I98/$C$99 -> #VALUE! | J100: =J98/$C$99 -> #VALUE! | K100: =K98/$C$99 -> #VALUE! | L100: =L98/$C$99 -> #VALUE! | M100: =M98/$C$99 -> #VALUE! | N100: =N98/$C$99 -> #VALUE! | O100: =O98/$C$99 -> #VALUE! | ... BM100: =BM98/$C$99 -> #VALUE!
B102: Detalhamento CSP | C102: CSP $ | D102: CSP % | F102: 1 | G102: 2 | H102: 3 | I102: 4 | J102: 5 | K102: 6 | L102: 7 | M102: 8 | N102: 9 | O102: 10 | P102: 11 | Q102: 12 | R102: 13 | S102: 14 | T102: 15 | U102: 16 | V102: 17 | W102: 18 | X102: 19 | Y102: 20 | Z102: 21 | AA102: 22 | AB102: 23 | AC102: 24 | AD102: 25 | AE102: 26 | AF102: 27 | AG102: 28 | AH102: 29 | AI102: 30 | AJ102: 31 | AK102: 32 | AL102: 33 | AM102: 34 | AN102: 35 | AO102: 36 | AP102: 37 | AQ102: 38 | AR102: 39 | AS102: 40 | AT102: 41 | AU102: 42 | AV102: 43 | AW102: 44 | AX102: 45 | AY102: 46 | AZ102: 47 | BA102: 48 | BB102: 49 | BC102: 50 | BD102: 51 | BE102: 52 | BF102: 53 | BG102: 54 | BH102: 55 | BI102: 56 | BJ102: 57 | BK102: 58 | BL102: 59 | BM102: 60
B103: =B6 -> Limpeza Residencial - 4 horas | D103: =C103/C52 -> #DIV/0! | H103: =H52*$D103 -> #VALUE! | I103: =I52*$D103 -> #VALUE! | J103: =J52*$D103 -> #VALUE! | K103: =K52*$D103 -> #VALUE! | L103: =L52*$D103 -> #VALUE! | M103: =M52*$D103 -> #VALUE! | N103: =N52*$D103 -> #VALUE! | O103: =O52*$D103 -> #VALUE! | ... BM103: =BM52*$D103 -> #VALUE!
B104: =B7 -> Limpeza Empresarial 4 horas | D104: =C104/C53 -> #DIV/0! | H104: =H53*$D104 -> #VALUE! | I104: =I53*$D104 -> #VALUE! | J104: =J53*$D104 -> #VALUE! | K104: =K53*$D104 -> #VALUE! | L104: =L53*$D104 -> #VALUE! | M104: =M53*$D104 -> #VALUE! | N104: =N53*$D104 -> #VALUE! | O104: =O53*$D104 -> #VALUE! | ... BM104: =BM53*$D104 -> #VALUE!
B105: =B8 -> Limpeza condominial 4 horas | D105: =C105/C54 -> #DIV/0! | H105: =H54*$D105 -> #VALUE! | I105: =I54*$D105 -> #VALUE! | J105: =J54*$D105 -> #VALUE! | K105: =K54*$D105 -> #VALUE! | L105: =L54*$D105 -> #VALUE! | M105: =M54*$D105 -> #VALUE! | N105: =N54*$D105 -> #VALUE! | O105: =O54*$D105 -> #VALUE! | ... BM105: =BM54*$D105 -> #VALUE!
B106: =B9 -> Passadoria - 4 horas | D106: =C106/C55 -> #DIV/0! | H106: =H55*$D106 -> #VALUE! | I106: =I55*$D106 -> #VALUE! | J106: =J55*$D106 -> #VALUE! | K106: =K55*$D106 -> #VALUE! | L106: =L55*$D106 -> #VALUE! | M106: =M55*$D106 -> #VALUE! | N106: =N55*$D106 -> #VALUE! | O106: =O55*$D106 -> #VALUE! | ... BM106: =BM55*$D106 -> #VALUE!
B107: =B10 -> Limpeza Residencial - 6 horas | D107: =C107/C56 -> #DIV/0! | H107: =H56*$D107 -> #VALUE! | I107: =I56*$D107 -> #VALUE! | J107: =J56*$D107 -> #VALUE! | K107: =K56*$D107 -> #VALUE! | L107: =L56*$D107 -> #VALUE! | M107: =M56*$D107 -> #VALUE! | N107: =N56*$D107 -> #VALUE! | O107: =O56*$D107 -> #VALUE! | ... BM107: =BM56*$D107 -> #VALUE!
B108: =B11 -> Limpeza Residencial - 8 horas | D108: =C108/C57 -> #DIV/0! | H108: =H57*$D108 -> #VALUE! | I108: =I57*$D108 -> #VALUE! | J108: =J57*$D108 -> #VALUE! | K108: =K57*$D108 -> #VALUE! | L108: =L57*$D108 -> #VALUE! | M108: =M57*$D108 -> #VALUE! | N108: =N57*$D108 -> #VALUE! | O108: =O57*$D108 -> #VALUE! | ... BM108: =BM57*$D108 -> #VALUE!
B109: =B12 -> Limpeza Residencial - 2 horas | D109: =C109/C58 -> #DIV/0! | H109: =H58*$D109 -> #VALUE! | I109: =I58*$D109 -> #VALUE! | J109: =J58*$D109 -> #VALUE! | K109: =K58*$D109 -> #VALUE! | L109: =L58*$D109 -> #VALUE! | M109: =M58*$D109 -> #VALUE! | N109: =N58*$D109 -> #VALUE! | O109: =O58*$D109 -> #VALUE! | ... BM109: =BM58*$D109 -> #VALUE!
B110: =B13 -> Babá 4 horas | D110: =C110/C59 -> #DIV/0! | H110: =H59*$D110 -> #VALUE! | I110: =I59*$D110 -> #VALUE! | J110: =J59*$D110 -> #VALUE! | K110: =K59*$D110 -> #VALUE! | L110: =L59*$D110 -> #VALUE! | M110: =M59*$D110 -> #VALUE! | N110: =N59*$D110 -> #VALUE! | O110: =O59*$D110 -> #VALUE! | ... BM110: =BM59*$D110 -> #VALUE!
B111: =B14 -> Limpeza Empresarial 8 horas | D111: =C111/C60 -> #DIV/0! | H111: =H60*$D111 -> #VALUE! | I111: =I60*$D111 -> #VALUE! | J111: =J60*$D111 -> #VALUE! | K111: =K60*$D111 -> #VALUE! | L111: =L60*$D111 -> #VALUE! | M111: =M60*$D111 -> #VALUE! | N111: =N60*$D111 -> #VALUE! | O111: =O60*$D111 -> #VALUE! | ... BM111: =BM60*$D111 -> #VALUE!
B112: =B15 -> Passadoria - 6 horas | D112: =C112/C61 -> #DIV/0! | H112: =H61*$D112 -> #VALUE! | I112: =I61*$D112 -> #VALUE! | J112: =J61*$D112 -> #VALUE! | K112: =K61*$D112 -> #VALUE! | L112: =L61*$D112 -> #VALUE! | M112: =M61*$D112 -> #VALUE! | N112: =N61*$D112 -> #VALUE! | O112: =O61*$D112 -> #VALUE! | ... BM112: =BM61*$D112 -> #VALUE!
B113: =B16 -> Limpeza Empresarial 6 horas | D113: =C113/C62 -> #DIV/0! | H113: =H62*$D113 -> #VALUE! | I113: =I62*$D113 -> #VALUE! | J113: =J62*$D113 -> #VALUE! | K113: =K62*$D113 -> #VALUE! | L113: =L62*$D113 -> #VALUE! | M113: =M62*$D113 -> #VALUE! | N113: =N62*$D113 -> #VALUE! | O113: =O62*$D113 -> #VALUE! | ... BM113: =BM62*$D113 -> #VALUE!
B114: =B17 -> Limpeza condominial 2 horas | D114: =C114/C63 -> #DIV/0! | H114: =H63*$D114 -> #VALUE! | I114: =I63*$D114 -> #VALUE! | J114: =J63*$D114 -> #VALUE! | K114: =K63*$D114 -> #VALUE! | L114: =L63*$D114 -> #VALUE! | M114: =M63*$D114 -> #VALUE! | N114: =N63*$D114 -> #VALUE! | O114: =O63*$D114 -> #VALUE! | ... BM114: =BM63*$D114 -> #VALUE!
... B147: =B50 -> Garçom 8 horas | D147: =C147/C96 -> #DIV/0! | H147: =H96*$D147 -> #VALUE! | I147: =I96*$D147 -> #VALUE! | J147: =J96*$D147 -> #VALUE! | K147: =K96*$D147 -> #VALUE! | L147: =L96*$D147 -> #VALUE! | M147: =M96*$D147 -> #VALUE! | N147: =N96*$D147 -> #VALUE! | O147: =O96*$D147 -> #VALUE! | ... BM147: =BM96*$D147 -> #VALUE!
B148: CSP Sub-TOTAL | H148: =SUM(H103:H147) -> #VALUE! | I148: =SUM(I103:I147) -> #VALUE! | J148: =SUM(J103:J147) -> #VALUE! | K148: =SUM(K103:K147) -> #VALUE! | L148: =SUM(L103:L147) -> #VALUE! | M148: =SUM(M103:M147) -> #VALUE! | N148: =SUM(N103:N147) -> #VALUE! | O148: =SUM(O103:O147) -> #VALUE! | ... BM148: =SUM(BM103:BM147) -> #VALUE! | BO148: =SUM(BO103:BO147) -> 0 | BP148: =SUM(BP103:BP147) -> 0 | BQ148: =SUM(BQ103:BQ147) -> 0 | BR148: =SUM(BR103:BR147) -> 0 | BS148: =SUM(BS103:BS147) -> 0
B150: Desperdício Comida | C150: 0 | H150: =$C$150*SUM(H103:H128) -> #VALUE! | I150: =$C$150*SUM(I103:I128) -> #VALUE! | J150: =$C$150*SUM(J103:J128) -> #VALUE! | K150: =$C$150*SUM(K103:K128) -> #VALUE! | L150: =$C$150*SUM(L103:L128) -> #VALUE! | M150: =$C$150*SUM(M103:M128) -> #VALUE! | N150: =$C$150*SUM(N103:N128) -> #VALUE! | O150: =$C$150*SUM(O103:O128) -> #VALUE! | ... BM150: =$C$150*SUM(BM103:BM128) -> #VALUE!
B151: Desperdício Bebida | C151: 0 | H151: =$C$151*SUM(H129:H147) -> #VALUE! | I151: =$C$151*SUM(I129:I147) -> #VALUE! | J151: =$C$151*SUM(J129:J147) -> #VALUE! | K151: =$C$151*SUM(K129:K147) -> #VALUE! | L151: =$C$151*SUM(L129:L147) -> #VALUE! | M151: =$C$151*SUM(M129:M147) -> #VALUE! | N151: =$C$151*SUM(N129:N147) -> #VALUE! | O151: =$C$151*SUM(O129:O147) -> #VALUE! | ... BM151: =$C$151*SUM(BM129:BM147) -> #VALUE!
B153: CSP TOTAL | H153: =H148+H150+H151 -> #VALUE! | I153: =I148+I150+I151 -> #VALUE! | J153: =J148+J150+J151 -> #VALUE! | K153: =K148+K150+K151 -> #VALUE! | L153: =L148+L150+L151 -> #VALUE! | M153: =M148+M150+M151 -> #VALUE! | N153: =N148+N150+N151 -> #VALUE! | O153: =O148+O150+O151 -> #VALUE! | ... CB153: =CB148+CB150+CB151 -> 0
B155: CSP TOTAL % | H155: =H153/H98 -> #VALUE! | I155: =I153/I98 -> #VALUE! | J155: =J153/J98 -> #VALUE! | K155: =K153/K98 -> #VALUE! | L155: =L153/L98 -> #VALUE! | M155: =M153/M98 -> #VALUE! | N155: =N153/N98 -> #VALUE! | O155: =O153/O98 -> #VALUE! | ... BM155: =BM153/BM98 -> #VALUE!
B157: OBSERVAÇÃO
B162: =Receitas_1!B161 -> CENÁRIO
B163: =Receitas_1!B162 -> Conservador
B164: =Receitas_1!B163 -> Moderado
B165: =Receitas_1!B164 -> Otimista
B187: Obs.: Esta planilha não configura compromisso ou projeção de resultado, os quais dependerão do esforço e dedicação de cada Franqueado.

Sheet Receitas_3
C1: SIMULAÇÃO DE FORMAÇÃO DA RECEITA
F2: Ano 1 | G2: Ano 1 | H2: Ano 1 | I2: Ano 1 | J2: Ano 1 | K2: Ano 1 | L2: Ano 1 | M2: Ano 1 | N2: Ano 1 | O2: Ano 1 | P2: Ano 1 | Q2: Ano 1 | R2: Ano 2 | S2: Ano 2 | T2: Ano 2 | U2: Ano 2 | V2: Ano 2 | W2: Ano 2 | X2: Ano 2 | Y2: Ano 2 | Z2: Ano 2 | AA2: Ano 2 | AB2: Ano 2 | AC2: Ano 2 | AD2: Ano 3 | AE2: Ano 3 | AF2: Ano 3 | AG2: Ano 3 | AH2: Ano 3 | AI2: Ano 3 | AJ2: Ano 3 | AK2: Ano 3 | AL2: Ano 3 | AM2: Ano 3 | AN2: Ano 3 | AO2: Ano 3 | AP2: Ano 4 | AQ2: Ano 4 | AR2: Ano 4 | AS2: Ano 4 | AT2: Ano 4 | AU2: Ano 4 | AV2: Ano 4 | AW2: Ano 4 | AX2: Ano 4 | AY2: Ano 4 | AZ2: Ano 4 | BA2: Ano 4 | BB2: Ano 5 | BC2: Ano 5 | BD2: Ano 5 | BE2: Ano 5 | BF2: Ano 5 | BG2: Ano 5 | BH2: Ano 5 | BI2: Ano 5 | BJ2: Ano 5 | BK2: Ano 5 | BL2: Ano 5 | BM2: Ano 5 | BP2: Ano 1 | BQ2: Ano 2 | BR2: Ano 3 | BS2: Ano 4 | BT2: Ano 5
F3: Jan | G3: Fev | H3: Mar | I3: Abr | J3: Mai | K3: Jun | L3: Jul | M3: Ago | N3: Set | O3: Out | P3: Nov | Q3: Dez | R3: Jan | S3: Fev | T3: Mar | U3: Abr | V3: Mai | W3: Jun | X3: Jul | Y3: Ago | Z3: Set | AA3: Out | AB3: Nov | AC3: Dez | AD3: Jan | AE3: Fev | AF3: Mar | AG3: Abr | AH3: Mai | AI3: Jun | AJ3: Jul | AK3: Ago | AL3: Set | AM3: Out | AN3: Nov | AO3: Dez | AP3: Jan | AQ3: Fev | AR3: Mar | AS3: Abr | AT3: Mai | AU3: Jun | AV3: Jul | AW3: Ago | AX3: Set | AY3: Out | AZ3: Nov | BA3: Dez | BB3: Jan | BC3: Fev | BD3: Mar | BE3: Abr | BF3: Mai | BG3: Jun | BH3: Jul | BI3: Ago | BJ3: Set | BK3: Out | BL3: Nov | BM3: Dez
B4: Quantidades vendidas | C4: Representatividade nas Vendas em % nos 5 anos | D4: Potencial TOTAL | E4: Quantidade Média Vendida | F4: IMPLANTAÇÃO | I4: Crescimento vs. Mês Anterior => | BP4: unidades | BQ4: unidades | BR4: unidades | BS4: unidades | BT4: unidades | BW4: Representatividade nas Vendas em % (Qtde) | BY4: Média Crescimento Ano 1 | BZ4: Média Crescimento Ano 2 | CA4: Média Crescimento Ano 3 | CB4: Média Crescimento Ano 4 | CC4: Média Geral
H5: % de Atingimento => | I5: 0 | J5: =SUM(J6:J50)/SUM($D$6:$D$50) -> #DIV/0! | K5: =SUM(K6:K50)/SUM($D$6:$D$50) -> #DIV/0! | L5: =SUM(L6:L50)/SUM($D$6:$D$50) -> #DIV/0! | M5: =SUM(M6:M50)/SUM($D$6:$D$50) -> #DIV/0! | N5: =SUM(N6:N50)/SUM($D$6:$D$50) -> #DIV/0! | O5: =SUM(O6:O50)/SUM($D$6:$D$50) -> #DIV/0! | P5: =SUM(P6:P50)/SUM($D$6:$D$50) -> #DIV/0! | Q5: =SUM(Q6:Q50)/SUM($D$6:$D$50) -> #DIV/0! | ... BM5: =SUM(BM6:BM50)/SUM($D$6:$D$50) -> #DIV/0!
B6: =Receitas_1!B6 -> Limpeza Residencial - 4 horas | C6: =SUM(F52:BN52)/SUM($F$97:$BN$97) -> #DIV/0! | D6: 0 | E6: 0 | I6: =IFERROR(IF($D6="","",$I$5*$D6),"") -> 0 | J6: =IFERROR(IF($D6="","",IF(I6+(I6*J$4)>$D6,$D6,I6+(I6*J$4))),"") -> 0 | K6: =IFERROR(IF($D6="","",IF(J6+(J6*K$4)>$D6,$D6,J6+(J6*K$4))),"") -> 0 | L6: =IFERROR(IF($D6="","",IF(K6+(K6*L$4)>$D6,$D6,K6+(K6*L$4))),"") -> 0 | M6: =IFERROR(IF($D6="","",IF(L6+(L6*M$4)>$D6,$D6,L6+(L6*M$4))),"") -> 0 | N6: =IFERROR(IF($D6="","",IF(M6+(M6*N$4)>$D6,$D6,M6+(M6*N$4))),"") -> 0 | O6: =IFERROR(IF($D6="","",IF(N6+(N6*O$4)>$D6,$D6,N6+(N6*O$4))),"") -> 0 | P6: =IFERROR(IF($D6="","",IF(O6+(O6*P$4)>$D6,$D6,O6+(O6*P$4))),"") -> 0 | Q6: =IFERROR(IF($D6="","",IF(P6+(P6*Q$4)>$D6,$D6,P6+(P6*Q$4))),"") -> 0 | ... BM6: =IFERROR(IF($D6="","",IF(BL6+(BL6*BM$4)>$D6,$D6,BL6+(BL6*BM$4))),"") -> 0
B7: =Receitas_1!B7 -> Limpeza Empresarial 4 horas | C7: =SUM(F53:BN53)/SUM($F$97:$BN$97) -> #DIV/0! | D7: 0 | E7: 0 | I7: =IFERROR(IF($D7="","",$I$5*$D7),"") -> 0 | J7: =IFERROR(IF($D7="","",IF(I7+(I7*J$4)>$D7,$D7,I7+(I7*J$4))),"") -> 0 | K7: =IFERROR(IF($D7="","",IF(J7+(J7*K$4)>$D7,$D7,J7+(J7*K$4))),"") -> 0 | L7: =IFERROR(IF($D7="","",IF(K7+(K7*L$4)>$D7,$D7,K7+(K7*L$4))),"") -> 0 | M7: =IFERROR(IF($D7="","",IF(L7+(L7*M$4)>$D7,$D7,L7+(L7*M$4))),"") -> 0 | N7: =IFERROR(IF($D7="","",IF(M7+(M7*N$4)>$D7,$D7,M7+(M7*N$4))),"") -> 0 | O7: =IFERROR(IF($D7="","",IF(N7+(N7*O$4)>$D7,$D7,N7+(N7*O$4))),"") -> 0 | P7: =IFERROR(IF($D7="","",IF(O7+(O7*P$4)>$D7,$D7,O7+(O7*P$4))),"") -> 0 | Q7: =IFERROR(IF($D7="","",IF(P7+(P7*Q$4)>$D7,$D7,P7+(P7*Q$4))),"") -> 0 | ... BM7: =IFERROR(IF($D7="","",IF(BL7+(BL7*BM$4)>$D7,$D7,BL7+(BL7*BM$4))),"") -> 0
B8: =Receitas_1!B8 -> Limpeza condominial 4 horas | C8: =SUM(F54:BN54)/SUM($F$97:$BN$97) -> #DIV/0! | D8: 0 | E8: 0 | I8: =IFERROR(IF($D8="","",$I$5*$D8),"") -> 0 | J8: =IFERROR(IF($D8="","",IF(I8+(I8*J$4)>$D8,$D8,I8+(I8*J$4))),"") -> 0 | K8: =IFERROR(IF($D8="","",IF(J8+(J8*K$4)>$D8,$D8,J8+(J8*K$4))),"") -> 0 | L8: =IFERROR(IF($D8="","",IF(K8+(K8*L$4)>$D8,$D8,K8+(K8*L$4))),"") -> 0 | M8: =IFERROR(IF($D8="","",IF(L8+(L8*M$4)>$D8,$D8,L8+(L8*M$4))),"") -> 0 | N8: =IFERROR(IF($D8="","",IF(M8+(M8*N$4)>$D8,$D8,M8+(M8*N$4))),"") -> 0 | O8: =IFERROR(IF($D8="","",IF(N8+(N8*O$4)>$D8,$D8,N8+(N8*O$4))),"") -> 0 | P8: =IFERROR(IF($D8="","",IF(O8+(O8*P$4)>$D8,$D8,O8+(O8*P$4))),"") -> 0 | Q8: =IFERROR(IF($D8="","",IF(P8+(P8*Q$4)>$D8,$D8,P8+(P8*Q$4))),"") -> 0 | ... BM8: =IFERROR(IF($D8="","",IF(BL8+(BL8*BM$4)>$D8,$D8,BL8+(BL8*BM$4))),"") -> 0
B9: =Receitas_1!B9 -> Passadoria - 4 horas | C9: =SUM(F55:BN55)/SUM($F$97:$BN$97) -> #DIV/0! | D9: 0 | E9: 0 | I9: =IFERROR(IF($D9="","",$I$5*$D9),"") -> 0 | J9: =IFERROR(IF($D9="","",IF(I9+(I9*J$4)>$D9,$D9,I9+(I9*J$4))),"") -> 0 | K9: =IFERROR(IF($D9="","",IF(J9+(J9*K$4)>$D9,$D9,J9+(J9*K$4))),"") -> 0 | L9: =IFERROR(IF($D9="","",IF(K9+(K9*L$4)>$D9,$D9,K9+(K9*L$4))),"") -> 0 | M9: =IFERROR(IF($D9="","",IF(L9+(L9*M$4)>$D9,$D9,L9+(L9*M$4))),"") -> 0 | N9: =IFERROR(IF($D9="","",IF(M9+(M9*N$4)>$D9,$D9,M9+(M9*N$4))),"") -> 0 | O9: =IFERROR(IF($D9="","",IF(N9+(N9*O$4)>$D9,$D9,N9+(N9*O$4))),"") -> 0 | P9: =IFERROR(IF($D9="","",IF(O9+(O9*P$4)>$D9,$D9,O9+(O9*P$4))),"") -> 0 | Q9: =IFERROR(IF($D9="","",IF(P9+(P9*Q$4)>$D9,$D9,P9+(P9*Q$4))),"") -> 0 | ... BM9: =IFERROR(IF($D9="","",IF(BL9+(BL9*BM$4)>$D9,$D9,BL9+(BL9*BM$4))),"") -> 0
B10: =Receitas_1!B10 -> Limpeza Residencial - 6 horas | C10: =SUM(F56:BN56)/SUM($F$97:$BN$97) -> #DIV/0! | D10: 0 | E10: 0 | I10: =IFERROR(IF($D10="","",$I$5*$D10),"") -> 0 | J10: =IFERROR(IF($D10="","",IF(I10+(I10*J$4)>$D10,$D10,I10+(I10*J$4))),"") -> 0 | K10: =IFERROR(IF($D10="","",IF(J10+(J10*K$4)>$D10,$D10,J10+(J10*K$4))),"") -> 0 | L10: =IFERROR(IF($D10="","",IF(K10+(K10*L$4)>$D10,$D10,K10+(K10*L$4))),"") -> 0 | M10: =IFERROR(IF($D10="","",IF(L10+(L10*M$4)>$D10,$D10,L10+(L10*M$4))),"") -> 0 | N10: =IFERROR(IF($D10="","",IF(M10+(M10*N$4)>$D10,$D10,M10+(M10*N$4))),"") -> 0 | O10: =IFERROR(IF($D10="","",IF(N10+(N10*O$4)>$D10,$D10,N10+(N10*O$4))),"") -> 0 | P10: =IFERROR(IF($D10="","",IF(O10+(O10*P$4)>$D10,$D10,O10+(O10*P$4))),"") -> 0 | Q10: =IFERROR(IF($D10="","",IF(P10+(P10*Q$4)>$D10,$D10,P10+(P10*Q$4))),"") -> 0 | ... BM10: =IFERROR(IF($D10="","",IF(BL10+(BL10*BM$4)>$D10,$D10,BL10+(BL10*BM$4))),"") -> 0
B11: =Receitas_1!B11 -> Limpeza Residencial - 8 horas | C11: =SUM(F57:BN57)/SUM($F$97:$BN$97) -> #DIV/0! | D11: 0 | E11: 0 | I11: =IFERROR(IF($D11="","",$I$5*$D11),"") -> 0 | J11: =IFERROR(IF($D11="","",IF(I11+(I11*J$4)>$D11,$D11,I11+(I11*J$4))),"") -> 0 | K11: =IFERROR(IF($D11="","",IF(J11+(J11*K$4)>$D11,$D11,J11+(J11*K$4))),"") -> 0 | L11: =IFERROR(IF($D11="","",IF(K11+(K11*L$4)>$D11,$D11,K11+(K11*L$4))),"") -> 0 | M11: =IFERROR(IF($D11="","",IF(L11+(L11*M$4)>$D11,$D11,L11+(L11*M$4))),"") -> 0 | N11: =IFERROR(IF($D11="","",IF(M11+(M11*N$4)>$D11,$D11,M11+(M11*N$4))),"") -> 0 | O11: =IFERROR(IF($D11="","",IF(N11+(N11*O$4)>$D11,$D11,N11+(N11*O$4))),"") -> 0 | P11: =IFERROR(IF($D11="","",IF(O11+(O11*P$4)>$D11,$D11,O11+(O11*P$4))),"") -> 0 | Q11: =IFERROR(IF($D11="","",IF(P11+(P11*Q$4)>$D11,$D11,P11+(P11*Q$4))),"") -> 0 | ... BM11: =IFERROR(IF($D11="","",IF(BL11+(BL11*BM$4)>$D11,$D11,BL11+(BL11*BM$4))),"") -> 0
B12: =Receitas_1!B12 -> Limpeza Residencial - 2 horas | C12: =SUM(F96:BN96)/SUM($F$97:$BN$97) -> #DIV/0! | D12: 0 | E12: 0 | I12: =IFERROR(IF($D12="","",$I$5*$D12),"") -> 0 | J12: =IFERROR(IF($D12="","",IF(I12+(I12*J$4)>$D12,$D12,I12+(I12*J$4))),"") -> 0 | K12: =IFERROR(IF($D12="","",IF(J12+(J12*K$4)>$D12,$D12,J12+(J12*K$4))),"") -> 0 | L12: =IFERROR(IF($D12="","",IF(K12+(K12*L$4)>$D12,$D12,K12+(K12*L$4))),"") -> 0 | M12: =IFERROR(IF($D12="","",IF(L12+(L12*M$4)>$D12,$D12,L12+(L12*M$4))),"") -> 0 | N12: =IFERROR(IF($D12="","",IF(M12+(M12*N$4)>$D12,$D12,M12+(M12*N$4))),"") -> 0 | O12: =IFERROR(IF($D12="","",IF(N12+(N12*O$4)>$D12,$D12,N12+(N12*O$4))),"") -> 0 | P12: =IFERROR(IF($D12="","",IF(O12+(O12*P$4)>$D12,$D12,O12+(O12*P$4))),"") -> 0 | Q12: =IFERROR(IF($D12="","",IF(P12+(P12*Q$4)>$D12,$D12,P12+(P12*Q$4))),"") -> 0 | ... BM12: =IFERROR(IF($D12="","",IF(BL12+(BL12*BM$4)>$D12,$D12,BL12+(BL12*BM$4))),"") -> 0
B13: =Receitas_1!B13 -> Babá 4 horas | C13: =SUM(F97:BN97)/SUM($F$97:$BN$97) -> #DIV/0! | D13: 0 | E13: 0 | I13: =IFERROR(IF($D13="","",$I$5*$D13),"") -> 0 | J13: =IFERROR(IF($D13="","",IF(I13+(I13*J$4)>$D13,$D13,I13+(I13*J$4))),"") -> 0 | K13: =IFERROR(IF($D13="","",IF(J13+(J13*K$4)>$D13,$D13,J13+(J13*K$4))),"") -> 0 | L13: =IFERROR(IF($D13="","",IF(K13+(K13*L$4)>$D13,$D13,K13+(K13*L$4))),"") -> 0 | M13: =IFERROR(IF($D13="","",IF(L13+(L13*M$4)>$D13,$D13,L13+(L13*M$4))),"") -> 0 | N13: =IFERROR(IF($D13="","",IF(M13+(M13*N$4)>$D13,$D13,M13+(M13*N$4))),"") -> 0 | O13: =IFERROR(IF($D13="","",IF(N13+(N13*O$4)>$D13,$D13,N13+(N13*O$4))),"") -> 0 | P13: =IFERROR(IF($D13="","",IF(O13+(O13*P$4)>$D13,$D13,O13+(O13*P$4))),"") -> 0 | Q13: =IFERROR(IF($D13="","",IF(P13+(P13*Q$4)>$D13,$D13,P13+(P13*Q$4))),"") -> 0 | ... BM13: =IFERROR(IF($D13="","",IF(BL13+(BL13*BM$4)>$D13,$D13,BL13+(BL13*BM$4))),"") -> 0
B14: =Receitas_1!B14 -> Limpeza Empresarial 8 horas | C14: =SUM(F98:BN98)/SUM($F$97:$BN$97) -> #DIV/0! | D14: 0 | E14: 0 | I14: =IFERROR(IF($D14="","",$I$5*$D14),"") -> 0 | J14: =IFERROR(IF($D14="","",IF(I14+(I14*J$4)>$D14,$D14,I14+(I14*J$4))),"") -> 0 | K14: =IFERROR(IF($D14="","",IF(J14+(J14*K$4)>$D14,$D14,J14+(J14*K$4))),"") -> 0 | L14: =IFERROR(IF($D14="","",IF(K14+(K14*L$4)>$D14,$D14,K14+(K14*L$4))),"") -> 0 | M14: =IFERROR(IF($D14="","",IF(L14+(L14*M$4)>$D14,$D14,L14+(L14*M$4))),"") -> 0 | N14: =IFERROR(IF($D14="","",IF(M14+(M14*N$4)>$D14,$D14,M14+(M14*N$4))),"") -> 0 | O14: =IFERROR(IF($D14="","",IF(N14+(N14*O$4)>$D14,$D14,N14+(N14*O$4))),"") -> 0 | P14: =IFERROR(IF($D14="","",IF(O14+(O14*P$4)>$D14,$D14,O14+(O14*P$4))),"") -> 0 | Q14: =IFERROR(IF($D14="","",IF(P14+(P14*Q$4)>$D14,$D14,P14+(P14*Q$4))),"") -> 0 | ... BM14: =IFERROR(IF($D14="","",IF(BL14+(BL14*BM$4)>$D14,$D14,BL14+(BL14*BM$4))),"") -> 0
B15: =Receitas_1!B15 -> Passadoria - 6 horas | C15: =SUM(F99:BN99)/SUM($F$97:$BN$97) -> #DIV/0! | D15: 0 | E15: 0 | I15: =IFERROR(IF($D15="","",$I$5*$D15),"") -> 0 | J15: =IFERROR(IF($D15="","",IF(I15+(I15*J$4)>$D15,$D15,I15+(I15*J$4))),"") -> 0 | K15: =IFERROR(IF($D15="","",IF(J15+(J15*K$4)>$D15,$D15,J15+(J15*K$4))),"") -> 0 | L15: =IFERROR(IF($D15="","",IF(K15+(K15*L$4)>$D15,$D15,K15+(K15*L$4))),"") -> 0 | M15: =IFERROR(IF($D15="","",IF(L15+(L15*M$4)>$D15,$D15,L15+(L15*M$4))),"") -> 0 | N15: =IFERROR(IF($D15="","",IF(M15+(M15*N$4)>$D15,$D15,M15+(M15*N$4))),"") -> 0 | O15: =IFERROR(IF($D15="","",IF(N15+(N15*O$4)>$D15,$D15,N15+(N15*O$4))),"") -> 0 | P15: =IFERROR(IF($D15="","",IF(O15+(O15*P$4)>$D15,$D15,O15+(O15*P$4))),"") -> 0 | Q15: =IFERROR(IF($D15="","",IF(P15+(P15*Q$4)>$D15,$D15,P15+(P15*Q$4))),"") -> 0 | ... BM15: =IFERROR(IF($D15="","",IF(BL15+(BL15*BM$4)>$D15,$D15,BL15+(BL15*BM$4))),"") -> 0
B16: =Receitas_1!B16 -> Limpeza Empresarial 6 horas | C16: =SUM(F100:BN100)/SUM($F$97:$BN$97) -> #DIV/0! | D16: 0 | E16: 0 | I16: =IFERROR(IF($D16="","",$I$5*$D16),"") -> 0 | J16: =IFERROR(IF($D16="","",IF(I16+(I16*J$4)>$D16,$D16,I16+(I16*J$4))),"") -> 0 | K16: =IFERROR(IF($D16="","",IF(J16+(J16*K$4)>$D16,$D16,J16+(J16*K$4))),"") -> 0 | L16: =IFERROR(IF($D16="","",IF(K16+(K16*L$4)>$D16,$D16,K16+(K16*L$4))),"") -> 0 | M16: =IFERROR(IF($D16="","",IF(L16+(L16*M$4)>$D16,$D16,L16+(L16*M$4))),"") -> 0 | N16: =IFERROR(IF($D16="","",IF(M16+(M16*N$4)>$D16,$D16,M16+(M16*N$4))),"") -> 0 | O16: =IFERROR(IF($D16="","",IF(N16+(N16*O$4)>$D16,$D16,N16+(N16*O$4))),"") -> 0 | P16: =IFERROR(IF($D16="","",IF(O16+(O16*P$4)>$D16,$D16,O16+(O16*P$4))),"") -> 0 | Q16: =IFERROR(IF($D16="","",IF(P16+(P16*Q$4)>$D16,$D16,P16+(P16*Q$4))),"") -> 0 | ... BM16: =IFERROR(IF($D16="","",IF(BL16+(BL16*BM$4)>$D16,$D16,BL16+(BL16*BM$4))),"") -> 0
B17: =Receitas_1!B17 -> Limpeza condominial 2 horas | C17: =SUM(F101:BN101)/SUM($F$97:$BN$97) -> #DIV/0! | D17: 0 | E17: 0 | I17: =IFERROR(IF($D17="","",$I$5*$D17),"") -> 0 | J17: =IFERROR(IF($D17="","",IF(I17+(I17*J$4)>$D17,$D17,I17+(I17*J$4))),"") -> 0 | K17: =IFERROR(IF($D17="","",IF(J17+(J17*K$4)>$D17,$D17,J17+(J17*K$4))),"") -> 0 | L17: =IFERROR(IF($D17="","",IF(K17+(K17*L$4)>$D17,$D17,K17+(K17*L$4))),"") -> 0 | M17: =IFERROR(IF($D17="","",IF(L17+(L17*M$4)>$D17,$D17,L17+(L17*M$4))),"") -> 0 | N17: =IFERROR(IF($D17="","",IF(M17+(M17*N$4)>$D17,$D17,M17+(M17*N$4))),"") -> 0 | O17: =IFERROR(IF($D17="","",IF(N17+(N17*O$4)>$D17,$D17,N17+(N17*O$4))),"") -> 0 | P17: =IFERROR(IF($D17="","",IF(O17+(O17*P$4)>$D17,$D17,O17+(O17*P$4))),"") -> 0 | Q17: =IFERROR(IF($D17="","",IF(P17+(P17*Q$4)>$D17,$D17,P17+(P17*Q$4))),"") -> 0 | ... BM17: =IFERROR(IF($D17="","",IF(BL17+(BL17*BM$4)>$D17,$D17,BL17+(BL17*BM$4))),"") -> 0
B18: =Receitas_1!B18 -> Limpeza Empresarial 2 horas | C18: =SUM(F102:BN102)/SUM($F$97:$BN$97) -> #DIV/0! | D18: 0 | E18: 0 | I18: =IFERROR(IF($D18="","",$I$5*$D18),"") -> 0 | J18: =IFERROR(IF($D18="","",IF(I18+(I18*J$4)>$D18,$D18,I18+(I18*J$4))),"") -> 0 | K18: =IFERROR(IF($D18="","",IF(J18+(J18*K$4)>$D18,$D18,J18+(J18*K$4))),"") -> 0 | L18: =IFERROR(IF($D18="","",IF(K18+(K18*L$4)>$D18,$D18,K18+(K18*L$4))),"") -> 0 | M18: =IFERROR(IF($D18="","",IF(L18+(L18*M$4)>$D18,$D18,L18+(L18*M$4))),"") -> 0 | N18: =IFERROR(IF($D18="","",IF(M18+(M18*N$4)>$D18,$D18,M18+(M18*N$4))),"") -> 0 | O18: =IFERROR(IF($D18="","",IF(N18+(N18*O$4)>$D18,$D18,N18+(N18*O$4))),"") -> 0 | P18: =IFERROR(IF($D18="","",IF(O18+(O18*P$4)>$D18,$D18,O18+(O18*P$4))),"") -> 0 | Q18: =IFERROR(IF($D18="","",IF(P18+(P18*Q$4)>$D18,$D18,P18+(P18*Q$4))),"") -> 0 | ... BM18: =IFERROR(IF($D18="","",IF(BL18+(BL18*BM$4)>$D18,$D18,BL18+(BL18*BM$4))),"") -> 0
B19: =Receitas_1!B19 -> Limpeza pré e pós eventos 4 horas | C19: =SUM(F103:BN103)/SUM($F$97:$BN$97) -> #DIV/0! | D19: 0 | E19: 0 | I19: =IFERROR(IF($D19="","",$I$5*$D19),"") -> 0 | J19: =IFERROR(IF($D19="","",IF(I19+(I19*J$4)>$D19,$D19,I19+(I19*J$4))),"") -> 0 | K19: =IFERROR(IF($D19="","",IF(J19+(J19*K$4)>$D19,$D19,J19+(J19*K$4))),"") -> 0 | L19: =IFERROR(IF($D19="","",IF(K19+(K19*L$4)>$D19,$D19,K19+(K19*L$4))),"") -> 0 | M19: =IFERROR(IF($D19="","",IF(L19+(L19*M$4)>$D19,$D19,L19+(L19*M$4))),"") -> 0 | N19: =IFERROR(IF($D19="","",IF(M19+(M19*N$4)>$D19,$D19,M19+(M19*N$4))),"") -> 0 | O19: =IFERROR(IF($D19="","",IF(N19+(N19*O$4)>$D19,$D19,N19+(N19*O$4))),"") -> 0 | P19: =IFERROR(IF($D19="","",IF(O19+(O19*P$4)>$D19,$D19,O19+(O19*P$4))),"") -> 0 | Q19: =IFERROR(IF($D19="","",IF(P19+(P19*Q$4)>$D19,$D19,P19+(P19*Q$4))),"") -> 0 | ... BM19: =IFERROR(IF($D19="","",IF(BL19+(BL19*BM$4)>$D19,$D19,BL19+(BL19*BM$4))),"") -> 0
B20: =Receitas_1!B20 -> Limpeza Pré mudança 4 Horas | C20: =SUM(F104:BN104)/SUM($F$97:$BN$97) -> #DIV/0! | D20: 0 | E20: 0 | I20: =IFERROR(IF($D20="","",$I$5*$D20),"") -> 0 | J20: =IFERROR(IF($D20="","",IF(I20+(I20*J$4)>$D20,$D20,I20+(I20*J$4))),"") -> 0 | K20: =IFERROR(IF($D20="","",IF(J20+(J20*K$4)>$D20,$D20,J20+(J20*K$4))),"") -> 0 | L20: =IFERROR(IF($D20="","",IF(K20+(K20*L$4)>$D20,$D20,K20+(K20*L$4))),"") -> 0 | M20: =IFERROR(IF($D20="","",IF(L20+(L20*M$4)>$D20,$D20,L20+(L20*M$4))),"") -> 0 | N20: =IFERROR(IF($D20="","",IF(M20+(M20*N$4)>$D20,$D20,M20+(M20*N$4))),"") -> 0 | O20: =IFERROR(IF($D20="","",IF(N20+(N20*O$4)>$D20,$D20,N20+(N20*O$4))),"") -> 0 | P20: =IFERROR(IF($D20="","",IF(O20+(O20*P$4)>$D20,$D20,O20+(O20*P$4))),"") -> 0 | Q20: =IFERROR(IF($D20="","",IF(P20+(P20*Q$4)>$D20,$D20,P20+(P20*Q$4))),"") -> 0 | ... BM20: =IFERROR(IF($D20="","",IF(BL20+(BL20*BM$4)>$D20,$D20,BL20+(BL20*BM$4))),"") -> 0
B21: =Receitas_1!B21 -> Limpeza residencial + Lavar roupa 4 horas | C21: =SUM(F105:BN105)/SUM($F$97:$BN$97) -> #DIV/0! | D21: 0 | E21: 0 | I21: =IFERROR(IF($D21="","",$I$5*$D21),"") -> 0 | J21: =IFERROR(IF($D21="","",IF(I21+(I21*J$4)>$D21,$D21,I21+(I21*J$4))),"") -> 0 | K21: =IFERROR(IF($D21="","",IF(J21+(J21*K$4)>$D21,$D21,J21+(J21*K$4))),"") -> 0 | L21: =IFERROR(IF($D21="","",IF(K21+(K21*L$4)>$D21,$D21,K21+(K21*L$4))),"") -> 0 | M21: =IFERROR(IF($D21="","",IF(L21+(L21*M$4)>$D21,$D21,L21+(L21*M$4))),"") -> 0 | N21: =IFERROR(IF($D21="","",IF(M21+(M21*N$4)>$D21,$D21,M21+(M21*N$4))),"") -> 0 | O21: =IFERROR(IF($D21="","",IF(N21+(N21*O$4)>$D21,$D21,N21+(N21*O$4))),"") -> 0 | P21: =IFERROR(IF($D21="","",IF(O21+(O21*P$4)>$D21,$D21,O21+(O21*P$4))),"") -> 0 | Q21: =IFERROR(IF($D21="","",IF(P21+(P21*Q$4)>$D21,$D21,P21+(P21*Q$4))),"") -> 0 | ... BM21: =IFERROR(IF($D21="","",IF(BL21+(BL21*BM$4)>$D21,$D21,BL21+(BL21*BM$4))),"") -> 0
B22: =Receitas_1!B22 -> Limpeza vidros 4 horas | C22: =SUM(F106:BN106)/SUM($F$97:$BN$97) -> #DIV/0! | D22: 0 | E22: 0 | I22: =IFERROR(IF($D22="","",$I$5*$D22),"") -> 0 | J22: =IFERROR(IF($D22="","",IF(I22+(I22*J$4)>$D22,$D22,I22+(I22*J$4))),"") -> 0 | K22: =IFERROR(IF($D22="","",IF(J22+(J22*K$4)>$D22,$D22,J22+(J22*K$4))),"") -> 0 | L22: =IFERROR(IF($D22="","",IF(K22+(K22*L$4)>$D22,$D22,K22+(K22*L$4))),"") -> 0 | M22: =IFERROR(IF($D22="","",IF(L22+(L22*M$4)>$D22,$D22,L22+(L22*M$4))),"") -> 0 | N22: =IFERROR(IF($D22="","",IF(M22+(M22*N$4)>$D22,$D22,M22+(M22*N$4))),"") -> 0 | O22: =IFERROR(IF($D22="","",IF(N22+(N22*O$4)>$D22,$D22,N22+(N22*O$4))),"") -> 0 | P22: =IFERROR(IF($D22="","",IF(O22+(O22*P$4)>$D22,$D22,O22+(O22*P$4))),"") -> 0 | Q22: =IFERROR(IF($D22="","",IF(P22+(P22*Q$4)>$D22,$D22,P22+(P22*Q$4))),"") -> 0 | ... BM22: =IFERROR(IF($D22="","",IF(BL22+(BL22*BM$4)>$D22,$D22,BL22+(BL22*BM$4))),"") -> 0
B23: =Receitas_1!B23 -> Limpeza residencial + Lavar roupa 6 horas | C23: =SUM(F107:BN107)/SUM($F$97:$BN$97) -> #DIV/0! | D23: 0 | E23: 0 | I23: =IFERROR(IF($D23="","",$I$5*$D23),"") -> 0 | J23: =IFERROR(IF($D23="","",IF(I23+(I23*J$4)>$D23,$D23,I23+(I23*J$4))),"") -> 0 | K23: =IFERROR(IF($D23="","",IF(J23+(J23*K$4)>$D23,$D23,J23+(J23*K$4))),"") -> 0 | L23: =IFERROR(IF($D23="","",IF(K23+(K23*L$4)>$D23,$D23,K23+(K23*L$4))),"") -> 0 | M23: =IFERROR(IF($D23="","",IF(L23+(L23*M$4)>$D23,$D23,L23+(L23*M$4))),"") -> 0 | N23: =IFERROR(IF($D23="","",IF(M23+(M23*N$4)>$D23,$D23,M23+(M23*N$4))),"") -> 0 | O23: =IFERROR(IF($D23="","",IF(N23+(N23*O$4)>$D23,$D23,N23+(N23*O$4))),"") -> 0 | P23: =IFERROR(IF($D23="","",IF(O23+(O23*P$4)>$D23,$D23,O23+(O23*P$4))),"") -> 0 | Q23: =IFERROR(IF($D23="","",IF(P23+(P23*Q$4)>$D23,$D23,P23+(P23*Q$4))),"") -> 0 | ... BM23: =IFERROR(IF($D23="","",IF(BL23+(BL23*BM$4)>$D23,$D23,BL23+(BL23*BM$4))),"") -> 0
B24: =Receitas_1!B24 -> Limpeza vidros 2 horas | C24: =SUM(F146:BN146)/SUM($F$97:$BN$97) -> #DIV/0! | D24: 0 | E24: 0 | I24: =IFERROR(IF($D24="","",$I$5*$D24),"") -> 0 | J24: =IFERROR(IF($D24="","",IF(I24+(I24*J$4)>$D24,$D24,I24+(I24*J$4))),"") -> 0 | K24: =IFERROR(IF($D24="","",IF(J24+(J24*K$4)>$D24,$D24,J24+(J24*K$4))),"") -> 0 | L24: =IFERROR(IF($D24="","",IF(K24+(K24*L$4)>$D24,$D24,K24+(K24*L$4))),"") -> 0 | M24: =IFERROR(IF($D24="","",IF(L24+(L24*M$4)>$D24,$D24,L24+(L24*M$4))),"") -> 0 | N24: =IFERROR(IF($D24="","",IF(M24+(M24*N$4)>$D24,$D24,M24+(M24*N$4))),"") -> 0 | O24: =IFERROR(IF($D24="","",IF(N24+(N24*O$4)>$D24,$D24,N24+(N24*O$4))),"") -> 0 | P24: =IFERROR(IF($D24="","",IF(O24+(O24*P$4)>$D24,$D24,O24+(O24*P$4))),"") -> 0 | Q24: =IFERROR(IF($D24="","",IF(P24+(P24*Q$4)>$D24,$D24,P24+(P24*Q$4))),"") -> 0 | ... BM24: =IFERROR(IF($D24="","",IF(BL24+(BL24*BM$4)>$D24,$D24,BL24+(BL24*BM$4))),"") -> 0
B25: =Receitas_1!B25 -> Limpeza condominial 8 horas | C25: =SUM(F147:BN147)/SUM($F$97:$BN$97) -> #DIV/0! | D25: 0 | E25: 0 | I25: =IFERROR(IF($D25="","",$I$5*$D25),"") -> 0 | J25: =IFERROR(IF($D25="","",IF(I25+(I25*J$4)>$D25,$D25,I25+(I25*J$4))),"") -> 0 | K25: =IFERROR(IF($D25="","",IF(J25+(J25*K$4)>$D25,$D25,J25+(J25*K$4))),"") -> 0 | L25: =IFERROR(IF($D25="","",IF(K25+(K25*L$4)>$D25,$D25,K25+(K25*L$4))),"") -> 0 | M25: =IFERROR(IF($D25="","",IF(L25+(L25*M$4)>$D25,$D25,L25+(L25*M$4))),"") -> 0 | N25: =IFERROR(IF($D25="","",IF(M25+(M25*N$4)>$D25,$D25,M25+(M25*N$4))),"") -> 0 | O25: =IFERROR(IF($D25="","",IF(N25+(N25*O$4)>$D25,$D25,N25+(N25*O$4))),"") -> 0 | P25: =IFERROR(IF($D25="","",IF(O25+(O25*P$4)>$D25,$D25,O25+(O25*P$4))),"") -> 0 | Q25: =IFERROR(IF($D25="","",IF(P25+(P25*Q$4)>$D25,$D25,P25+(P25*Q$4))),"") -> 0 | ... BM25: =IFERROR(IF($D25="","",IF(BL25+(BL25*BM$4)>$D25,$D25,BL25+(BL25*BM$4))),"") -> 0
B26: =Receitas_1!B26 -> Limpeza Pré mudança 8 Horas | C26: =SUM(F148:BN148)/SUM($F$97:$BN$97) -> #DIV/0! | D26: 0 | E26: 0 | I26: =IFERROR(IF($D26="","",$I$5*$D26),"") -> 0 | J26: =IFERROR(IF($D26="","",IF(I26+(I26*J$4)>$D26,$D26,I26+(I26*J$4))),"") -> 0 | K26: =IFERROR(IF($D26="","",IF(J26+(J26*K$4)>$D26,$D26,J26+(J26*K$4))),"") -> 0 | L26: =IFERROR(IF($D26="","",IF(K26+(K26*L$4)>$D26,$D26,K26+(K26*L$4))),"") -> 0 | M26: =IFERROR(IF($D26="","",IF(L26+(L26*M$4)>$D26,$D26,L26+(L26*M$4))),"") -> 0 | N26: =IFERROR(IF($D26="","",IF(M26+(M26*N$4)>$D26,$D26,M26+(M26*N$4))),"") -> 0 | O26: =IFERROR(IF($D26="","",IF(N26+(N26*O$4)>$D26,$D26,N26+(N26*O$4))),"") -> 0 | P26: =IFERROR(IF($D26="","",IF(O26+(O26*P$4)>$D26,$D26,O26+(O26*P$4))),"") -> 0 | Q26: =IFERROR(IF($D26="","",IF(P26+(P26*Q$4)>$D26,$D26,P26+(P26*Q$4))),"") -> 0 | ... BM26: =IFERROR(IF($D26="","",IF(BL26+(BL26*BM$4)>$D26,$D26,BL26+(BL26*BM$4))),"") -> 0
B27: =Receitas_1!B27 -> Limpeza residencial + Lavar roupa 8 horas | C27: =SUM(F149:BN149)/SUM($F$97:$BN$97) -> #DIV/0! | D27: 0 | E27: 0 | I27: =IFERROR(IF($D27="","",$I$5*$D27),"") -> 0 | J27: =IFERROR(IF($D27="","",IF(I27+(I27*J$4)>$D27,$D27,I27+(I27*J$4))),"") -> 0 | K27: =IFERROR(IF($D27="","",IF(J27+(J27*K$4)>$D27,$D27,J27+(J27*K$4))),"") -> 0 | L27: =IFERROR(IF($D27="","",IF(K27+(K27*L$4)>$D27,$D27,K27+(K27*L$4))),"") -> 0 | M27: =IFERROR(IF($D27="","",IF(L27+(L27*M$4)>$D27,$D27,L27+(L27*M$4))),"") -> 0 | N27: =IFERROR(IF($D27="","",IF(M27+(M27*N$4)>$D27,$D27,M27+(M27*N$4))),"") -> 0 | O27: =IFERROR(IF($D27="","",IF(N27+(N27*O$4)>$D27,$D27,N27+(N27*O$4))),"") -> 0 | P27: =IFERROR(IF($D27="","",IF(O27+(O27*P$4)>$D27,$D27,O27+(O27*P$4))),"") -> 0 | Q27: =IFERROR(IF($D27="","",IF(P27+(P27*Q$4)>$D27,$D27,P27+(P27*Q$4))),"") -> 0 | ... BM27: =IFERROR(IF($D27="","",IF(BL27+(BL27*BM$4)>$D27,$D27,BL27+(BL27*BM$4))),"") -> 0
B28: =Receitas_1!B28 -> Passadoria - 2 horas | C28: =SUM(F150:BN150)/SUM($F$97:$BN$97) -> #DIV/0! | D28: 0 | E28: 0 | I28: =IFERROR(IF($D28="","",$I$5*$D28),"") -> 0 | J28: =IFERROR(IF($D28="","",IF(I28+(I28*J$4)>$D28,$D28,I28+(I28*J$4))),"") -> 0 | K28: =IFERROR(IF($D28="","",IF(J28+(J28*K$4)>$D28,$D28,J28+(J28*K$4))),"") -> 0 | L28: =IFERROR(IF($D28="","",IF(K28+(K28*L$4)>$D28,$D28,K28+(K28*L$4))),"") -> 0 | M28: =IFERROR(IF($D28="","",IF(L28+(L28*M$4)>$D28,$D28,L28+(L28*M$4))),"") -> 0 | N28: =IFERROR(IF($D28="","",IF(M28+(M28*N$4)>$D28,$D28,M28+(M28*N$4))),"") -> 0 | O28: =IFERROR(IF($D28="","",IF(N28+(N28*O$4)>$D28,$D28,N28+(N28*O$4))),"") -> 0 | P28: =IFERROR(IF($D28="","",IF(O28+(O28*P$4)>$D28,$D28,O28+(O28*P$4))),"") -> 0 | Q28: =IFERROR(IF($D28="","",IF(P28+(P28*Q$4)>$D28,$D28,P28+(P28*Q$4))),"") -> 0 | ... BM28: =IFERROR(IF($D28="","",IF(BL28+(BL28*BM$4)>$D28,$D28,BL28+(BL28*BM$4))),"") -> 0
B29: =Receitas_1!B29 -> Passadoria - 8 horas | C29: =SUM(F151:BN151)/SUM($F$97:$BN$97) -> #DIV/0! | D29: 0 | E29: 0 | I29: =IFERROR(IF($D29="","",$I$5*$D29),"") -> 0 | J29: =IFERROR(IF($D29="","",IF(I29+(I29*J$4)>$D29,$D29,I29+(I29*J$4))),"") -> 0 | K29: =IFERROR(IF($D29="","",IF(J29+(J29*K$4)>$D29,$D29,J29+(J29*K$4))),"") -> 0 | L29: =IFERROR(IF($D29="","",IF(K29+(K29*L$4)>$D29,$D29,K29+(K29*L$4))),"") -> 0 | M29: =IFERROR(IF($D29="","",IF(L29+(L29*M$4)>$D29,$D29,L29+(L29*M$4))),"") -> 0 | N29: =IFERROR(IF($D29="","",IF(M29+(M29*N$4)>$D29,$D29,M29+(M29*N$4))),"") -> 0 | O29: =IFERROR(IF($D29="","",IF(N29+(N29*O$4)>$D29,$D29,N29+(N29*O$4))),"") -> 0 | P29: =IFERROR(IF($D29="","",IF(O29+(O29*P$4)>$D29,$D29,O29+(O29*P$4))),"") -> 0 | Q29: =IFERROR(IF($D29="","",IF(P29+(P29*Q$4)>$D29,$D29,P29+(P29*Q$4))),"") -> 0 | ... BM29: =IFERROR(IF($D29="","",IF(BL29+(BL29*BM$4)>$D29,$D29,BL29+(BL29*BM$4))),"") -> 0
B30: =Receitas_1!B30 -> Limpeza residencial + Lavar roupa 2 horas | C30: =SUM(F152:BN152)/SUM($F$97:$BN$97) -> #DIV/0! | D30: 0 | E30: 0 | I30: =IFERROR(IF($D30="","",$I$5*$D30),"") -> 0 | J30: =IFERROR(IF($D30="","",IF(I30+(I30*J$4)>$D30,$D30,I30+(I30*J$4))),"") -> 0 | K30: =IFERROR(IF($D30="","",IF(J30+(J30*K$4)>$D30,$D30,J30+(J30*K$4))),"") -> 0 | L30: =IFERROR(IF($D30="","",IF(K30+(K30*L$4)>$D30,$D30,K30+(K30*L$4))),"") -> 0 | M30: =IFERROR(IF($D30="","",IF(L30+(L30*M$4)>$D30,$D30,L30+(L30*M$4))),"") -> 0 | N30: =IFERROR(IF($D30="","",IF(M30+(M30*N$4)>$D30,$D30,M30+(M30*N$4))),"") -> 0 | O30: =IFERROR(IF($D30="","",IF(N30+(N30*O$4)>$D30,$D30,N30+(N30*O$4))),"") -> 0 | P30: =IFERROR(IF($D30="","",IF(O30+(O30*P$4)>$D30,$D30,O30+(O30*P$4))),"") -> 0 | Q30: =IFERROR(IF($D30="","",IF(P30+(P30*Q$4)>$D30,$D30,P30+(P30*Q$4))),"") -> 0 | ... BM30: =IFERROR(IF($D30="","",IF(BL30+(BL30*BM$4)>$D30,$D30,BL30+(BL30*BM$4))),"") -> 0
B31: =Receitas_1!B31 -> Limpeza vidros 6 horas | C31: =SUM(F153:BN153)/SUM($F$97:$BN$97) -> #DIV/0! | D31: 0 | E31: 0 | I31: =IFERROR(IF($D31="","",$I$5*$D31),"") -> 0 | J31: =IFERROR(IF($D31="","",IF(I31+(I31*J$4)>$D31,$D31,I31+(I31*J$4))),"") -> 0 | K31: =IFERROR(IF($D31="","",IF(J31+(J31*K$4)>$D31,$D31,J31+(J31*K$4))),"") -> 0 | L31: =IFERROR(IF($D31="","",IF(K31+(K31*L$4)>$D31,$D31,K31+(K31*L$4))),"") -> 0 | M31: =IFERROR(IF($D31="","",IF(L31+(L31*M$4)>$D31,$D31,L31+(L31*M$4))),"") -> 0 | N31: =IFERROR(IF($D31="","",IF(M31+(M31*N$4)>$D31,$D31,M31+(M31*N$4))),"") -> 0 | O31: =IFERROR(IF($D31="","",IF(N31+(N31*O$4)>$D31,$D31,N31+(N31*O$4))),"") -> 0 | P31: =IFERROR(IF($D31="","",IF(O31+(O31*P$4)>$D31,$D31,O31+(O31*P$4))),"") -> 0 | Q31: =IFERROR(IF($D31="","",IF(P31+(P31*Q$4)>$D31,$D31,P31+(P31*Q$4))),"") -> 0 | ... BM31: =IFERROR(IF($D31="","",IF(BL31+(BL31*BM$4)>$D31,$D31,BL31+(BL31*BM$4))),"") -> 0
B32: =Receitas_1!B32 -> Limpeza vidros 8 horas | C32: =SUM(F154:BN154)/SUM($F$97:$BN$97) -> #DIV/0! | D32: 0 | E32: 0 | I32: =IFERROR(IF($D32="","",$I$5*$D32),"") -> 0 | J32: =IFERROR(IF($D32="","",IF(I32+(I32*J$4)>$D32,$D32,I32+(I32*J$4))),"") -> 0 | K32: =IFERROR(IF($D32="","",IF(J32+(J32*K$4)>$D32,$D32,J32+(J32*K$4))),"") -> 0 | L32: =IFERROR(IF($D32="","",IF(K32+(K32*L$4)>$D32,$D32,K32+(K32*L$4))),"") -> 0 | M32: =IFERROR(IF($D32="","",IF(L32+(L32*M$4)>$D32,$D32,L32+(L32*M$4))),"") -> 0 | N32: =IFERROR(IF($D32="","",IF(M32+(M32*N$4)>$D32,$D32,M32+(M32*N$4))),"") -> 0 | O32: =IFERROR(IF($D32="","",IF(N32+(N32*O$4)>$D32,$D32,N32+(N32*O$4))),"") -> 0 | P32: =IFERROR(IF($D32="","",IF(O32+(O32*P$4)>$D32,$D32,O32+(O32*P$4))),"") -> 0 | Q32: =IFERROR(IF($D32="","",IF(P32+(P32*Q$4)>$D32,$D32,P32+(P32*Q$4))),"") -> 0 | ... BM32: =IFERROR(IF($D32="","",IF(BL32+(BL32*BM$4)>$D32,$D32,BL32+(BL32*BM$4))),"") -> 0
B33: =Receitas_1!B33 -> Limpeza pré e pós eventos 2 horas | C33: =SUM(F155:BN155)/SUM($F$97:$BN$97) -> #DIV/0! | D33: 0 | E33: 0 | I33: =IFERROR(IF($D33="","",$I$5*$D33),"") -> 0 | J33: =IFERROR(IF($D33="","",IF(I33+(I33*J$4)>$D33,$D33,I33+(I33*J$4))),"") -> 0 | K33: =IFERROR(IF($D33="","",IF(J33+(J33*K$4)>$D33,$D33,J33+(J33*K$4))),"") -> 0 | L33: =IFERROR(IF($D33="","",IF(K33+(K33*L$4)>$D33,$D33,K33+(K33*L$4))),"") -> 0 | M33: =IFERROR(IF($D33="","",IF(L33+(L33*M$4)>$D33,$D33,L33+(L33*M$4))),"") -> 0 | N33: =IFERROR(IF($D33="","",IF(M33+(M33*N$4)>$D33,$D33,M33+(M33*N$4))),"") -> 0 | O33: =IFERROR(IF($D33="","",IF(N33+(N33*O$4)>$D33,$D33,N33+(N33*O$4))),"") -> 0 | P33: =IFERROR(IF($D33="","",IF(O33+(O33*P$4)>$D33,$D33,O33+(O33*P$4))),"") -> 0 | Q33: =IFERROR(IF($D33="","",IF(P33+(P33*Q$4)>$D33,$D33,P33+(P33*Q$4))),"") -> 0 | ... BM33: =IFERROR(IF($D33="","",IF(BL33+(BL33*BM$4)>$D33,$D33,BL33+(BL33*BM$4))),"") -> 0
B34: =Receitas_1!B34 -> Limpeza pré e pós eventos 6 horas | C34: =SUM(F156:BN156)/SUM($F$97:$BN$97) -> #DIV/0! | D34: 0 | E34: 0 | I34: =IFERROR(IF($D34="","",$I$5*$D34),"") -> 0 | J34: =IFERROR(IF($D34="","",IF(I34+(I34*J$4)>$D34,$D34,I34+(I34*J$4))),"") -> 0 | K34: =IFERROR(IF($D34="","",IF(J34+(J34*K$4)>$D34,$D34,J34+(J34*K$4))),"") -> 0 | L34: =IFERROR(IF($D34="","",IF(K34+(K34*L$4)>$D34,$D34,K34+(K34*L$4))),"") -> 0 | M34: =IFERROR(IF($D34="","",IF(L34+(L34*M$4)>$D34,$D34,L34+(L34*M$4))),"") -> 0 | N34: =IFERROR(IF($D34="","",IF(M34+(M34*N$4)>$D34,$D34,M34+(M34*N$4))),"") -> 0 | O34: =IFERROR(IF($D34="","",IF(N34+(N34*O$4)>$D34,$D34,N34+(N34*O$4))),"") -> 0 | P34: =IFERROR(IF($D34="","",IF(O34+(O34*P$4)>$D34,$D34,O34+(O34*P$4))),"") -> 0 | Q34: =IFERROR(IF($D34="","",IF(P34+(P34*Q$4)>$D34,$D34,P34+(P34*Q$4))),"") -> 0 | ... BM34: =IFERROR(IF($D34="","",IF(BL34+(BL34*BM$4)>$D34,$D34,BL34+(BL34*BM$4))),"") -> 0
B35: =Receitas_1!B35 -> Limpeza pré e pós eventos 8 horas | C35: =SUM(F157:BN157)/SUM($F$97:$BN$97) -> #DIV/0! | D35: 0 | E35: 0 | I35: =IFERROR(IF($D35="","",$I$5*$D35),"") -> 0 | J35: =IFERROR(IF($D35="","",IF(I35+(I35*J$4)>$D35,$D35,I35+(I35*J$4))),"") -> 0 | K35: =IFERROR(IF($D35="","",IF(J35+(J35*K$4)>$D35,$D35,J35+(J35*K$4))),"") -> 0 | L35: =IFERROR(IF($D35="","",IF(K35+(K35*L$4)>$D35,$D35,K35+(K35*L$4))),"") -> 0 | M35: =IFERROR(IF($D35="","",IF(L35+(L35*M$4)>$D35,$D35,L35+(L35*M$4))),"") -> 0 | N35: =IFERROR(IF($D35="","",IF(M35+(M35*N$4)>$D35,$D35,M35+(M35*N$4))),"") -> 0 | O35: =IFERROR(IF($D35="","",IF(N35+(N35*O$4)>$D35,$D35,N35+(N35*O$4))),"") -> 0 | P35: =IFERROR(IF($D35="","",IF(O35+(O35*P$4)>$D35,$D35,O35+(O35*P$4))),"") -> 0 | Q35: =IFERROR(IF($D35="","",IF(P35+(P35*Q$4)>$D35,$D35,P35+(P35*Q$4))),"") -> 0 | ... BM35: =IFERROR(IF($D35="","",IF(BL35+(BL35*BM$4)>$D35,$D35,BL35+(BL35*BM$4))),"") -> 0
... B49: =Receitas_1!B49 -> Garçom 6 horas | C49: =SUM(F171:BN171)/SUM($F$97:$BN$97) -> #DIV/0! | D49: 0 | E49: 0 | I49: =IFERROR(IF($D49="","",$I$5*$D49),"") -> 0 | J49: =IFERROR(IF($D49="","",IF(I49+(I49*J$4)>$D49,$D49,I49+(I49*J$4))),"") -> 0 | K49: =IFERROR(IF($D49="","",IF(J49+(J49*K$4)>$D49,$D49,J49+(J49*K$4))),"") -> 0 | L49: =IFERROR(IF($D49="","",IF(K49+(K49*L$4)>$D49,$D49,K49+(K49*L$4))),"") -> 0 | M49: =IFERROR(IF($D49="","",IF(L49+(L49*M$4)>$D49,$D49,L49+(L49*M$4))),"") -> 0 | N49: =IFERROR(IF($D49="","",IF(M49+(M49*N$4)>$D49,$D49,M49+(M49*N$4))),"") -> 0 | O49: =IFERROR(IF($D49="","",IF(N49+(N49*O$4)>$D49,$D49,N49+(N49*O$4))),"") -> 0 | P49: =IFERROR(IF($D49="","",IF(O49+(O49*P$4)>$D49,$D49,O49+(O49*P$4))),"") -> 0 | Q49: =IFERROR(IF($D49="","",IF(P49+(P49*Q$4)>$D49,$D49,P49+(P49*Q$4))),"") -> 0 | ... BM49: =IFERROR(IF($D49="","",IF(BL49+(BL49*BM$4)>$D49,$D49,BL49+(BL49*BM$4))),"") -> 0
B50: =Receitas_1!B50 -> Garçom 8 horas | C50: =SUM(F96:BN96)/SUM($F$97:$BN$97) -> #DIV/0! | D50: 0 | E50: 0 | I50: =IFERROR(IF($D50="","",$I$5*$D50),"") -> 0 | J50: =IFERROR(IF($D50="","",IF(I50+(I50*J$4)>$D50,$D50,I50+(I50*J$4))),"") -> 0 | K50: =IFERROR(IF($D50="","",IF(J50+(J50*K$4)>$D50,$D50,J50+(J50*K$4))),"") -> 0 | L50: =IFERROR(IF($D50="","",IF(K50+(K50*L$4)>$D50,$D50,K50+(K50*L$4))),"") -> 0 | M50: =IFERROR(IF($D50="","",IF(L50+(L50*M$4)>$D50,$D50,L50+(L50*M$4))),"") -> 0 | N50: =IFERROR(IF($D50="","",IF(M50+(M50*N$4)>$D50,$D50,M50+(M50*N$4))),"") -> 0 | O50: =IFERROR(IF($D50="","",IF(N50+(N50*O$4)>$D50,$D50,N50+(N50*O$4))),"") -> 0 | P50: =IFERROR(IF($D50="","",IF(O50+(O50*P$4)>$D50,$D50,O50+(O50*P$4))),"") -> 0 | Q50: =IFERROR(IF($D50="","",IF(P50+(P50*Q$4)>$D50,$D50,P50+(P50*Q$4))),"") -> 0 | ... BM50: =IFERROR(IF($D50="","",IF(BL50+(BL50*BM$4)>$D50,$D50,BL50+(BL50*BM$4))),"") -> 0
B51: Faturamento Bruto | C51: Preço Médio de Venda em R$ | D51: Receita Potencial | E51: Receita Média | BP51: R$ | BQ51: R$ | BR51: R$ | BS51: R$
B52: =B6 -> Limpeza Residencial - 4 horas | C52: 0 | D52: =IFERROR(C52*D6,"") -> 0 | E52: =IFERROR(AVERAGE(I52:BN52),"") -> 0 | I52: =$C52*I6 -> 0 | J52: =$C52*J6 -> 0 | K52: =$C52*K6 -> 0 | L52: =$C52*L6 -> 0 | M52: =$C52*M6 -> 0 | N52: =$C52*N6 -> 0 | O52: =$C52*O6 -> 0 | P52: =$C52*P6 -> 0 | ... BM52: =$C52*BM6 -> 0
B53: =B7 -> Limpeza Empresarial 4 horas | C53: 0 | D53: =IFERROR(C53*D7,"") -> 0 | E53: =IFERROR(AVERAGE(I53:BN53),"") -> 0 | I53: =$C53*I7 -> 0 | J53: =$C53*J7 -> 0 | K53: =$C53*K7 -> 0 | L53: =$C53*L7 -> 0 | M53: =$C53*M7 -> 0 | N53: =$C53*N7 -> 0 | O53: =$C53*O7 -> 0 | P53: =$C53*P7 -> 0 | ... BM53: =$C53*BM7 -> 0
B54: =B8 -> Limpeza condominial 4 horas | C54: 0 | D54: =IFERROR(C54*D8,"") -> 0 | E54: =IFERROR(AVERAGE(I54:BN54),"") -> 0 | I54: =$C54*I8 -> 0 | J54: =$C54*J8 -> 0 | K54: =$C54*K8 -> 0 | L54: =$C54*L8 -> 0 | M54: =$C54*M8 -> 0 | N54: =$C54*N8 -> 0 | O54: =$C54*O8 -> 0 | P54: =$C54*P8 -> 0 | ... BM54: =$C54*BM8 -> 0
B55: =B9 -> Passadoria - 4 horas | C55: 0 | D55: =IFERROR(C55*D9,"") -> 0 | E55: =IFERROR(AVERAGE(I55:BN55),"") -> 0 | I55: =$C55*I9 -> 0 | J55: =$C55*J9 -> 0 | K55: =$C55*K9 -> 0 | L55: =$C55*L9 -> 0 | M55: =$C55*M9 -> 0 | N55: =$C55*N9 -> 0 | O55: =$C55*O9 -> 0 | P55: =$C55*P9 -> 0 | ... BM55: =$C55*BM9 -> 0
B56: =B10 -> Limpeza Residencial - 6 horas | C56: 0 | D56: =IFERROR(C56*D10,"") -> 0 | E56: =IFERROR(AVERAGE(I56:BN56),"") -> 0 | I56: =$C56*I10 -> 0 | J56: =$C56*J10 -> 0 | K56: =$C56*K10 -> 0 | L56: =$C56*L10 -> 0 | M56: =$C56*M10 -> 0 | N56: =$C56*N10 -> 0 | O56: =$C56*O10 -> 0 | P56: =$C56*P10 -> 0 | ... BM56: =$C56*BM10 -> 0
B57: =B11 -> Limpeza Residencial - 8 horas | C57: 0 | D57: =IFERROR(C57*D11,"") -> 0 | E57: =IFERROR(AVERAGE(I57:BN57),"") -> 0 | I57: =$C57*I11 -> 0 | J57: =$C57*J11 -> 0 | K57: =$C57*K11 -> 0 | L57: =$C57*L11 -> 0 | M57: =$C57*M11 -> 0 | N57: =$C57*N11 -> 0 | O57: =$C57*O11 -> 0 | P57: =$C57*P11 -> 0 | ... BM57: =$C57*BM11 -> 0
B58: =B12 -> Limpeza Residencial - 2 horas | C58: 0 | D58: =IFERROR(C58*D12,"") -> 0 | E58: =IFERROR(AVERAGE(I58:BN58),"") -> 0 | I58: =$C58*I12 -> 0 | J58: =$C58*J12 -> 0 | K58: =$C58*K12 -> 0 | L58: =$C58*L12 -> 0 | M58: =$C58*M12 -> 0 | N58: =$C58*N12 -> 0 | O58: =$C58*O12 -> 0 | P58: =$C58*P12 -> 0 | ... BM58: =$C58*BM12 -> 0
B59: =B13 -> Babá 4 horas | C59: 0 | D59: =IFERROR(C59*D13,"") -> 0 | E59: =IFERROR(AVERAGE(I59:BN59),"") -> 0 | I59: =$C59*I13 -> 0 | J59: =$C59*J13 -> 0 | K59: =$C59*K13 -> 0 | L59: =$C59*L13 -> 0 | M59: =$C59*M13 -> 0 | N59: =$C59*N13 -> 0 | O59: =$C59*O13 -> 0 | P59: =$C59*P13 -> 0 | ... BM59: =$C59*BM13 -> 0
B60: =B14 -> Limpeza Empresarial 8 horas | C60: 0 | D60: =IFERROR(C60*D14,"") -> 0 | E60: =IFERROR(AVERAGE(I60:BN60),"") -> 0 | I60: =$C60*I14 -> 0 | J60: =$C60*J14 -> 0 | K60: =$C60*K14 -> 0 | L60: =$C60*L14 -> 0 | M60: =$C60*M14 -> 0 | N60: =$C60*N14 -> 0 | O60: =$C60*O14 -> 0 | P60: =$C60*P14 -> 0 | ... BM60: =$C60*BM14 -> 0
B61: =B15 -> Passadoria - 6 horas | C61: 0 | D61: =IFERROR(C61*D15,"") -> 0 | E61: =IFERROR(AVERAGE(I61:BN61),"") -> 0 | I61: =$C61*I15 -> 0 | J61: =$C61*J15 -> 0 | K61: =$C61*K15 -> 0 | L61: =$C61*L15 -> 0 | M61: =$C61*M15 -> 0 | N61: =$C61*N15 -> 0 | O61: =$C61*O15 -> 0 | P61: =$C61*P15 -> 0 | ... BM61: =$C61*BM15 -> 0
B62: =B16 -> Limpeza Empresarial 6 horas | C62: 0 | D62: =IFERROR(C62*D16,"") -> 0 | E62: =IFERROR(AVERAGE(I62:BN62),"") -> 0 | I62: =$C62*I16 -> 0 | J62: =$C62*J16 -> 0 | K62: =$C62*K16 -> 0 | L62: =$C62*L16 -> 0 | M62: =$C62*M16 -> 0 | N62: =$C62*N16 -> 0 | O62: =$C62*O16 -> 0 | P62: =$C62*P16 -> 0 | ... BM62: =$C62*BM16 -> 0
B63: =B17 -> Limpeza condominial 2 horas | C63: 0 | D63: =IFERROR(C63*D17,"") -> 0 | E63: =IFERROR(AVERAGE(I63:BN63),"") -> 0 | I63: =$C63*I17 -> 0 | J63: =$C63*J17 -> 0 | K63: =$C63*K17 -> 0 | L63: =$C63*L17 -> 0 | M63: =$C63*M17 -> 0 | N63: =$C63*N17 -> 0 | O63: =$C63*O17 -> 0 | P63: =$C63*P17 -> 0 | ... BM63: =$C63*BM17 -> 0
... B96: =B50 -> Garçom 8 horas | C96: 0 | D96: =IFERROR(C96*D50,"") -> 0 | E96: =IFERROR(AVERAGE(I96:BN96),"") -> 0 | I96: =$C96*I50 -> 0 | J96: =$C96*J50 -> 0 | K96: =$C96*K50 -> 0 | L96: =$C96*L50 -> 0 | M96: =$C96*M50 -> 0 | N96: =$C96*N50 -> 0 | O96: =$C96*O50 -> 0 | P96: =$C96*P50 -> 0 | ... BM96: =$C96*BM50 -> 0
B97: Receita Total Mês (Potencial / Média) | D97: =SUM(D52:D96) -> 0 | E97: =SUM(E52:E96) -> 0 | I97: =SUM(I52:I96) -> 0 | J97: =SUM(J52:J96) -> 0 | K97: =SUM(K52:K96) -> 0 | L97: =SUM(L52:L96) -> 0 | M97: =SUM(M52:M96) -> 0 | N97: =SUM(N52:N96) -> 0 | O97: =SUM(O52:O96) -> 0 | P97: =SUM(P52:P96) -> 0 | ... BM97: =SUM(BM52:BM96) -> 0 | BP97: =SUMIF($F$2:$BA$2,BP$2,$F97:$BB97) -> 0 | BQ97: =SUMIF($F$2:$BA$2,BQ$2,$F97:$BB97) -> 0 | BR97: =SUMIF($F$2:$BA$2,BR$2,$F97:$BB97) -> 0 | BS97: =SUMIF($F$2:$BA$2,BS$2,$F97:$BB97) -> 0 | BT97: =SUM(BT52:BT96) -> 0
B98: Ticket Médio | C98: 33
B99: Quantidade de Clientes | I99: =I97/$C$98 -> 0 | J99: =J97/$C$98 -> 0 | K99: =K97/$C$98 -> 0 | L99: =L97/$C$98 -> 0 | M99: =M97/$C$98 -> 0 | N99: =N97/$C$98 -> 0 | O99: =O97/$C$98 -> 0 | P99: =P97/$C$98 -> 0 | ... BM99: =BM97/$C$98 -> 0
B101: Detalhamento CSP | C101: CSP $ | D101: CSP % | F101: 1 | G101: 2 | H101: 3 | I101: 4 | J101: 5 | K101: 6 | L101: 7 | M101: 8 | N101: 9 | O101: 10 | P101: 11 | Q101: 12 | R101: 13 | S101: 14 | T101: 15 | U101: 16 | V101: 17 | W101: 18 | X101: 19 | Y101: 20 | Z101: 21 | AA101: 22 | AB101: 23 | AC101: 24 | AD101: 25 | AE101: 26 | AF101: 27 | AG101: 28 | AH101: 29 | AI101: 30 | AJ101: 31 | AK101: 32 | AL101: 33 | AM101: 34 | AN101: 35 | AO101: 36 | AP101: 37 | AQ101: 38 | AR101: 39 | AS101: 40 | AT101: 41 | AU101: 42 | AV101: 43 | AW101: 44 | AX101: 45 | AY101: 46 | AZ101: 47 | BA101: 48 | BB101: 49 | BC101: 50 | BD101: 51 | BE101: 52 | BF101: 53 | BG101: 54 | BH101: 55 | BI101: 56 | BJ101: 57 | BK101: 58 | BL101: 59 | BM101: 60
B102: =B6 -> Limpeza Residencial - 4 horas | C102: 0 | D102: =C102/C52 -> #DIV/0! | I102: =I52*$D102 -> #DIV/0! | J102: =J52*$D102 -> #DIV/0! | K102: =K52*$D102 -> #DIV/0! | L102: =L52*$D102 -> #DIV/0! | M102: =M52*$D102 -> #DIV/0! | N102: =N52*$D102 -> #DIV/0! | O102: =O52*$D102 -> #DIV/0! | P102: =P52*$D102 -> #DIV/0! | ... BM102: =BM52*$D102 -> #DIV/0!
B103: =B7 -> Limpeza Empresarial 4 horas | C103: 0 | D103: =C103/C53 -> #DIV/0! | I103: =I53*$D103 -> #DIV/0! | J103: =J53*$D103 -> #DIV/0! | K103: =K53*$D103 -> #DIV/0! | L103: =L53*$D103 -> #DIV/0! | M103: =M53*$D103 -> #DIV/0! | N103: =N53*$D103 -> #DIV/0! | O103: =O53*$D103 -> #DIV/0! | P103: =P53*$D103 -> #DIV/0! | ... BM103: =BM53*$D103 -> #DIV/0!
B104: =B8 -> Limpeza condominial 4 horas | C104: 0 | D104: =C104/C54 -> #DIV/0! | I104: =I54*$D104 -> #DIV/0! | J104: =J54*$D104 -> #DIV/0! | K104: =K54*$D104 -> #DIV/0! | L104: =L54*$D104 -> #DIV/0! | M104: =M54*$D104 -> #DIV/0! | N104: =N54*$D104 -> #DIV/0! | O104: =O54*$D104 -> #DIV/0! | P104: =P54*$D104 -> #DIV/0! | ... BM104: =BM54*$D104 -> #DIV/0!
B105: =B9 -> Passadoria - 4 horas | C105: 0 | D105: =C105/C55 -> #DIV/0! | I105: =I55*$D105 -> #DIV/0! | J105: =J55*$D105 -> #DIV/0! | K105: =K55*$D105 -> #DIV/0! | L105: =L55*$D105 -> #DIV/0! | M105: =M55*$D105 -> #DIV/0! | N105: =N55*$D105 -> #DIV/0! | O105: =O55*$D105 -> #DIV/0! | P105: =P55*$D105 -> #DIV/0! | ... BM105: =BM55*$D105 -> #DIV/0!
B106: =B10 -> Limpeza Residencial - 6 horas | C106: 0 | D106: =C106/C56 -> #DIV/0! | I106: =I56*$D106 -> #DIV/0! | J106: =J56*$D106 -> #DIV/0! | K106: =K56*$D106 -> #DIV/0! | L106: =L56*$D106 -> #DIV/0! | M106: =M56*$D106 -> #DIV/0! | N106: =N56*$D106 -> #DIV/0! | O106: =O56*$D106 -> #DIV/0! | P106: =P56*$D106 -> #DIV/0! | ... BM106: =BM56*$D106 -> #DIV/0!
B107: =B11 -> Limpeza Residencial - 8 horas | C107: 0 | D107: =C107/C57 -> #DIV/0! | I107: =I57*$D107 -> #DIV/0! | J107: =J57*$D107 -> #DIV/0! | K107: =K57*$D107 -> #DIV/0! | L107: =L57*$D107 -> #DIV/0! | M107: =M57*$D107 -> #DIV/0! | N107: =N57*$D107 -> #DIV/0! | O107: =O57*$D107 -> #DIV/0! | P107: =P57*$D107 -> #DIV/0! | ... BM107: =BM57*$D107 -> #DIV/0!
B108: =B12 -> Limpeza Residencial - 2 horas | C108: 0 | D108: =C108/C58 -> #DIV/0! | I108: =I58*$D108 -> #DIV/0! | J108: =J58*$D108 -> #DIV/0! | K108: =K58*$D108 -> #DIV/0! | L108: =L58*$D108 -> #DIV/0! | M108: =M58*$D108 -> #DIV/0! | N108: =N58*$D108 -> #DIV/0! | O108: =O58*$D108 -> #DIV/0! | P108: =P58*$D108 -> #DIV/0! | ... BM108: =BM58*$D108 -> #DIV/0!
B109: =B13 -> Babá 4 horas | C109: 0 | D109: =C109/C59 -> #DIV/0! | I109: =I59*$D109 -> #DIV/0! | J109: =J59*$D109 -> #DIV/0! | K109: =K59*$D109 -> #DIV/0! | L109: =L59*$D109 -> #DIV/0! | M109: =M59*$D109 -> #DIV/0! | N109: =N59*$D109 -> #DIV/0! | O109: =O59*$D109 -> #DIV/0! | P109: =P59*$D109 -> #DIV/0! | ... BM109: =BM59*$D109 -> #DIV/0!
B110: =B14 -> Limpeza Empresarial 8 horas | C110: 0 | D110: =C110/C60 -> #DIV/0! | I110: =I60*$D110 -> #DIV/0! | J110: =J60*$D110 -> #DIV/0! | K110: =K60*$D110 -> #DIV/0! | L110: =L60*$D110 -> #DIV/0! | M110: =M60*$D110 -> #DIV/0! | N110: =N60*$D110 -> #DIV/0! | O110: =O60*$D110 -> #DIV/0! | P110: =P60*$D110 -> #DIV/0! | ... BM110: =BM60*$D110 -> #DIV/0!
B111: =B15 -> Passadoria - 6 horas | C111: 0 | D111: =C111/C61 -> #DIV/0! | I111: =I61*$D111 -> #DIV/0! | J111: =J61*$D111 -> #DIV/0! | K111: =K61*$D111 -> #DIV/0! | L111: =L61*$D111 -> #DIV/0! | M111: =M61*$D111 -> #DIV/0! | N111: =N61*$D111 -> #DIV/0! | O111: =O61*$D111 -> #DIV/0! | P111: =P61*$D111 -> #DIV/0! | ... BM111: =BM61*$D111 -> #DIV/0!
B112: =B16 -> Limpeza Empresarial 6 horas | C112: 0 | D112: =C112/C62 -> #DIV/0! | I112: =I62*$D112 -> #DIV/0! | J112: =J62*$D112 -> #DIV/0! | K112: =K62*$D112 -> #DIV/0! | L112: =L62*$D112 -> #DIV/0! | M112: =M62*$D112 -> #DIV/0! | N112: =N62*$D112 -> #DIV/0! | O112: =O62*$D112 -> #DIV/0! | P112: =P62*$D112 -> #DIV/0! | ... BM112: =BM62*$D112 -> #DIV/0!
B113: =B17 -> Limpeza condominial 2 horas | C113: 0 | D113: =C113/C63 -> #DIV/0! | I113: =I63*$D113 -> #DIV/0! | J113: =J63*$D113 -> #DIV/0! | K113: =K63*$D113 -> #DIV/0! | L113: =L63*$D113 -> #DIV/0! | M113: =M63*$D113 -> #DIV/0! | N113: =N63*$D113 -> #DIV/0! | O113: =O63*$D113 -> #DIV/0! | P113: =P63*$D113 -> #DIV/0! | ... BM113: =BM63*$D113 -> #DIV/0!
... B146: =B50 -> Garçom 8 horas | C146: 0 | D146: =C146/C96 -> #DIV/0! | I146: =I96*$D146 -> #DIV/0! | J146: =J96*$D146 -> #DIV/0! | K146: =K96*$D146 -> #DIV/0! | L146: =L96*$D146 -> #DIV/0! | M146: =M96*$D146 -> #DIV/0! | N146: =N96*$D146 -> #DIV/0! | O146: =O96*$D146 -> #DIV/0! | P146: =P96*$D146 -> #DIV/0! | ... BM146: =BM96*$D146 -> #DIV/0!
B147: CSP Sub-TOTAL | I147: =SUM(I102:I146) -> #DIV/0! | J147: =SUM(J102:J146) -> #DIV/0! | K147: =SUM(K102:K146) -> #DIV/0! | L147: =SUM(L102:L146) -> #DIV/0! | M147: =SUM(M102:M146) -> #DIV/0! | N147: =SUM(N102:N146) -> #DIV/0! | O147: =SUM(O102:O146) -> #DIV/0! | P147: =SUM(P102:P146) -> #DIV/0! | ... BM147: =SUM(BM102:BM146) -> #DIV/0! | BP147: =SUM(BP102:BP146) -> 0 | BQ147: =SUM(BQ102:BQ146) -> 0 | BR147: =SUM(BR102:BR146) -> 0 | BS147: =SUM(BS102:BS146) -> 0 | BT147: =SUM(BT102:BT146) -> 0
B149: Inadimplência | C149: 0 | I149: =$C$149*I147 -> #DIV/0! | J149: =$C$149*J147 -> #DIV/0! | K149: =$C$149*K147 -> #DIV/0! | L149: =$C$149*L147 -> #DIV/0! | M149: =$C$149*M147 -> #DIV/0! | N149: =$C$149*N147 -> #DIV/0! | O149: =$C$149*O147 -> #DIV/0! | P149: =$C$149*P147 -> #DIV/0! | ... BM149: =$C$149*BM147 -> #DIV/0!
B151: CSP TOTAL | I151: =I147+I149 -> #DIV/0! | J151: =J147+J149 -> #DIV/0! | K151: =K147+K149 -> #DIV/0! | L151: =L147+L149 -> #DIV/0! | M151: =M147+M149 -> #DIV/0! | N151: =N147+N149 -> #DIV/0! | O151: =O147+O149 -> #DIV/0! | P151: =P147+P149 -> #DIV/0! | ... BM151: =BM147+BM149 -> #DIV/0!
B153: CSP TOTAL % | I153: =I151/I97 -> #DIV/0! | J153: =J151/J97 -> #DIV/0! | K153: =K151/K97 -> #DIV/0! | L153: =L151/L97 -> #DIV/0! | M153: =M151/M97 -> #DIV/0! | N153: =N151/N97 -> #DIV/0! | O153: =O151/O97 -> #DIV/0! | P153: =P151/P97 -> #DIV/0! | ... BM153: =BM151/BM97 -> #DIV/0!
B155: OBSERVAÇÃO
B185: Obs.: Esta planilha não configura compromisso ou projeção de resultado, os quais dependerão do esforço e dedicação de cada Franqueado.

Sheet Financiamento
B8: SIMULAÇÃO DE FINANCIAMENTOS
B12: DESCRIÇÃO | H12: Ano 1 | I12: Ano 1 | J12: Ano 1 | K12: Ano 1 | L12: Ano 1 | M12: Ano 1 | N12: Ano 1 | O12: Ano 1 | P12: Ano 1 | Q12: Ano 1 | R12: Ano 1 | S12: Ano 1 | T12: Ano 2 | U12: Ano 2 | V12: Ano 2 | W12: Ano 2 | X12: Ano 2 | Y12: Ano 2 | Z12: Ano 2 | AA12: Ano 2 | AB12: Ano 2 | AC12: Ano 2 | AD12: Ano 2 | AE12: Ano 2 | AF12: Ano 3 | AG12: Ano 3 | AH12: Ano 3 | AI12: Ano 3 | AJ12: Ano 3 | AK12: Ano 3 | AL12: Ano 3 | AM12: Ano 3 | AN12: Ano 3 | AO12: Ano 3 | AP12: Ano 3 | AQ12: Ano 3 | AR12: Ano 4 | AS12: Ano 4 | AT12: Ano 4 | AU12: Ano 4 | AV12: Ano 4 | AW12: Ano 4 | AX12: Ano 4 | AY12: Ano 4 | AZ12: Ano 4 | BA12: Ano 4 | BB12: Ano 4 | BC12: Ano 4 | BD12: Ano 5 | BE12: Ano 5 | BF12: Ano 5 | BG12: Ano 5 | BH12: Ano 5 | BI12: Ano 5 | BJ12: Ano 5 | BK12: Ano 5 | BL12: Ano 5 | BM12: Ano 5 | BN12: Ano 5 | BO12: Ano 5 | BQ12: Ano 1 | BR12: Ano 2 | BS12: Ano 3 | BT12: Ano 4 | BU12: Ano 5 | BW12: Média | CA12: =BQ12 -> Ano 1 | CB12: =BR12 -> Ano 2 | CC12: =BS12 -> Ano 3 | CD12: =BT12 -> Ano 4 | CF12: =BW12 -> Média
H13: mês 1 | I13: mês 2 | J13: mês 3 | K13: mês 4 | L13: mês 5 | M13: mês 6 | N13: mês 7 | O13: mês 8 | P13: mês 9 | Q13: mês 10 | R13: mês 11 | S13: mês 12 | T13: mês 13 | U13: mês 14 | V13: mês 15 | W13: mês 16 | X13: mês 17 | Y13: mês 18 | Z13: mês 19 | AA13: mês 20 | AB13: mês 21 | AC13: mês 22 | AD13: mês 23 | AE13: mês 24 | AF13: mês 25 | AG13: mês 26 | AH13: mês 27 | AI13: mês 28 | AJ13: mês 29 | AK13: mês 30 | AL13: mês 31 | AM13: mês 32 | AN13: mês 33 | AO13: mês 34 | AP13: mês 35 | AQ13: mês 36 | AR13: mês 37 | AS13: mês 38 | AT13: mês 39 | AU13: mês 40 | AV13: mês 41 | AW13: mês 42 | AX13: mês 43 | AY13: mês 44 | AZ13: mês 45 | BA13: mês 46 | BB13: mês 47 | BC13: mês 48 | BD13: mês 49 | BE13: mês 50 | BF13: mês 51 | BG13: mês 52 | BH13: mês 53 | BI13: mês 54 | BJ13: mês 55 | BK13: mês 56 | BL13: mês 57 | BM13: mês 58 | BN13: mês 59 | BO13: mês 60 | BQ13: R$ | BR13: R$ | BS13: R$ | BT13: R$ | CA13: % | CB13: % | CC13: % | CD13: %
B15: Financiamentos | H15: =SUM(H16:H17) -> 0 | I15: =SUM(I16:I17) -> 0 | J15: =SUM(J16:J17) -> 0 | K15: =SUM(K16:K17) -> 0 | L15: =SUM(L16:L17) -> 0 | M15: =SUM(M16:M17) -> 0 | N15: =SUM(N16:N17) -> 0 | O15: =SUM(O16:O17) -> 0 | ... BO15: =SUM(BO16:BO17) -> 0 | BQ15: =SUMIF($H$2:$BC$2,BQ$2,$H15:$BC15) -> 0 | BR15: =SUMIF($H$2:$BC$2,BR$2,$H15:$BC15) -> 0 | BS15: =SUMIF($H$2:$BC$2,BS$2,$H15:$BC15) -> 0 | BT15: =SUMIF($H$2:$BC$2,BT$2,$H15:$BC15) -> 0 | BU15: =SUMIF($H$2:$BO$2,BU$2,$H15:$BO15) -> 0 | BW15: =AVERAGE(BQ15:BT15) -> 0 | CA15: =IF(BQ15=0,0,BQ15/SUM($BQ$187,$BR$187,$BS$187,$BT$187)) -> 0 | CB15: =IF(BR15=0,0,BR15/SUM($BQ$187,$BR$187,$BS$187,$BT$187)) -> 0 | CC15: =IF(BS15=0,0,BS15/SUM($BQ$187,$BR$187,$BS$187,$BT$187)) -> 0 | CD15: =IF(BT15=0,0,BT15/SUM($BQ$187,$BR$187,$BS$187,$BT$187)) -> 0 | CF15: =AVERAGE(CA15:CD15) -> 0
B16: (+) Entradas | H16: 0 | I16: 0 | J16: 0 | K16: 0 | L16: 0 | M16: 0 | N16: 0 | O16: 0 | P16: 0 | Q16: 0 | R16: 0 | S16: 0 | T16: 0 | U16: 0 | V16: 0 | W16: 0 | X16: 0 | Y16: 0 | Z16: 0 | AA16: 0 | AB16: 0 | AC16: 0 | AD16: 0 | AE16: 0 | AF16: 0 | AG16: 0 | AH16: 0 | AI16: 0 | AJ16: 0 | AK16: 0 | AL16: 0 | AM16: 0 | AN16: 0 | AO16: 0 | AP16: 0 | AQ16: 0 | AR16: 0 | AS16: 0 | AT16: 0 | AU16: 0 | AV16: 0 | AW16: 0 | AX16: 0 | AY16: 0 | AZ16: 0 | BA16: 0 | BB16: 0 | BC16: 0 | BD16: 0 | BE16: 0 | BF16: 0 | BG16: 0 | BH16: 0 | BI16: 0 | BJ16: 0 | BK16: 0 | BL16: 0 | BM16: 0 | BN16: 0 | BO16: 0 | BQ16: =SUMIF($H$2:$BO$2,BQ$2,$H16:$BO16) -> 0 | BR16: =SUMIF($H$2:$BO$2,BR$2,$H16:$BO16) -> 0 | BS16: =SUMIF($H$2:$BO$2,BS$2,$H16:$BO16) -> 0 | BT16: =SUMIF($H$2:$BO$2,BT$2,$H16:$BO16) -> 0 | BU16: =SUMIF($H$2:$BO$2,BU$2,$H16:$BO16) -> 0
B17: (-) Pagamentos | H17: 0 | I17: 0 | J17: 0 | K17: 0 | L17: 0 | M17: 0 | N17: 0 | O17: 0 | P17: 0 | Q17: 0 | R17: 0 | S17: 0 | T17: 0 | U17: 0 | V17: 0 | W17: 0 | X17: 0 | Y17: 0 | Z17: 0 | AA17: 0 | AB17: 0 | AC17: 0 | AD17: 0 | AE17: 0 | AF17: 0 | AG17: 0 | AH17: 0 | AI17: 0 | AJ17: 0 | AK17: 0 | AL17: 0 | AM17: 0 | AN17: 0 | AO17: 0 | AP17: 0 | AQ17: 0 | AR17: 0 | AS17: 0 | AT17: 0 | AU17: 0 | AV17: 0 | AW17: 0 | AX17: 0 | AY17: 0 | AZ17: 0 | BA17: 0 | BB17: 0 | BC17: 0 | BD17: 0 | BE17: 0 | BF17: 0 | BG17: 0 | BH17: 0 | BI17: 0 | BJ17: 0 | BK17: 0 | BL17: 0 | BM17: 0 | BN17: 0 | BO17: 0 | BQ17: =SUMIF($H$2:$BO$2,BQ$2,$H17:$BO17) -> 0 | BR17: =SUMIF($H$2:$BO$2,BR$2,$H17:$BO17) -> 0 | BS17: =SUMIF($H$2:$BO$2,BS$2,$H17:$BO17) -> 0 | BT17: =SUMIF($H$2:$BO$2,BT$2,$H17:$BO17) -> 0 | BU17: =SUMIF($H$2:$BO$2,BU$2,$H17:$BO17) -> 0

Sheet DRE
B1: SIMULAÇÃO DO DEMONSTRATIVO DE RESULTADOS (DRE) | CA1: Analise Horizontal
B2: DESCRIÇÃO | H2: Ano 1 | I2: Ano 1 | J2: Ano 1 | K2: Ano 1 | L2: Ano 1 | M2: Ano 1 | N2: Ano 1 | O2: Ano 1 | P2: Ano 1 | Q2: Ano 1 | R2: Ano 1 | S2: Ano 1 | T2: Ano 2 | U2: Ano 2 | V2: Ano 2 | W2: Ano 2 | X2: Ano 2 | Y2: Ano 2 | Z2: Ano 2 | AA2: Ano 2 | AB2: Ano 2 | AC2: Ano 2 | AD2: Ano 2 | AE2: Ano 2 | AF2: Ano 3 | AG2: Ano 3 | AH2: Ano 3 | AI2: Ano 3 | AJ2: Ano 3 | AK2: Ano 3 | AL2: Ano 3 | AM2: Ano 3 | AN2: Ano 3 | AO2: Ano 3 | AP2: Ano 3 | AQ2: Ano 3 | AR2: Ano 4 | AS2: Ano 4 | AT2: Ano 4 | AU2: Ano 4 | AV2: Ano 4 | AW2: Ano 4 | AX2: Ano 4 | AY2: Ano 4 | AZ2: Ano 4 | BA2: Ano 4 | BB2: Ano 4 | BC2: Ano 4 | BD2: Ano 5 | BE2: Ano 5 | BF2: Ano 5 | BG2: Ano 5 | BH2: Ano 5 | BI2: Ano 5 | BJ2: Ano 5 | BK2: Ano 5 | BL2: Ano 5 | BM2: Ano 5 | BN2: Ano 5 | BO2: Ano 5 | BQ2: Ano 1 | BR2: Ano 2 | BS2: Ano 3 | BT2: Ano 4 | BU2: Ano 5 | BW2: Média | CA2: =BQ2 -> Ano 1 | CB2: =BR2 -> Ano 2 | CC2: =BS2 -> Ano 3 | CD2: =BT2 -> Ano 4 | CE2: =BU2 -> Ano 5 | CG2: =BW2 -> Média
H3: mês 1 | I3: mês 2 | J3: mês 3 | K3: mês 4 | L3: mês 5 | M3: mês 6 | N3: mês 7 | O3: mês 8 | P3: mês 9 | Q3: mês 10 | R3: mês 11 | S3: mês 12 | T3: mês 13 | U3: mês 14 | V3: mês 15 | W3: mês 16 | X3: mês 17 | Y3: mês 18 | Z3: mês 19 | AA3: mês 20 | AB3: mês 21 | AC3: mês 22 | AD3: mês 23 | AE3: mês 24 | AF3: mês 25 | AG3: mês 26 | AH3: mês 27 | AI3: mês 28 | AJ3: mês 29 | AK3: mês 30 | AL3: mês 31 | AM3: mês 32 | AN3: mês 33 | AO3: mês 34 | AP3: mês 35 | AQ3: mês 36 | AR3: mês 37 | AS3: mês 38 | AT3: mês 39 | AU3: mês 40 | AV3: mês 41 | AW3: mês 42 | AX3: mês 43 | AY3: mês 44 | AZ3: mês 45 | BA3: mês 46 | BB3: mês 47 | BC3: mês 48 | BD3: mês 49 | BE3: mês 50 | BF3: mês 51 | BG3: mês 52 | BH3: mês 53 | BI3: mês 54 | BJ3: mês 55 | BK3: mês 56 | BL3: mês 57 | BM3: mês 58 | BN3: mês 59 | BO3: mês 60 | BQ3: R$ | BR3: R$ | BS3: R$ | BT3: R$ | BU3: R$ | CA3: % | CB3: % | CC3: % | CD3: % | CE3: %
B5: (+) Receita Bruta | H5: =IF(Premissas!$H$107="Receitas_1",Receitas_1!F97,IF(Premissas!$H$107="Receitas_2",Receitas_2!F98,IF(Premissas!$H$107="Receitas_3",Receitas_3!F97,""))) -> 0 | I5: =IF(Premissas!$H$107="Receitas_1",Receitas_1!G97,IF(Premissas!$H$107="Receitas_2",Receitas_2!G98,IF(Premissas!$H$107="Receitas_3",Receitas_3!G97,""))) -> 7559.28 | J5: =IF(Premissas!$H$107="Receitas_1",Receitas_1!H97,IF(Premissas!$H$107="Receitas_2",Receitas_2!H98,IF(Premissas!$H$107="Receitas_3",Receitas_3!H97,""))) -> 15118.56 | K5: =IF(Premissas!$H$107="Receitas_1",Receitas_1!I97,IF(Premissas!$H$107="Receitas_2",Receitas_2!I98,IF(Premissas!$H$107="Receitas_3",Receitas_3!I97,""))) -> 22677.84 | L5: =IF(Premissas!$H$107="Receitas_1",Receitas_1!J97,IF(Premissas!$H$107="Receitas_2",Receitas_2!J98,IF(Premissas!$H$107="Receitas_3",Receitas_3!J97,""))) -> 30161.527 | M5: =IF(Premissas!$H$107="Receitas_1",Receitas_1!K97,IF(Premissas!$H$107="Receitas_2",Receitas_2!K98,IF(Premissas!$H$107="Receitas_3",Receitas_3!K97,""))) -> 37701.909 | N5: =IF(Premissas!$H$107="Receitas_1",Receitas_1!L97,IF(Premissas!$H$107="Receitas_2",Receitas_2!L98,IF(Premissas!$H$107="Receitas_3",Receitas_3!L97,""))) -> 45242.291 | O5: =IF(Premissas!$H$107="Receitas_1",Receitas_1!M97,IF(Premissas!$H$107="Receitas_2",Receitas_2!M98,IF(Premissas!$H$107="Receitas_3",Receitas_3!M97,""))) -> 52481.058 | ... BO5: =IF(Premissas!$H$107="Receitas_1",Receitas_1!BM97,IF(Premissas!$H$107="Receitas_2",Receitas_2!BM98,IF(Premissas!$H$107="Receitas_3",Receitas_3!BM97,""))) -> 133564.54 | BQ5: =SUMIF($H$2:$BC$2,BQ$2,$H5:$BC5) -> 495966.78 | BR5: =SUMIF($H$2:$BC$2,BR$2,$H5:$BC5) -> 952559.81 | BS5: =SUMIF($H$2:$BC$2,BS$2,$H5:$BC5) -> 1141483.9 | BT5: =SUMIF($H$2:$BO$2,BT$2,$H5:$BO5) -> 1237951.5 | BU5: =SUMIF($H$2:$BO$2,BU$2,$H5:$BO5) -> 1358182.9 | BW5: =AVERAGE(BQ5:BU5) -> 1037229 | CA5: =BQ5/SUM($BQ$5,$BR$5,$BS$5,$BT$5,$BU$5) -> 0.095633037 | CB5: =BR5/SUM($BQ$5,$BR$5,$BS$5,$BT$5,$BU$5) -> 0.18367397 | CC5: =BS5/SUM($BQ$5,$BR$5,$BS$5,$BT$5,$BU$5) -> 0.22010258 | CD5: =BT5/SUM($BQ$5,$BR$5,$BS$5,$BT$5,$BU$5) -> 0.23870361 | CE5: =BU5/SUM($BQ$5,$BR$5,$BS$5,$BT$5,$BU$5) -> 0.26188681 | CG5: =BW5/BW5 -> 1
G6: 0 | I6: =IF('Investimento Inicial'!$E$2>1, INT($G$6/10)*100,INT($G$6/10)*100) -> 0 | J6: =IF('Investimento Inicial'!$E$2>1, INT($G$6/10)*100,INT($G$6/10)*100) -> 0 | K6: =IF('Investimento Inicial'!$E$2>1, INT($G$6/10)*100,INT($G$6/10)*100) -> 0 | L6: =IF('Investimento Inicial'!$E$2>1, INT($G$6/10)*100,INT($G$6/10)*100) -> 0 | M6: =IF('Investimento Inicial'!$E$2>1, INT($G$6/10)*100,INT($G$6/10)*100) -> 0 | N6: =IF('Investimento Inicial'!$E$2>1, INT($G$6/10)*100,INT($G$6/10)*100) -> 0 | O6: =IF('Investimento Inicial'!$E$2>1, INT($G$6/10)*100,INT($G$6/10)*100) -> 0 | P6: =IF('Investimento Inicial'!$E$2>1, INT($G$6/10)*100,INT($G$6/10)*100) -> 0 | ... BO6: =IF('Investimento Inicial'!$E$2>1, INT($G$6/10)*100,INT($G$6/10)*100) -> 0 | BQ6: =SUMIF($H$2:$BO$2,BQ$2,$H6:$BO6) -> 0 | BR6: =SUMIF($H$2:$BO$2,BR$2,$H6:$BO6) -> 0 | BS6: =SUMIF($H$2:$BO$2,BS$2,$H6:$BO6) -> 0 | BT6: =SUMIF($H$2:$BO$2,BT$2,$H6:$BO6) -> 0 | BU6: =SUMIF($H$2:$BO$2,BU$2,$H6:$BO6) -> 0 | BW6: =AVERAGE(BQ6:BU6) -> 0
B9: ='Calculo Impostos - Franqueado'!B14 -> Aliquota Efetiva | H9: ='Calculo Impostos - Franqueado'!C6 -> 0 | I9: ='Calculo Impostos - Franqueado'!D6 -> 0.045 | J9: ='Calculo Impostos - Franqueado'!E6 -> 0.045 | K9: =IF(K5>'Calculo Impostos - Franqueado'!$C$18,'Calculo Impostos - Franqueado'!F6,'Calculo Impostos - Franqueado'!F12) -> 0.045 | L9: =IF(L5>'Calculo Impostos - Franqueado'!$C$18,'Calculo Impostos - Franqueado'!G6,'Calculo Impostos - Franqueado'!G12) -> 0.045 | M9: =IF(M5>'Calculo Impostos - Franqueado'!$C$18,'Calculo Impostos - Franqueado'!H6,'Calculo Impostos - Franqueado'!H12) -> 0.045 | N9: =IF(N5>'Calculo Impostos - Franqueado'!$C$18,'Calculo Impostos - Franqueado'!I6,'Calculo Impostos - Franqueado'!I12) -> 0.045 | O9: =IF(O5>'Calculo Impostos - Franqueado'!$C$18,'Calculo Impostos - Franqueado'!J6,'Calculo Impostos - Franqueado'!J12) -> 0.051600904 | P9: =IF(P5>'Calculo Impostos - Franqueado'!$C$18,'Calculo Impostos - Franqueado'!K6,'Calculo Impostos - Franqueado'!K12) -> 0.060085408 | Q9: =IF(Q5>'Calculo Impostos - Franqueado'!$C$18,'Calculo Impostos - Franqueado'!L6,'Calculo Impostos - Franqueado'!L12) -> 0.066062201 | R9: =IF(R5>'Calculo Impostos - Franqueado'!$C$18,'Calculo Impostos - Franqueado'!M6,'Calculo Impostos - Franqueado'!M12) -> 0.071957893 | ... BO9: =IF(BO5>'Calculo Impostos - Franqueado'!$C$18,'Calculo Impostos - Franqueado'!BJ6,'Calculo Impostos - Franqueado'!BJ12) -> 0.11071087
B10: (-) Impostos | H10: =H5*H9 -> 0 | I10: =I5*I9 -> 340.1676 | J10: =J5*J9 -> 680.3352 | K10: =K5*K9 -> 1020.5028 | L10: =L5*L9 -> 1357.2687 | M10: =M5*M9 -> 1696.5859 | N10: =N5*N9 -> 2035.9031 | O10: =O5*O9 -> 2708.07 | ... BO10: =BO5*BO9 -> 14787.046 | BQ10: =SUMIF($H$2:$BO$2,BQ$2,$H10:$BO10) -> 29652.43 | BR10: =SUMIF($H$2:$BC$2,BR$2,$H10:$BC10) -> 86677.323 | BS10: =SUMIF($H$2:$BC$2,BS$2,$H10:$BC10) -> 117760.87 | BT10: =SUMIF($H$2:$BC$2,BT$2,$H10:$BC10) -> 132038.14 | BU10: =SUMIF($H$2:$BO$2,BU$2,$H10:$BO10) -> 148654.78 | BW10: =AVERAGE(BQ10:BU11) -> 102956.71 | CA10: =BQ10/SUM($BQ$10,$BR$10,$BS$10,$BT$10,$BU$10) -> 0.057601744 | CB10: =BR10/SUM($BQ$10,$BR$10,$BS$10,$BT$10,$BU$10) -> 0.16837625 | CC10: =BS10/SUM($BQ$10,$BR$10,$BS$10,$BT$10,$BU$10) -> 0.22875803 | CD10: =BT10/SUM($BQ$10,$BR$10,$BS$10,$BT$10,$BU$10) -> 0.25649255 | CE10: =BU10/SUM($BQ$10,$BR$10,$BS$10,$BT$10,$BU$10) -> 0.28877143 | CG10: =BW10/BW5 -> 0.099261314
BW11: =AVERAGE(BQ11:BU11) -> #DIV/0!
B13: (=) Receita Líquida | H13: =H5-H10 -> 0 | I13: =I5-I10 -> 7219.1124 | J13: =J5-J10 -> 14438.225 | K13: =K5-K10 -> 21657.337 | L13: =L5-L10 -> 28804.259 | M13: =M5-M10 -> 36005.323 | N13: =N5-N10 -> 43206.388 | O13: =O5-O10 -> 49772.988 | ... BO13: =BO5-BO10 -> 118777.49 | BQ13: =SUMIF($H$2:$BC$2,BQ$2,$H13:$BC13) -> 466314.35 | BR13: =SUMIF($H$2:$BC$2,BR$2,$H13:$BC13) -> 865882.48 | BS13: =SUMIF($H$2:$BC$2,BS$2,$H13:$BC13) -> 1023723 | BT13: =SUMIF($H$2:$BC$2,BT$2,$H13:$BC13) -> 1105913.3 | BU13: =SUMIF($H$2:$BO$2,BU$2,$H13:$BO13) -> 1209528.1 | BW13: =AVERAGE(BQ13:BU13) -> 934272.26 | CA13: =BQ13/SUM($BQ$13,$BR$13,$BS$13,$BT$13,$BU$13) -> 0.099824082 | CB13: =BR13/SUM($BQ$13,$BR$13,$BS$13,$BT$13,$BU$13) -> 0.18535978 | CC13: =BS13/SUM($BQ$13,$BR$13,$BS$13,$BT$13,$BU$13) -> 0.21914875 | CD13: =BT13/SUM($BQ$13,$BR$13,$BS$13,$BT$13,$BU$13) -> 0.23674327 | CE13: =BU13/SUM($BQ$13,$BR$13,$BS$13,$BT$13,$BU$13) -> 0.25892412 | CG13: =BW13/BW5 -> 0.90073869
B15: (-) CSP | H15: =IF(Premissas!$H$107="Receitas_1",Receitas_1!F152,IF(Premissas!$H$107="Receitas_2",Receitas_2!F153,IF(Premissas!$H$107="Receitas_3",Receitas_3!F151,""))) -> 0 | I15: =IF(Premissas!$H$107="Receitas_1",Receitas_1!G152,IF(Premissas!$H$107="Receitas_2",Receitas_2!G153,IF(Premissas!$H$107="Receitas_3",Receitas_3!G151,""))) -> 4072.526 | J15: =IF(Premissas!$H$107="Receitas_1",Receitas_1!H152,IF(Premissas!$H$107="Receitas_2",Receitas_2!H153,IF(Premissas!$H$107="Receitas_3",Receitas_3!H151,""))) -> 8145.052 | K15: =IF(Premissas!$H$107="Receitas_1",Receitas_1!I152,IF(Premissas!$H$107="Receitas_2",Receitas_2!I153,IF(Premissas!$H$107="Receitas_3",Receitas_3!I151,""))) -> 12217.578 | L15: =IF(Premissas!$H$107="Receitas_1",Receitas_1!J152,IF(Premissas!$H$107="Receitas_2",Receitas_2!J153,IF(Premissas!$H$107="Receitas_3",Receitas_3!J151,""))) -> 16249.379 | M15: =IF(Premissas!$H$107="Receitas_1",Receitas_1!K152,IF(Premissas!$H$107="Receitas_2",Receitas_2!K153,IF(Premissas!$H$107="Receitas_3",Receitas_3!K151,""))) -> 20311.723 | N15: =IF(Premissas!$H$107="Receitas_1",Receitas_1!L152,IF(Premissas!$H$107="Receitas_2",Receitas_2!L153,IF(Premissas!$H$107="Receitas_3",Receitas_3!L151,""))) -> 24374.068 | O15: =IF(Premissas!$H$107="Receitas_1",Receitas_1!M152,IF(Premissas!$H$107="Receitas_2",Receitas_2!M153,IF(Premissas!$H$107="Receitas_3",Receitas_3!M151,""))) -> 28273.919 | ... BO15: =IF(Premissas!$H$107="Receitas_1",Receitas_1!BM152,IF(Premissas!$H$107="Receitas_2",Receitas_2!BM153,IF(Premissas!$H$107="Receitas_3",Receitas_3!BM151,""))) -> 71957.257 | BQ15: =SUMIF($H$2:$BO$2,BQ$2,$H15:$BO15) -> 267199.74 | BR15: =SUMIF($H$2:$BO$2,BR$2,$H15:$BO15) -> 513187.05 | BS15: =SUMIF($H$2:$BO$2,BS$2,$H15:$BO15) -> 614968.99 | BT15: =SUMIF($H$2:$BO$2,BT$2,$H15:$BO15) -> 666940.45 | BU15: =SUMIF($H$2:$BO$2,BU$2,$H15:$BO15) -> 731714.56 | BW15: =AVERAGE(BQ15:BU15) -> 558802.15 | CA15: =IF(BQ15=0,0,BQ15/SUM($BQ$15,$BR$15,$BS$15,$BT$15,$BU$15)) -> 0.095633037 | CB15: =IF(BR15=0,0,BR15/SUM($BQ$15,$BR$15,$BS$15,$BT$15,$BU$15)) -> 0.18367397 | CC15: =IF(BS15=0,0,BS15/SUM($BQ$15,$BR$15,$BS$15,$BT$15,$BU$15)) -> 0.22010258 | CD15: =IF(BT15=0,0,BT15/SUM($BQ$15,$BR$15,$BS$15,$BT$15,$BU$15)) -> 0.23870361 | CE15: =IF(BU15=0,0,BU15/SUM($BQ$15,$BR$15,$BS$15,$BT$15,$BU$15)) -> 0.26188681 | CG15: =BW15/BW5 -> 0.53874522
B16: CSP % | H16: =IFERROR(H15/H5,"") | I16: =IFERROR(I15/I5,"") -> 0.53874522 | J16: =IFERROR(J15/J5,"") -> 0.53874522 | K16: =IFERROR(K15/K5,"") -> 0.53874522 | L16: =IFERROR(L15/L5,"") -> 0.53874522 | M16: =IFERROR(M15/M5,"") -> 0.53874522 | N16: =IFERROR(N15/N5,"") -> 0.53874522 | O16: =IFERROR(O15/O5,"") -> 0.53874522 | ... BO16: =IFERROR(BO15/BO5,"") -> 0.53874522 | BQ16: =BQ15/BQ5 -> 0.53874522 | BR16: =BR15/BR5 -> 0.53874522 | BS16: =BS15/BS5 -> 0.53874522 | BT16: =BT15/BT5 -> 0.53874522 | BU16: =BU15/BU5 -> 0.53874522 | BW16: =BW15/BW5 -> 0.53874522
C18: Taxas Médias | D18: % Recebimento
B19: (-) Cartão de Crédito | H19: =H5*$C$19*$D$19 -> 0 | I19: =I5*$C$19*$D$19 -> 0 | J19: =J5*$C$19*$D$19 -> 0 | K19: =K5*$C$19*$D$19 -> 0 | L19: =L5*$C$19*$D$19 -> 0 | M19: =M5*$C$19*$D$19 -> 0 | N19: =N5*$C$19*$D$19 -> 0 | O19: =O5*$C$19*$D$19 -> 0 | ... BO19: =BO5*$C$19*$D$19 -> 0 | BQ19: =SUMIF($H$2:$BO$2,BQ$2,$H19:$BO19) -> 0 | BR19: =SUMIF($H$2:$BO$2,BR$2,$H19:$BO19) -> 0 | BS19: =SUMIF($H$2:$BO$2,BS$2,$H19:$BO19) -> 0 | BT19: =SUMIF($H$2:$BO$2,BT$2,$H19:$BO19) -> 0 | BU19: =SUMIF($H$2:$BO$2,BU$2,$H19:$BO19) -> 0 | BW19: =AVERAGE(BQ19:BU19) -> 0 | CA19: =BQ19/SUM($BQ$19,$BR$19,$BS$19,$BT$19,$BU$19) -> #DIV/0! | CB19: =BR19/SUM($BQ$19,$BR$19,$BS$19,$BT$19,$BU$19) -> #DIV/0! | CC19: =BS19/SUM($BQ$19,$BR$19,$BS$19,$BT$19,$BU$19) -> #DIV/0! | CD19: =BT19/SUM($BQ$19,$BR$19,$BS$19,$BT$19,$BU$19) -> #DIV/0! | CE19: =BU19/SUM($BQ$19,$BR$19,$BS$19,$BT$19,$BU$19) -> #DIV/0! | CG19: =BW19/BW5 -> 0
B20: (-) Cartão de Débito | H20: =H5*$C$20*$D$20 -> 0 | I20: =I5*$C$20*$D$20 -> 0 | J20: =J5*$C$20*$D$20 -> 0 | K20: =K5*$C$20*$D$20 -> 0 | L20: =L5*$C$20*$D$20 -> 0 | M20: =M5*$C$20*$D$20 -> 0 | N20: =N5*$C$20*$D$20 -> 0 | O20: =O5*$C$20*$D$20 -> 0 | ... BO20: =BO5*$C$20*$D$20 -> 0 | BQ20: =SUMIF($H$2:$BO$2,BQ$2,$H20:$BO20) -> 0 | BR20: =SUMIF($H$2:$BO$2,BR$2,$H20:$BO20) -> 0 | BS20: =SUMIF($H$2:$BO$2,BS$2,$H20:$BO20) -> 0 | BT20: =SUMIF($H$2:$BO$2,BT$2,$H20:$BO20) -> 0 | BU20: =SUMIF($H$2:$BO$2,BU$2,$H20:$BO20) -> 0 | BW20: =AVERAGE(BQ20:BU20) -> 0 | CA20: =BQ20/SUM($BQ$20,$BR$20,$BS$20,$BT$20,$BU$20) -> #DIV/0! | CB20: =BR20/SUM($BQ$20,$BR$20,$BS$20,$BT$20,$BU$20) -> #DIV/0! | CC20: =BS20/SUM($BQ$20,$BR$20,$BS$20,$BT$20,$BU$20) -> #DIV/0! | CD20: =BT20/SUM($BQ$20,$BR$20,$BS$20,$BT$20,$BU$20) -> #DIV/0! | CE20: =BU20/SUM($BQ$20,$BR$20,$BS$20,$BT$20,$BU$20) -> #DIV/0! | CG20: =BW20/BW5 -> 0
B21: PIX | C21: 0 | D21: 0.98 | H21: =H5*$C$21*$D$21 -> 0 | I21: =I5*$C$21*$D$21 -> 0 | J21: =J5*$C$21*$D$21 -> 0 | K21: =K5*$C$21*$D$21 -> 0 | L21: =L5*$C$21*$D$21 -> 0 | M21: =M5*$C$21*$D$21 -> 0 | N21: =N5*$C$21*$D$21 -> 0 | O21: =O5*$C$21*$D$21 -> 0 | ... BO21: =BO5*$C$21*$D$21 -> 0 | BQ21: =SUMIF($H$2:$BO$2,BQ$2,$H21:$BO21) -> 0 | BR21: =SUMIF($H$2:$BO$2,BR$2,$H21:$BO21) -> 0 | BS21: =SUMIF($H$2:$BO$2,BS$2,$H21:$BO21) -> 0 | BT21: =SUMIF($H$2:$BO$2,BT$2,$H21:$BO21) -> 0 | BU21: =SUMIF($H$2:$BO$2,BU$2,$H21:$BO21) -> 0 | BW21: =AVERAGE(BQ21:BU21) -> 0 | CA21: =IF(BQ21=0,0,BQ21/SUM($BQ$21,$BR$21,$BS$21,$BT$21,$BU$21)) -> 0 | CB21: =IF(BR21=0,0,BR21/SUM($BQ$21,$BR$21,$BS$21,$BT$21,$BU$21)) -> 0 | CC21: =IF(BS21=0,0,BS21/SUM($BQ$21,$BR$21,$BS$21,$BT$21,$BU$21)) -> 0 | CD21: =IF(BT21=0,0,BT21/SUM($BQ$21,$BR$21,$BS$21,$BT$21,$BU$21)) -> 0 | CE21: =IF(BU21=0,0,BU21/SUM($BQ$21,$BR$21,$BS$21,$BT$21,$BU$21)) -> 0 | CG21: =BW21/BW5 -> 0
B22: Boleto | C22: 0 | D22: 0.02 | H22: =H5*$C$22*$D$22 -> 0 | I22: =I5*$C$22*$D$22 -> 0 | J22: =J5*$C$22*$D$22 -> 0 | K22: =K5*$C$22*$D$22 -> 0 | L22: =L5*$C$22*$D$22 -> 0 | M22: =M5*$C$22*$D$22 -> 0 | N22: =N5*$C$22*$D$22 -> 0 | O22: =O5*$C$22*$D$22 -> 0 | ... BO22: =BO5*$C$22*$D$22 -> 0 | BQ22: =SUMIF($H$2:$BO$2,BQ$2,$H22:$BO22) -> 0 | BR22: =SUMIF($H$2:$BO$2,BR$2,$H22:$BO22) -> 0 | BS22: =SUMIF($H$2:$BO$2,BS$2,$H22:$BO22) -> 0 | BT22: =SUMIF($H$2:$BO$2,BT$2,$H22:$BO22) -> 0 | BU22: =SUMIF($H$2:$BO$2,BU$2,$H22:$BO22) -> 0 | BW22: =AVERAGE(BQ22:BU22) -> 0 | CA22: =IF(BQ22=0,0,BQ22/SUM($BQ$22,$BR$22,$BS$22,$BT$22,$BU$22)) -> 0 | CB22: =IF(BR22=0,0,BR22/SUM($BQ$22,$BR$22,$BS$22,$BT$22,$BU$22)) -> 0 | CC22: =IF(BS22=0,0,BS22/SUM($BQ$22,$BR$22,$BS$22,$BT$22,$BU$22)) -> 0 | CD22: =IF(BT22=0,0,BT22/SUM($BQ$22,$BR$22,$BS$22,$BT$22,$BU$22)) -> 0 | CE22: =IF(BU22=0,0,BU22/SUM($BQ$22,$BR$22,$BS$22,$BT$22,$BU$22)) -> 0 | CG22: =BW22/BW5 -> 0
B23: (-) Taxas de Cartão | H23: =SUM(H19:H20) -> 0 | I23: =SUM(I19:I20) -> 0 | J23: =SUM(J19:J22) -> 0 | K23: =SUM(K19:K22) -> 0 | L23: =SUM(L19:L22) -> 0 | M23: =SUM(M19:M22) -> 0 | N23: =SUM(N19:N22) -> 0 | O23: =SUM(O19:O22) -> 0 | P23: =SUM(P19:P22) -> 0 | Q23: =SUM(Q19:Q22) -> 0 | ... BO23: =SUM(BO19:BO22) -> 0 | BQ23: =SUMIF($H$2:$BO$2,BQ$2,$H23:$BO23) -> 0 | BR23: =SUMIF($H$2:$BO$2,BR$2,$H23:$BO23) -> 0 | BS23: =SUMIF($H$2:$BO$2,BS$2,$H23:$BO23) -> 0 | BT23: =SUMIF($H$2:$BO$2,BT$2,$H23:$BO23) -> 0 | BU23: =SUMIF($H$2:$BO$2,BU$2,$H23:$BO23) -> 0 | BW23: =AVERAGE(BQ23:BU23) -> 0 | CA23: =IF(BQ23=0,0,BQ23/SUM($BQ$23,$BR$23,$BS$23,$BT$23,$BU$23)) -> 0 | CB23: =IF(BR23=0,0,BR23/SUM($BQ$23,$BR$23,$BS$23,$BT$23,$BU$23)) -> 0 | CC23: =IF(BS23=0,0,BS23/SUM($BQ$23,$BR$23,$BS$23,$BT$23,$BU$23)) -> 0 | CD23: =IF(BT23=0,0,BT23/SUM($BQ$23,$BR$23,$BS$23,$BT$23,$BU$23)) -> 0 | CE23: =IF(BU23=0,0,BU23/SUM($BQ$23,$BR$23,$BS$23,$BT$23,$BU$23)) -> 0 | CG23: =BW23/BW5 -> 0
B25: (-) Despesas Variávies | C25: (%) | D25: % Vendas Diretas | G25: Tx Sobre
B26: (-) Comissão | C26: 0 | D26: 0 | G26: Ft Bruto | H26: =IF($G$26="Ft Bruto",(H5*$D$26)*$C$26,IF($G$26="Fluxo Cx",('Fluxo de Caixa'!I5*$D$26),"")) -> 0 | I26: =IF($G$26="Ft Bruto",(I5*$D$26)*$C$26,IF($G$26="Fluxo Cx",('Fluxo de Caixa'!J5*$D$26),"")) -> 0 | J26: =IF($G$26="Ft Bruto",(J5*$D$26)*$C$26,IF($G$26="Fluxo Cx",('Fluxo de Caixa'!K5*$D$26)*$C$26,"")) -> 0 | K26: =IF($G$26="Ft Bruto",(K5*$D$26)*$C$26,IF($G$26="Fluxo Cx",('Fluxo de Caixa'!L5*$D$26)*$C$26,"")) -> 0 | L26: =IF($G$26="Ft Bruto",(L5*$D$26)*$C$26,IF($G$26="Fluxo Cx",('Fluxo de Caixa'!M5*$D$26)*$C$26,"")) -> 0 | M26: =IF($G$26="Ft Bruto",(M5*$D$26)*$C$26,IF($G$26="Fluxo Cx",('Fluxo de Caixa'!N5*$D$26)*$C$26,"")) -> 0 | N26: =IF($G$26="Ft Bruto",(N5*$D$26)*$C$26,IF($G$26="Fluxo Cx",('Fluxo de Caixa'!O5*$D$26)*$C$26,"")) -> 0 | O26: =IF($G$26="Ft Bruto",(O5*$D$26)*$C$26,IF($G$26="Fluxo Cx",('Fluxo de Caixa'!P5*$D$26)*$C$26,"")) -> 0 | P26: =IF($G$26="Ft Bruto",(P5*$D$26)*$C$26,IF($G$26="Fluxo Cx",('Fluxo de Caixa'!Q5*$D$26)*$C$26,"")) -> 0 | Q26: =IF($G$26="Ft Bruto",(Q5*$D$26)*$C$26,IF($G$26="Fluxo Cx",('Fluxo de Caixa'!R5*$D$26)*$C$26,"")) -> 0 | ... BO26: =IF($G$26="Ft Bruto",(BO5*$D$26)*$C$26,IF($G$26="Fluxo Cx",('Fluxo de Caixa'!BP5*$D$26)*$C$26,"")) -> 0 | BQ26: =SUMIF($H$2:$BO$2,BQ$2,$H26:$BO26) -> 0 | BR26: =SUMIF($H$2:$BO$2,BR$2,$H26:$BO26) -> 0 | BS26: =SUMIF($H$2:$BO$2,BS$2,$H26:$BO26) -> 0 | BT26: =SUMIF($H$2:$BO$2,BT$2,$H26:$BO26) -> 0 | BU26: =SUMIF($H$2:$BO$2,BU$2,$H26:$BO26) -> 0 | BW26: =AVERAGE(BQ26:BU26) -> 0
B27: (-) Encargos Comissão | H27: =IF(H26<1,"",H26*(H32/H31)) | I27: =IF(I26<1,"",I26*(I32/I31)) | J27: =IF(J26<1,"",J26*(J32/J31)) | K27: =IF(K26<1,"",K26*(K32/K31)) | L27: =IF(L26<1,"",L26*(L32/L31)) | M27: =IF(M26<1,"",M26*(M32/M31)) | N27: =IF(N26<1,"",N26*(N32/N31)) | O27: =IF(O26<1,"",O26*(O32/O31)) | ... BO27: =IF(BO26<1,"",BO26*(BO32/BO31)) | BQ27: =SUMIF($H$2:$BO$2,BQ$2,$H27:$BO27) -> 0 | BR27: =SUMIF($H$2:$BO$2,BR$2,$H27:$BO27) -> 0 | BS27: =SUMIF($H$2:$BO$2,BS$2,$H27:$BO27) -> 0 | BT27: =SUMIF($H$2:$BO$2,BT$2,$H27:$BO27) -> 0 | BU27: =SUMIF($H$2:$BO$2,BU$2,$H27:$BO27) -> 0 | BV27: =AVERAGEIF($H$2:$BO$2,BV$2,$H27:$BO27) -> #DIV/0! | BW27: =AVERAGE(BQ27:BU27) -> 0
B28: (=) Margem de Contribuição | H28: =IFERROR(H13-H15-H23-H26-H27,"") | I28: =IFERROR(IF($C$26=0%,I13-I15-I23,I13-I15-I23-I26-I27),"") -> 3146.5864 | J28: =IFERROR(IF($C$26=0%,J13-J15-J23,J13-J15-J23-J26-J27),"") -> 6293.1728 | K28: =IFERROR(IF($C$26=0%,K13-K15-K23,K13-K15-K23-K26-K27),"") -> 9439.7593 | L28: =IFERROR(IF($C$26=0%,L13-L15-L23,L13-L15-L23-L26-L27),"") -> 12554.88 | M28: =IFERROR(IF($C$26=0%,M13-M15-M23,M13-M15-M23-M26-M27),"") -> 15693.6 | N28: =IFERROR(IF($C$26=0%,N13-N15-N23,N13-N15-N23-N26-N27),"") -> 18832.32 | O28: =IFERROR(IF($C$26=0%,O13-O15-O23,O13-O15-O23-O26-O27),"") -> 21499.068 | P28: =IFERROR(IF($C$26=0%,P13-P15-P23,P13-P15-P23-P26-P27),"") -> 24001.324 | ... BO28: =IFERROR(IF($C$26=0%,BO13-BO15-BO23,BO13-BO15-BO23-BO26-BO27),"") -> 46820.235 | BQ28: =SUMIF($H$2:$BO$2,BQ$2,$H28:$BO28) -> 199114.62 | BR28: =SUMIF($H$2:$BO$2,BR$2,$H28:$BO28) -> 352695.44 | BS28: =SUMIF($H$2:$BO$2,BS$2,$H28:$BO28) -> 408754.02 | BT28: =SUMIF($H$2:$BO$2,BT$2,$H28:$BO28) -> 438972.89 | BU28: =SUMIF($H$2:$BO$2,BU$2,$H28:$BO28) -> 477813.58 | BW28: =AVERAGE(BQ28:BU28) -> 375470.11 | CA28: =BQ28/SUM($BQ$28,$BR$28,$BS$28,$BT$28,$BU$28) -> 0.1060615 | CB28: =BR28/SUM($BQ$28,$BR$28,$BS$28,$BT$28,$BU$28) -> 0.18786872 | CC28: =BS28/SUM($BQ$28,$BR$28,$BS$28,$BT$28,$BU$28) -> 0.21772919 | CD28: =BT28/SUM($BQ$28,$BR$28,$BS$28,$BT$28,$BU$28) -> 0.23382574 | CE28: =BU28/SUM($BQ$28,$BR$28,$BS$28,$BT$28,$BU$28) -> 0.25451484 | CG28: =BW28/BW5 -> 0.36199346
B29: Margem de Contribuição % | H29: =IFERROR(H28/H5,"") | I29: =IFERROR(I28/I5,"") -> 0.41625478 | J29: =IFERROR(J28/J5,"") -> 0.41625478 | K29: =IFERROR(K28/K5,"") -> 0.41625478 | L29: =IFERROR(L28/L5,"") -> 0.41625478 | M29: =IFERROR(M28/M5,"") -> 0.41625478 | N29: =IFERROR(N28/N5,"") -> 0.41625478 | O29: =IFERROR(O28/O5,"") -> 0.40965387 | ... BO29: =IFERROR(BO28/BO5,"") -> 0.35054391 | BQ29: =BQ28/BQ5 -> 0.40146765 | BR29: =BR28/BR5 -> 0.37026068 | BS29: =BS28/BS5 -> 0.35809005 | BT29: =BT28/BT5 -> 0.3545962 | BU29: =BU28/BU5 -> 0.35180355 | BW29: =BW28/BW5 -> 0.36199346
BQ30: =BQ28/BQ5 -> 0.40146765 | BR30: =BR28/BR5 -> 0.37026068 | BS30: =BS28/BS5 -> 0.35809005 | BT30: =BT28/BT5 -> 0.3545962 | BU30: =BU28/BU5 -> 0.35180355
B31: Salários | H31: 0 | I31: =IF(Premissas!$H$107="Receitas_1",VLOOKUP($B31,'Recursos Humanos'!$B$88:$H$92,2,0),0) -> 4000 | J31: =IF(Premissas!$H$107="Receitas_3",0,VLOOKUP($B31,'Recursos Humanos'!$B$88:$H$92,2,0)) -> 4000 | K31: =VLOOKUP($B31,'Recursos Humanos'!$B$88:$H$92,2,0) -> 4000 | L31: =VLOOKUP($B31,'Recursos Humanos'!$B$88:$H$92,2,0) -> 4000 | M31: =VLOOKUP($B31,'Recursos Humanos'!$B$88:$H$92,2,0) -> 4000 | N31: =VLOOKUP($B31,'Recursos Humanos'!$B$88:$H$92,2,0) -> 4000 | O31: =VLOOKUP($B31,'Recursos Humanos'!$B$88:$H$92,2,0) -> 4000 | P31: =VLOOKUP($B31,'Recursos Humanos'!$B$88:$H$92,2,0) -> 4000 | Q31: =VLOOKUP($B31,'Recursos Humanos'!$B$88:$H$92,2,0) -> 4000 | R31: =VLOOKUP($B31,'Recursos Humanos'!$B$88:$H$92,2,0) -> 4000 | S31: =VLOOKUP($B31,'Recursos Humanos'!$B$88:$H$92,2,0) -> 4000 | T31: =VLOOKUP($B31,'Recursos Humanos'!$B$88:$H$92,3,0) -> 4000 | U31: =VLOOKUP($B31,'Recursos Humanos'!$B$88:$H$92,3,0) -> 4000 | V31: =VLOOKUP($B31,'Recursos Humanos'!$B$88:$H$92,3,0) -> 4000 | W31: =VLOOKUP($B31,'Recursos Humanos'!$B$88:$H$92,3,0) -> 4000 | X31: =VLOOKUP($B31,'Recursos Humanos'!$B$88:$H$92,3,0) -> 4000 | Y31: =VLOOKUP($B31,'Recursos Humanos'!$B$88:$H$92,3,0) -> 4000 | Z31: =VLOOKUP($B31,'Recursos Humanos'!$B$88:$H$92,3,0) -> 4000 | AA31: =VLOOKUP($B31,'Recursos Humanos'!$B$88:$H$92,3,0) -> 4000 | ... AE31: =VLOOKUP($B31,'Recursos Humanos'!$B$88:$H$92,3,0) -> 4000 | AF31: =VLOOKUP($B31,'Recursos Humanos'!$B$88:$H$92,4,0) -> 4000 | AG31: =VLOOKUP($B31,'Recursos Humanos'!$B$88:$H$92,4,0) -> 4000 | AH31: =VLOOKUP($B31,'Recursos Humanos'!$B$88:$H$92,4,0) -> 4000 | AI31: =VLOOKUP($B31,'Recursos Humanos'!$B$88:$H$92,4,0) -> 4000 | AJ31: =VLOOKUP($B31,'Recursos Humanos'!$B$88:$H$92,4,0) -> 4000 | AK31: =VLOOKUP($B31,'Recursos Humanos'!$B$88:$H$92,4,0) -> 4000 | AL31: =VLOOKUP($B31,'Recursos Humanos'!$B$88:$H$92,4,0) -> 4000 | AM31: =VLOOKUP($B31,'Recursos Humanos'!$B$88:$H$92,4,0) -> 4000 | ... AQ31: =VLOOKUP($B31,'Recursos Humanos'!$B$88:$H$92,4,0) -> 4000 | AR31: =VLOOKUP($B31,'Recursos Humanos'!$B$88:$H$92,5,0) -> 4000 | AS31: =VLOOKUP($B31,'Recursos Humanos'!$B$88:$H$92,5,0) -> 4000 | AT31: =VLOOKUP($B31,'Recursos Humanos'!$B$88:$H$92,5,0) -> 4000 | AU31: =VLOOKUP($B31,'Recursos Humanos'!$B$88:$H$92,5,0) -> 4000 | AV31: =VLOOKUP($B31,'Recursos Humanos'!$B$88:$H$92,5,0) -> 4000 | AW31: =VLOOKUP($B31,'Recursos Humanos'!$B$88:$H$92,5,0) -> 4000 | AX31: =VLOOKUP($B31,'Recursos Humanos'!$B$88:$H$92,5,0) -> 4000 | AY31: =VLOOKUP($B31,'Recursos Humanos'!$B$88:$H$92,5,0) -> 4000 | ... BC31: =VLOOKUP($B31,'Recursos Humanos'!$B$88:$H$92,5,0) -> 4000 | BD31: =VLOOKUP($B31,'Recursos Humanos'!$B$88:$H$92,6,0) -> 4000 | BE31: =VLOOKUP($B31,'Recursos Humanos'!$B$88:$H$92,6,0) -> 4000 | BF31: =VLOOKUP($B31,'Recursos Humanos'!$B$88:$H$92,6,0) -> 4000 | BG31: =VLOOKUP($B31,'Recursos Humanos'!$B$88:$H$92,6,0) -> 4000 | BH31: =VLOOKUP($B31,'Recursos Humanos'!$B$88:$H$92,6,0) -> 4000 | BI31: =VLOOKUP($B31,'Recursos Humanos'!$B$88:$H$92,6,0) -> 4000 | BJ31: =VLOOKUP($B31,'Recursos Humanos'!$B$88:$H$92,6,0) -> 4000 | BK31: =VLOOKUP($B31,'Recursos Humanos'!$B$88:$H$92,6,0) -> 4000 | ... BO31: =VLOOKUP($B31,'Recursos Humanos'!$B$88:$H$92,6,0) -> 4000 | BQ31: =SUMIF($H$2:$BC$2,BQ$2,$H31:$BC31) -> 44000 | BR31: =SUMIF($H$2:$BC$2,BR$2,$H31:$BC31) -> 48000 | BS31: =SUMIF($H$2:$BC$2,BS$2,$H31:$BC31) -> 48000 | BT31: =SUMIF($H$2:$BO$2,BT$2,$H31:$BO31) -> 48000 | BU31: =SUMIF($H$2:$BO$2,BU$2,$H31:$BO31) -> 48000 | BW31: =AVERAGE(BQ31:BT31) -> 47000 | CA31: =BQ31/SUM($BQ$34,$BR$34,$BS$34,$BT$34) -> 0.16874636 | CB31: =BR31/SUM($BQ$34,$BR$34,$BS$34,$BT$34) -> 0.18408694 | CC31: =BS31/SUM($BQ$34,$BR$34,$BS$34,$BT$34) -> 0.18408694 | CD31: =BT31/SUM($BQ$34,$BR$34,$BS$34,$BT$34) -> 0.18408694 | CE31: =BU31/SUM($BQ$34,$BR$34,$BS$34,$BT$34) -> 0.18408694 | CG31: =BW31/BW5 -> 0.045313042
B32: Encargos | H32: 0 | I32: =IF(Premissas!$H$107="Receitas_1",VLOOKUP($B32,'Recursos Humanos'!$B$88:$H$92,2,0),0) -> 1545.5733 | J32: =IF(Premissas!$H$107="Receitas_3",0,VLOOKUP($B32,'Recursos Humanos'!$B$88:$H$92,2,0)) -> 1545.5733 | K32: =VLOOKUP($B32,'Recursos Humanos'!$B$88:$H$92,2,0) -> 1545.5733 | L32: =VLOOKUP($B32,'Recursos Humanos'!$B$88:$H$92,2,0) -> 1545.5733 | M32: =VLOOKUP($B32,'Recursos Humanos'!$B$88:$H$92,2,0) -> 1545.5733 | N32: =VLOOKUP($B32,'Recursos Humanos'!$B$88:$H$92,2,0) -> 1545.5733 | O32: =VLOOKUP($B32,'Recursos Humanos'!$B$88:$H$92,2,0) -> 1545.5733 | P32: =VLOOKUP($B32,'Recursos Humanos'!$B$88:$H$92,2,0) -> 1545.5733 | Q32: =VLOOKUP($B32,'Recursos Humanos'!$B$88:$H$92,2,0) -> 1545.5733 | R32: =VLOOKUP($B32,'Recursos Humanos'!$B$88:$H$92,2,0) -> 1545.5733 | S32: =VLOOKUP($B32,'Recursos Humanos'!$B$88:$H$92,2,0) -> 1545.5733 | T32: =VLOOKUP($B32,'Recursos Humanos'!$B$88:$H$92,3,0) -> 1545.5733 | U32: =VLOOKUP($B32,'Recursos Humanos'!$B$88:$H$92,3,0) -> 1545.5733 | V32: =VLOOKUP($B32,'Recursos Humanos'!$B$88:$H$92,3,0) -> 1545.5733 | W32: =VLOOKUP($B32,'Recursos Humanos'!$B$88:$H$92,3,0) -> 1545.5733 | X32: =VLOOKUP($B32,'Recursos Humanos'!$B$88:$H$92,3,0) -> 1545.5733 | Y32: =VLOOKUP($B32,'Recursos Humanos'!$B$88:$H$92,3,0) -> 1545.5733 | Z32: =VLOOKUP($B32,'Recursos Humanos'!$B$88:$H$92,3,0) -> 1545.5733 | AA32: =VLOOKUP($B32,'Recursos Humanos'!$B$88:$H$92,3,0) -> 1545.5733 | ... AE32: =VLOOKUP($B32,'Recursos Humanos'!$B$88:$H$92,3,0) -> 1545.5733 | AF32: =VLOOKUP($B32,'Recursos Humanos'!$B$88:$H$92,4,0) -> 1545.5733 | AG32: =VLOOKUP($B32,'Recursos Humanos'!$B$88:$H$92,4,0) -> 1545.5733 | AH32: =VLOOKUP($B32,'Recursos Humanos'!$B$88:$H$92,4,0) -> 1545.5733 | AI32: =VLOOKUP($B32,'Recursos Humanos'!$B$88:$H$92,4,0) -> 1545.5733 | AJ32: =VLOOKUP($B32,'Recursos Humanos'!$B$88:$H$92,4,0) -> 1545.5733 | AK32: =VLOOKUP($B32,'Recursos Humanos'!$B$88:$H$92,4,0) -> 1545.5733 | AL32: =VLOOKUP($B32,'Recursos Humanos'!$B$88:$H$92,4,0) -> 1545.5733 | AM32: =VLOOKUP($B32,'Recursos Humanos'!$B$88:$H$92,4,0) -> 1545.5733 | ... AQ32: =VLOOKUP($B32,'Recursos Humanos'!$B$88:$H$92,4,0) -> 1545.5733 | AR32: =VLOOKUP($B32,'Recursos Humanos'!$B$88:$H$92,5,0) -> 1545.5733 | AS32: =VLOOKUP($B32,'Recursos Humanos'!$B$88:$H$92,5,0) -> 1545.5733 | AT32: =VLOOKUP($B32,'Recursos Humanos'!$B$88:$H$92,5,0) -> 1545.5733 | AU32: =VLOOKUP($B32,'Recursos Humanos'!$B$88:$H$92,5,0) -> 1545.5733 | AV32: =VLOOKUP($B32,'Recursos Humanos'!$B$88:$H$92,5,0) -> 1545.5733 | AW32: =VLOOKUP($B32,'Recursos Humanos'!$B$88:$H$92,5,0) -> 1545.5733 | AX32: =VLOOKUP($B32,'Recursos Humanos'!$B$88:$H$92,5,0) -> 1545.5733 | AY32: =VLOOKUP($B32,'Recursos Humanos'!$B$88:$H$92,5,0) -> 1545.5733 | ... BC32: =VLOOKUP($B32,'Recursos Humanos'!$B$88:$H$92,5,0) -> 1545.5733 | BD32: =VLOOKUP($B32,'Recursos Humanos'!$B$88:$H$92,6,0) -> 1545.5733 | BE32: =VLOOKUP($B32,'Recursos Humanos'!$B$88:$H$92,6,0) -> 1545.5733 | BF32: =VLOOKUP($B32,'Recursos Humanos'!$B$88:$H$92,6,0) -> 1545.5733 | BG32: =VLOOKUP($B32,'Recursos Humanos'!$B$88:$H$92,6,0) -> 1545.5733 | BH32: =VLOOKUP($B32,'Recursos Humanos'!$B$88:$H$92,6,0) -> 1545.5733 | BI32: =VLOOKUP($B32,'Recursos Humanos'!$B$88:$H$92,6,0) -> 1545.5733 | BJ32: =VLOOKUP($B32,'Recursos Humanos'!$B$88:$H$92,6,0) -> 1545.5733 | BK32: =VLOOKUP($B32,'Recursos Humanos'!$B$88:$H$92,6,0) -> 1545.5733 | ... BO32: =VLOOKUP($B32,'Recursos Humanos'!$B$88:$H$92,6,0) -> 1545.5733 | BQ32: =SUMIF($H$2:$BC$2,BQ$2,$H32:$BC32) -> 17001.307 | BR32: =SUMIF($H$2:$BC$2,BR$2,$H32:$BC32) -> 18546.88 | BS32: =SUMIF($H$2:$BC$2,BS$2,$H32:$BC32) -> 18546.88 | BT32: =SUMIF($H$2:$BO$2,BT$2,$H32:$BO32) -> 18546.88 | BU32: =SUMIF($H$2:$BO$2,BU$2,$H32:$BO32) -> 18546.88 | BW32: =AVERAGE(BQ32:BT32) -> 18160.487 | CA32: =BQ32/SUM($BQ$34,$BR$34,$BS$34,$BT$34) -> 0.065202469 | CB32: =BR32/SUM($BQ$34,$BR$34,$BS$34,$BT$34) -> 0.071129966 | CC32: =BS32/SUM($BQ$34,$BR$34,$BS$34,$BT$34) -> 0.071129966 | CD32: =BT32/SUM($BQ$34,$BR$34,$BS$34,$BT$34) -> 0.071129966 | CE32: =BU32/SUM($BQ$34,$BR$34,$BS$34,$BT$34) -> 0.071129966 | CG32: =BW32/BW5 -> 0.017508657
B33: Benefícios | H33: 0 | I33: =IF(Premissas!$H$107="Receitas_1",VLOOKUP($B33,'Recursos Humanos'!$B$88:$H$92,2,0),0) -> 2.2216667 | J33: =IF(Premissas!$H$107="Receitas_3",0,VLOOKUP($B33,'Recursos Humanos'!$B$88:$H$92,2,0)) -> 2.2216667 | K33: =VLOOKUP($B33,'Recursos Humanos'!$B$88:$H$92,2,0) -> 2.2216667 | L33: =VLOOKUP($B33,'Recursos Humanos'!$B$88:$H$92,2,0) -> 2.2216667 | M33: =VLOOKUP($B33,'Recursos Humanos'!$B$88:$H$92,2,0) -> 2.2216667 | N33: =VLOOKUP($B33,'Recursos Humanos'!$B$88:$H$92,2,0) -> 2.2216667 | O33: =VLOOKUP($B33,'Recursos Humanos'!$B$88:$H$92,2,0) -> 2.2216667 | P33: =VLOOKUP($B33,'Recursos Humanos'!$B$88:$H$92,2,0) -> 2.2216667 | Q33: =VLOOKUP($B33,'Recursos Humanos'!$B$88:$H$92,2,0) -> 2.2216667 | R33: =VLOOKUP($B33,'Recursos Humanos'!$B$88:$H$92,2,0) -> 2.2216667 | S33: =VLOOKUP($B33,'Recursos Humanos'!$B$88:$H$92,2,0) -> 2.2216667 | T33: =VLOOKUP($B33,'Recursos Humanos'!$B$88:$H$92,3,0) -> 2.2216667 | U33: =VLOOKUP($B33,'Recursos Humanos'!$B$88:$H$92,3,0) -> 2.2216667 | V33: =VLOOKUP($B33,'Recursos Humanos'!$B$88:$H$92,3,0) -> 2.2216667 | W33: =VLOOKUP($B33,'Recursos Humanos'!$B$88:$H$92,3,0) -> 2.2216667 | X33: =VLOOKUP($B33,'Recursos Humanos'!$B$88:$H$92,3,0) -> 2.2216667 | Y33: =VLOOKUP($B33,'Recursos Humanos'!$B$88:$H$92,3,0) -> 2.2216667 | Z33: =VLOOKUP($B33,'Recursos Humanos'!$B$88:$H$92,3,0) -> 2.2216667 | AA33: =VLOOKUP($B33,'Recursos Humanos'!$B$88:$H$92,3,0) -> 2.2216667 | ... AE33: =VLOOKUP($B33,'Recursos Humanos'!$B$88:$H$92,3,0) -> 2.2216667 | AF33: =VLOOKUP($B33,'Recursos Humanos'!$B$88:$H$92,4,0) -> 2.2216667 | AG33: =VLOOKUP($B33,'Recursos Humanos'!$B$88:$H$92,4,0) -> 2.2216667 | AH33: =VLOOKUP($B33,'Recursos Humanos'!$B$88:$H$92,4,0) -> 2.2216667 | AI33: =VLOOKUP($B33,'Recursos Humanos'!$B$88:$H$92,4,0) -> 2.2216667 | AJ33: =VLOOKUP($B33,'Recursos Humanos'!$B$88:$H$92,4,0) -> 2.2216667 | AK33: =VLOOKUP($B33,'Recursos Humanos'!$B$88:$H$92,4,0) -> 2.2216667 | AL33: =VLOOKUP($B33,'Recursos Humanos'!$B$88:$H$92,4,0) -> 2.2216667 | AM33: =VLOOKUP($B33,'Recursos Humanos'!$B$88:$H$92,4,0) -> 2.2216667 | ... AQ33: =VLOOKUP($B33,'Recursos Humanos'!$B$88:$H$92,4,0) -> 2.2216667 | AR33: =VLOOKUP($B33,'Recursos Humanos'!$B$88:$H$92,5,0) -> 2.2216667 | AS33: =VLOOKUP($B33,'Recursos Humanos'!$B$88:$H$92,5,0) -> 2.2216667 | AT33: =VLOOKUP($B33,'Recursos Humanos'!$B$88:$H$92,5,0) -> 2.2216667 | AU33: =VLOOKUP($B33,'Recursos Humanos'!$B$88:$H$92,5,0) -> 2.2216667 | AV33: =VLOOKUP($B33,'Recursos Humanos'!$B$88:$H$92,5,0) -> 2.2216667 | AW33: =VLOOKUP($B33,'Recursos Humanos'!$B$88:$H$92,5,0) -> 2.2216667 | AX33: =VLOOKUP($B33,'Recursos Humanos'!$B$88:$H$92,5,0) -> 2.2216667 | AY33: =VLOOKUP($B33,'Recursos Humanos'!$B$88:$H$92,5,0) -> 2.2216667 | ... BC33: =VLOOKUP($B33,'Recursos Humanos'!$B$88:$H$92,5,0) -> 2.2216667 | BD33: =VLOOKUP($B33,'Recursos Humanos'!$B$88:$H$92,6,0) -> 2.2216667 | BE33: =VLOOKUP($B33,'Recursos Humanos'!$B$88:$H$92,6,0) -> 2.2216667 | BF33: =VLOOKUP($B33,'Recursos Humanos'!$B$88:$H$92,6,0) -> 2.2216667 | BG33: =VLOOKUP($B33,'Recursos Humanos'!$B$88:$H$92,6,0) -> 2.2216667 | BH33: =VLOOKUP($B33,'Recursos Humanos'!$B$88:$H$92,6,0) -> 2.2216667 | BI33: =VLOOKUP($B33,'Recursos Humanos'!$B$88:$H$92,6,0) -> 2.2216667 | BJ33: =VLOOKUP($B33,'Recursos Humanos'!$B$88:$H$92,6,0) -> 2.2216667 | BK33: =VLOOKUP($B33,'Recursos Humanos'!$B$88:$H$92,6,0) -> 2.2216667 | ... BO33: =VLOOKUP($B33,'Recursos Humanos'!$B$88:$H$92,6,0) -> 2.2216667 | BQ33: =SUMIF($H$2:$BC$2,BQ$2,$H33:$BC33) -> 24.438333 | BR33: =SUMIF($H$2:$BC$2,BR$2,$H33:$BC33) -> 26.66 | BS33: =SUMIF($H$2:$BC$2,BS$2,$H33:$BC33) -> 26.66 | BT33: =SUMIF($H$2:$BO$2,BT$2,$H33:$BO33) -> 26.66 | BU33: =SUMIF($H$2:$BO$2,BU$2,$H33:$BO33) -> 26.66 | BW33: =AVERAGE(BQ33:BT33) -> 26.104583 | CA33: =BQ33/SUM($BQ$34,$BR$34,$BS$34,$BT$34) -> 9.3724541e-05 | CB33: =BR33/SUM($BQ$34,$BR$34,$BS$34,$BT$34) -> 0.00010224495 | CC33: =BS33/SUM($BQ$34,$BR$34,$BS$34,$BT$34) -> 0.00010224495 | CD33: =BT33/SUM($BQ$34,$BR$34,$BS$34,$BT$34) -> 0.00010224495 | CE33: =BU33/SUM($BQ$34,$BR$34,$BS$34,$BT$34) -> 0.00010224495 | CG33: =BW33/BW5 -> 2.5167619e-05
B34: (-) Folha de Pagamento | H34: =SUM(H31:H33) -> 0 | I34: =SUM(I31:I33) -> 5547.795 | J34: =SUM(J31:J33) -> 5547.795 | K34: =SUM(K31:K33) -> 5547.795 | L34: =SUM(L31:L33) -> 5547.795 | M34: =SUM(M31:M33) -> 5547.795 | N34: =SUM(N31:N33) -> 5547.795 | O34: =SUM(O31:O33) -> 5547.795 | ... BO34: =SUM(BO31:BO33) -> 5547.795 | BQ34: =SUMIF($H$2:$BC$2,BQ$2,$H34:$BC34) -> 61025.745 | BR34: =SUMIF($H$2:$BC$2,BR$2,$H34:$BC34) -> 66573.54 | BS34: =SUMIF($H$2:$BC$2,BS$2,$H34:$BC34) -> 66573.54 | BT34: =SUMIF($H$2:$BO$2,BT$2,$H34:$BO34) -> 66573.54 | BU34: =SUMIF($H$2:$BO$2,BU$2,$H34:$BO34) -> 66573.54 | BW34: =AVERAGE(BQ34:BU34) -> 65463.981 | CA34: =BQ34/SUM($BQ$34,$BR$34,$BS$34,$BT$34,$BU$34) -> 0.18644068 | CB34: =BR34/SUM($BQ$34,$BR$34,$BS$34,$BT$34,$BU$34) -> 0.20338983 | CC34: =BS34/SUM($BQ$34,$BR$34,$BS$34,$BT$34,$BU$34) -> 0.20338983 | CD34: =BT34/SUM($BQ$34,$BR$34,$BS$34,$BT$34,$BU$34) -> 0.20338983 | CE34: =BU34/SUM($BQ$34,$BR$34,$BS$34,$BT$34,$BU$34) -> 0.20338983 | CG34: =BW34/BW5 -> 0.0631143
B36: ='Despesas Mensais'!B5 -> Ocupação
B37: ='Despesas Mensais'!B6 -> Aluguel XX m² | H37: 0 | I37: =IF(Premissas!$H$107="Receitas_3",0,VLOOKUP($B37,'Despesas Mensais'!$B$4:$G$40,VLOOKUP(I$2,'Despesas Mensais'!$B$46:$D$50,3,0),0)) -> 0 | J37: =IF(Premissas!$H$107="Receitas_3",0,VLOOKUP($B37,'Despesas Mensais'!$B$4:$G$40,VLOOKUP(J$2,'Despesas Mensais'!$B$46:$D$50,3,0),0)) -> 0 | K37: =VLOOKUP($B37,'Despesas Mensais'!$B$4:$G$40,VLOOKUP(K$2,'Despesas Mensais'!$B$46:$D$50,3,0),0) -> 0 | L37: =VLOOKUP($B37,'Despesas Mensais'!$B$4:$G$40,VLOOKUP(L$2,'Despesas Mensais'!$B$46:$D$50,3,0),0) -> 0 | M37: =VLOOKUP($B37,'Despesas Mensais'!$B$4:$G$40,VLOOKUP(M$2,'Despesas Mensais'!$B$46:$D$50,3,0),0) -> 0 | N37: =VLOOKUP($B37,'Despesas Mensais'!$B$4:$G$40,VLOOKUP(N$2,'Despesas Mensais'!$B$46:$D$50,3,0),0) -> 0 | O37: =VLOOKUP($B37,'Despesas Mensais'!$B$4:$G$40,VLOOKUP(O$2,'Despesas Mensais'!$B$46:$D$50,3,0),0) -> 0 | P37: =VLOOKUP($B37,'Despesas Mensais'!$B$4:$G$40,VLOOKUP(P$2,'Despesas Mensais'!$B$46:$D$50,3,0),0) -> 0 | Q37: =VLOOKUP($B37,'Despesas Mensais'!$B$4:$G$40,VLOOKUP(Q$2,'Despesas Mensais'!$B$46:$D$50,3,0),0) -> 0 | R37: =VLOOKUP($B37,'Despesas Mensais'!$B$4:$G$40,VLOOKUP(R$2,'Despesas Mensais'!$B$46:$D$50,3,0),0) -> 0 | ... BC37: =VLOOKUP($B37,'Despesas Mensais'!$B$4:$G$40,VLOOKUP(BC$2,'Despesas Mensais'!$B$46:$D$50,3,0),0) -> 0 | BD37: =VLOOKUP($B37,'Despesas Mensais'!$B$4:$H$40,VLOOKUP(BD$2,'Despesas Mensais'!$B$46:$D$50,3,0),0) -> 0 | BE37: =VLOOKUP($B37,'Despesas Mensais'!$B$4:$H$40,VLOOKUP(BE$2,'Despesas Mensais'!$B$46:$D$50,3,0),0) -> 0 | BF37: =VLOOKUP($B37,'Despesas Mensais'!$B$4:$H$40,VLOOKUP(BF$2,'Despesas Mensais'!$B$46:$D$50,3,0),0) -> 0 | BG37: =VLOOKUP($B37,'Despesas Mensais'!$B$4:$H$40,VLOOKUP(BG$2,'Despesas Mensais'!$B$46:$D$50,3,0),0) -> 0 | BH37: =VLOOKUP($B37,'Despesas Mensais'!$B$4:$H$40,VLOOKUP(BH$2,'Despesas Mensais'!$B$46:$D$50,3,0),0) -> 0 | BI37: =VLOOKUP($B37,'Despesas Mensais'!$B$4:$H$40,VLOOKUP(BI$2,'Despesas Mensais'!$B$46:$D$50,3,0),0) -> 0 | BJ37: =VLOOKUP($B37,'Despesas Mensais'!$B$4:$H$40,VLOOKUP(BJ$2,'Despesas Mensais'!$B$46:$D$50,3,0),0) -> 0 | BK37: =VLOOKUP($B37,'Despesas Mensais'!$B$4:$H$40,VLOOKUP(BK$2,'Despesas Mensais'!$B$46:$D$50,3,0),0) -> 0 | ... BO37: =VLOOKUP($B37,'Despesas Mensais'!$B$4:$H$40,VLOOKUP(BO$2,'Despesas Mensais'!$B$46:$D$50,3,0),0) -> 0 | BQ37: =SUMIF($H$2:$BC$2,BQ$2,$H37:$BC37) -> 0 | BR37: =SUMIF($H$2:$BC$2,BR$2,$H37:$BC37) -> 0 | BS37: =SUMIF($H$2:$BC$2,BS$2,$H37:$BC37) -> 0 | BT37: =SUMIF($H$2:$BO$2,BT$2,$H37:$BO37) -> 0 | BU37: =SUMIF($H$2:$BO$2,BU$2,$H37:$BO37) -> 0 | BW37: =AVERAGE(BQ37:BT37) -> 0 | CA37: =BQ37/SUM($BQ$70,$BR$70,$BS$70,$BT$70) -> 0 | CB37: =BR37/SUM($BQ$70,$BR$70,$BS$70,$BT$70) -> 0 | CC37: =BS37/SUM($BQ$70,$BR$70,$BS$70,$BT$70) -> 0 | CD37: =BT37/SUM($BQ$70,$BR$70,$BS$70,$BT$70) -> 0 | CE37: =BU37/SUM($BQ$70,$BR$70,$BS$70,$BT$70) -> 0 | CG37: =BW37/BW5 -> 0
B38: ='Despesas Mensais'!B7 -> IPTU | H38: 0 | I38: =IF(Premissas!$H$107="Receitas_3",0,VLOOKUP($B38,'Despesas Mensais'!$B$4:$G$40,VLOOKUP(I$2,'Despesas Mensais'!$B$46:$D$50,3,0),0)) -> 0 | J38: =IF(Premissas!$H$107="Receitas_3",0,VLOOKUP($B38,'Despesas Mensais'!$B$4:$G$40,VLOOKUP(J$2,'Despesas Mensais'!$B$46:$D$50,3,0),0)) -> 0 | K38: =VLOOKUP($B38,'Despesas Mensais'!$B$4:$G$40,VLOOKUP(K$2,'Despesas Mensais'!$B$46:$D$50,3,0),0) -> 0 | L38: =VLOOKUP($B38,'Despesas Mensais'!$B$4:$G$40,VLOOKUP(L$2,'Despesas Mensais'!$B$46:$D$50,3,0),0) -> 0 | M38: =VLOOKUP($B38,'Despesas Mensais'!$B$4:$G$40,VLOOKUP(M$2,'Despesas Mensais'!$B$46:$D$50,3,0),0) -> 0 | N38: =VLOOKUP($B38,'Despesas Mensais'!$B$4:$G$40,VLOOKUP(N$2,'Despesas Mensais'!$B$46:$D$50,3,0),0) -> 0 | O38: =VLOOKUP($B38,'Despesas Mensais'!$B$4:$G$40,VLOOKUP(O$2,'Despesas Mensais'!$B$46:$D$50,3,0),0) -> 0 | P38: =VLOOKUP($B38,'Despesas Mensais'!$B$4:$G$40,VLOOKUP(P$2,'Despesas Mensais'!$B$46:$D$50,3,0),0) -> 0 | Q38: =VLOOKUP($B38,'Despesas Mensais'!$B$4:$G$40,VLOOKUP(Q$2,'Despesas Mensais'!$B$46:$D$50,3,0),0) -> 0 | R38: =VLOOKUP($B38,'Despesas Mensais'!$B$4:$G$40,VLOOKUP(R$2,'Despesas Mensais'!$B$46:$D$50,3,0),0) -> 0 | ... BC38: =VLOOKUP($B38,'Despesas Mensais'!$B$4:$G$40,VLOOKUP(BC$2,'Despesas Mensais'!$B$46:$D$50,3,0),0) -> 0 | BD38: =VLOOKUP($B38,'Despesas Mensais'!$B$4:$H$40,VLOOKUP(BD$2,'Despesas Mensais'!$B$46:$D$50,3,0),0) -> 0 | BE38: =VLOOKUP($B38,'Despesas Mensais'!$B$4:$H$40,VLOOKUP(BE$2,'Despesas Mensais'!$B$46:$D$50,3,0),0) -> 0 | BF38: =VLOOKUP($B38,'Despesas Mensais'!$B$4:$H$40,VLOOKUP(BF$2,'Despesas Mensais'!$B$46:$D$50,3,0),0) -> 0 | BG38: =VLOOKUP($B38,'Despesas Mensais'!$B$4:$H$40,VLOOKUP(BG$2,'Despesas Mensais'!$B$46:$D$50,3,0),0) -> 0 | BH38: =VLOOKUP($B38,'Despesas Mensais'!$B$4:$H$40,VLOOKUP(BH$2,'Despesas Mensais'!$B$46:$D$50,3,0),0) -> 0 | BI38: =VLOOKUP($B38,'Despesas Mensais'!$B$4:$H$40,VLOOKUP(BI$2,'Despesas Mensais'!$B$46:$D$50,3,0),0) -> 0 | BJ38: =VLOOKUP($B38,'Despesas Mensais'!$B$4:$H$40,VLOOKUP(BJ$2,'Despesas Mensais'!$B$46:$D$50,3,0),0) -> 0 | BK38: =VLOOKUP($B38,'Despesas Mensais'!$B$4:$H$40,VLOOKUP(BK$2,'Despesas Mensais'!$B$46:$D$50,3,0),0) -> 0 | ... BO38: =VLOOKUP($B38,'Despesas Mensais'!$B$4:$H$40,VLOOKUP(BO$2,'Despesas Mensais'!$B$46:$D$50,3,0),0) -> 0 | BQ38: =SUMIF($H$2:$BC$2,BQ$2,$H38:$BC38) -> 0 | BR38: =SUMIF($H$2:$BC$2,BR$2,$H38:$BC38) -> 0 | BS38: =SUMIF($H$2:$BC$2,BS$2,$H38:$BC38) -> 0 | BT38: =SUMIF($H$2:$BO$2,BT$2,$H38:$BO38) -> 0 | BU38: =SUMIF($H$2:$BO$2,BU$2,$H38:$BO38) -> 0 | BW38: =AVERAGE(BQ38:BT38) -> 0 | CA38: =BQ38/SUM($BQ$70,$BR$70,$BS$70,$BT$70) -> 0 | CB38: =BR38/SUM($BQ$70,$BR$70,$BS$70,$BT$70) -> 0 | CC38: =BS38/SUM($BQ$70,$BR$70,$BS$70,$BT$70) -> 0 | CD38: =BT38/SUM($BQ$70,$BR$70,$BS$70,$BT$70) -> 0 | CE38: =BU38/SUM($BQ$70,$BR$70,$BS$70,$BT$70) -> 0 | CG38: =BW38/BW5 -> 0
B39: ='Despesas Mensais'!B8 -> Condomínio | H39: 0 | I39: =IF(Premissas!$H$107="Receitas_3",0,VLOOKUP($B39,'Despesas Mensais'!$B$4:$G$40,VLOOKUP(I$2,'Despesas Mensais'!$B$46:$D$50,3,0),0)) -> 0 | J39: =IF(Premissas!$H$107="Receitas_3",0,VLOOKUP($B39,'Despesas Mensais'!$B$4:$G$40,VLOOKUP(J$2,'Despesas Mensais'!$B$46:$D$50,3,0),0)) -> 0 | K39: =VLOOKUP($B39,'Despesas Mensais'!$B$4:$G$40,VLOOKUP(K$2,'Despesas Mensais'!$B$46:$D$50,3,0),0) -> 0 | L39: =VLOOKUP($B39,'Despesas Mensais'!$B$4:$G$40,VLOOKUP(L$2,'Despesas Mensais'!$B$46:$D$50,3,0),0) -> 0 | M39: =VLOOKUP($B39,'Despesas Mensais'!$B$4:$G$40,VLOOKUP(M$2,'Despesas Mensais'!$B$46:$D$50,3,0),0) -> 0 | N39: =VLOOKUP($B39,'Despesas Mensais'!$B$4:$G$40,VLOOKUP(N$2,'Despesas Mensais'!$B$46:$D$50,3,0),0) -> 0 | O39: =VLOOKUP($B39,'Despesas Mensais'!$B$4:$G$40,VLOOKUP(O$2,'Despesas Mensais'!$B$46:$D$50,3,0),0) -> 0 | P39: =VLOOKUP($B39,'Despesas Mensais'!$B$4:$G$40,VLOOKUP(P$2,'Despesas Mensais'!$B$46:$D$50,3,0),0) -> 0 | Q39: =VLOOKUP($B39,'Despesas Mensais'!$B$4:$G$40,VLOOKUP(Q$2,'Despesas Mensais'!$B$46:$D$50,3,0),0) -> 0 | R39: =VLOOKUP($B39,'Despesas Mensais'!$B$4:$G$40,VLOOKUP(R$2,'Despesas Mensais'!$B$46:$D$50,3,0),0) -> 0 | ... BC39: =VLOOKUP($B39,'Despesas Mensais'!$B$4:$G$40,VLOOKUP(BC$2,'Despesas Mensais'!$B$46:$D$50,3,0),0) -> 0 | BD39: =VLOOKUP($B39,'Despesas Mensais'!$B$4:$H$40,VLOOKUP(BD$2,'Despesas Mensais'!$B$46:$D$50,3,0),0) -> 0 | BE39: =VLOOKUP($B39,'Despesas Mensais'!$B$4:$H$40,VLOOKUP(BE$2,'Despesas Mensais'!$B$46:$D$50,3,0),0) -> 0 | BF39: =VLOOKUP($B39,'Despesas Mensais'!$B$4:$H$40,VLOOKUP(BF$2,'Despesas Mensais'!$B$46:$D$50,3,0),0) -> 0 | BG39: =VLOOKUP($B39,'Despesas Mensais'!$B$4:$H$40,VLOOKUP(BG$2,'Despesas Mensais'!$B$46:$D$50,3,0),0) -> 0 | BH39: =VLOOKUP($B39,'Despesas Mensais'!$B$4:$H$40,VLOOKUP(BH$2,'Despesas Mensais'!$B$46:$D$50,3,0),0) -> 0 | BI39: =VLOOKUP($B39,'Despesas Mensais'!$B$4:$H$40,VLOOKUP(BI$2,'Despesas Mensais'!$B$46:$D$50,3,0),0) -> 0 | BJ39: =VLOOKUP($B39,'Despesas Mensais'!$B$4:$H$40,VLOOKUP(BJ$2,'Despesas Mensais'!$B$46:$D$50,3,0),0) -> 0 | BK39: =VLOOKUP($B39,'Despesas Mensais'!$B$4:$H$40,VLOOKUP(BK$2,'Despesas Mensais'!$B$46:$D$50,3,0),0) -> 0 | ... BO39: =VLOOKUP($B39,'Despesas Mensais'!$B$4:$H$40,VLOOKUP(BO$2,'Despesas Mensais'!$B$46:$D$50,3,0),0) -> 0 | BQ39: =SUMIF($H$2:$BC$2,BQ$2,$H39:$BC39) -> 0 | BR39: =SUMIF($H$2:$BC$2,BR$2,$H39:$BC39) -> 0 | BS39: =SUMIF($H$2:$BC$2,BS$2,$H39:$BC39) -> 0 | BT39: =SUMIF($H$2:$BO$2,BT$2,$H39:$BO39) -> 0 | BU39: =SUMIF($H$2:$BO$2,BU$2,$H39:$BO39) -> 0 | BW39: =AVERAGE(BQ39:BT39) -> 0 | CA39: =BQ39/SUM($BQ$70,$BR$70,$BS$70,$BT$70) -> 0 | CB39: =BR39/SUM($BQ$70,$BR$70,$BS$70,$BT$70) -> 0 | CC39: =BS39/SUM($BQ$70,$BR$70,$BS$70,$BT$70) -> 0 | CD39: =BT39/SUM($BQ$70,$BR$70,$BS$70,$BT$70) -> 0 | CE39: =BU39/SUM($BQ$70,$BR$70,$BS$70,$BT$70) -> 0 | CG39: =BW39/BW5 -> 0
B40: ='Despesas Mensais'!B9 -> Utilidades | BD40: =VLOOKUP($B40,'Despesas Mensais'!$B$4:$H$40,VLOOKUP(BD$2,'Despesas Mensais'!$B$46:$D$50,3,0),0) -> 0 | BE40: =VLOOKUP($B40,'Despesas Mensais'!$B$4:$H$40,VLOOKUP(BE$2,'Despesas Mensais'!$B$46:$D$50,3,0),0) -> 0 | BF40: =VLOOKUP($B40,'Despesas Mensais'!$B$4:$H$40,VLOOKUP(BF$2,'Despesas Mensais'!$B$46:$D$50,3,0),0) -> 0 | BG40: =VLOOKUP($B40,'Despesas Mensais'!$B$4:$H$40,VLOOKUP(BG$2,'Despesas Mensais'!$B$46:$D$50,3,0),0) -> 0 | BH40: =VLOOKUP($B40,'Despesas Mensais'!$B$4:$H$40,VLOOKUP(BH$2,'Despesas Mensais'!$B$46:$D$50,3,0),0) -> 0 | BI40: =VLOOKUP($B40,'Despesas Mensais'!$B$4:$H$40,VLOOKUP(BI$2,'Despesas Mensais'!$B$46:$D$50,3,0),0) -> 0 | BJ40: =VLOOKUP($B40,'Despesas Mensais'!$B$4:$H$40,VLOOKUP(BJ$2,'Despesas Mensais'!$B$46:$D$50,3,0),0) -> 0 | BK40: =VLOOKUP($B40,'Despesas Mensais'!$B$4:$H$40,VLOOKUP(BK$2,'Despesas Mensais'!$B$46:$D$50,3,0),0) -> 0 | ... BO40: =VLOOKUP($B40,'Despesas Mensais'!$B$4:$H$40,VLOOKUP(BO$2,'Despesas Mensais'!$B$46:$D$50,3,0),0) -> 0 | BT40: =SUMIF($H$2:$BO$2,BT$2,$H40:$BO40) -> 0 | BU40: =SUMIF($H$2:$BO$2,BU$2,$H40:$BO40) -> 0 | BW40: =AVERAGE(BQ40:BT40) -> 0
B41: ='Despesas Mensais'!B10 -> Água | H41: 0 | I41: =IF(Premissas!$H$107="Receitas_3",0,VLOOKUP($B41,'Despesas Mensais'!$B$4:$G$40,VLOOKUP(I$2,'Despesas Mensais'!$B$46:$D$50,3,0),0)) -> 0 | J41: =IF(Premissas!$H$107="Receitas_3",0,VLOOKUP($B41,'Despesas Mensais'!$B$4:$G$40,VLOOKUP(J$2,'Despesas Mensais'!$B$46:$D$50,3,0),0)) -> 0 | K41: =VLOOKUP($B41,'Despesas Mensais'!$B$4:$G$40,VLOOKUP(K$2,'Despesas Mensais'!$B$46:$D$50,3,0),0) -> 0 | L41: =VLOOKUP($B41,'Despesas Mensais'!$B$4:$G$40,VLOOKUP(L$2,'Despesas Mensais'!$B$46:$D$50,3,0),0) -> 0 | M41: =VLOOKUP($B41,'Despesas Mensais'!$B$4:$G$40,VLOOKUP(M$2,'Despesas Mensais'!$B$46:$D$50,3,0),0) -> 0 | N41: =VLOOKUP($B41,'Despesas Mensais'!$B$4:$G$40,VLOOKUP(N$2,'Despesas Mensais'!$B$46:$D$50,3,0),0) -> 0 | O41: =VLOOKUP($B41,'Despesas Mensais'!$B$4:$G$40,VLOOKUP(O$2,'Despesas Mensais'!$B$46:$D$50,3,0),0) -> 0 | P41: =VLOOKUP($B41,'Despesas Mensais'!$B$4:$G$40,VLOOKUP(P$2,'Despesas Mensais'!$B$46:$D$50,3,0),0) -> 0 | Q41: =VLOOKUP($B41,'Despesas Mensais'!$B$4:$G$40,VLOOKUP(Q$2,'Despesas Mensais'!$B$46:$D$50,3,0),0) -> 0 | R41: =VLOOKUP($B41,'Despesas Mensais'!$B$4:$G$40,VLOOKUP(R$2,'Despesas Mensais'!$B$46:$D$50,3,0),0) -> 0 | ... BC41: =VLOOKUP($B41,'Despesas Mensais'!$B$4:$G$40,VLOOKUP(BC$2,'Despesas Mensais'!$B$46:$D$50,3,0),0) -> 0 | BD41: =VLOOKUP($B41,'Despesas Mensais'!$B$4:$H$40,VLOOKUP(BD$2,'Despesas Mensais'!$B$46:$D$50,3,0),0) -> 0 | BE41: =VLOOKUP($B41,'Despesas Mensais'!$B$4:$H$40,VLOOKUP(BE$2,'Despesas Mensais'!$B$46:$D$50,3,0),0) -> 0 | BF41: =VLOOKUP($B41,'Despesas Mensais'!$B$4:$H$40,VLOOKUP(BF$2,'Despesas Mensais'!$B$46:$D$50,3,0),0) -> 0 | BG41: =VLOOKUP($B41,'Despesas Mensais'!$B$4:$H$40,VLOOKUP(BG$2,'Despesas Mensais'!$B$46:$D$50,3,0),0) -> 0 | BH41: =VLOOKUP($B41,'Despesas Mensais'!$B$4:$H$40,VLOOKUP(BH$2,'Despesas Mensais'!$B$46:$D$50,3,0),0) -> 0 | BI41: =VLOOKUP($B41,'Despesas Mensais'!$B$4:$H$40,VLOOKUP(BI$2,'Despesas Mensais'!$B$46:$D$50,3,0),0) -> 0 | BJ41: =VLOOKUP($B41,'Despesas Mensais'!$B$4:$H$40,VLOOKUP(BJ$2,'Despesas Mensais'!$B$46:$D$50,3,0),0) -> 0 | BK41: =VLOOKUP($B41,'Despesas Mensais'!$B$4:$H$40,VLOOKUP(BK$2,'Despesas Mensais'!$B$46:$D$50,3,0),0) -> 0 | ... BO41: =VLOOKUP($B41,'Despesas Mensais'!$B$4:$H$40,VLOOKUP(BO$2,'Despesas Mensais'!$B$46:$D$50,3,0),0) -> 0 | BQ41: =SUMIF($H$2:$BC$2,BQ$2,$H41:$BC41) -> 0 | BR41: =SUMIF($H$2:$BC$2,BR$2,$H41:$BC41) -> 0 | BS41: =SUMIF($H$2:$BC$2,BS$2,$H41:$BC41) -> 0 | BT41: =SUMIF($H$2:$BO$2,BT$2,$H41:$BO41) -> 0 | BU41: =SUMIF($H$2:$BO$2,BU$2,$H41:$BO41) -> 0 | BW41: =AVERAGE(BQ41:BT41) -> 0 | CA41: =BQ41/SUM($BQ$70,$BR$70,$BS$70,$BT$70) -> 0 | CB41: =BR41/SUM($BQ$70,$BR$70,$BS$70,$BT$70) -> 0 | CC41: =BS41/SUM($BQ$70,$BR$70,$BS$70,$BT$70) -> 0 | CD41: =BT41/SUM($BQ$70,$BR$70,$BS$70,$BT$70) -> 0 | CE41: =BU41/SUM($BQ$70,$BR$70,$BS$70,$BT$70) -> 0 | CG41: =BW41/BW5 -> 0
